Workbook
Name episodeCode: #REF!
Name excemail: #REF!

Sheet Sheet1
A1: product | B1: parent_episode | C1: EpisodeId | D1: episode_code | E1: StepId | F1: step_name | G1: Definition Agreed | H1: Volumes From Chill | I1: Priority
A2: Motor | B2: ACQUISITION_JOURNEY | C2: 1 | D2: MOTOR_QUOTE_JOURNEY | E2: 1 | F2: Quote initiated | I2: 1
A3: Motor | B3: ACQUISITION_JOURNEY | C3: 1 | D3: MOTOR_QUOTE_JOURNEY | E3: 2 | F3: Site landing page viewed
A4: Motor | B4: ACQUISITION_JOURNEY | C4: 1 | D4: MOTOR_QUOTE_JOURNEY | E4: 3 | F4: Quote progressed | G4: Not Sure | I4: 1
A5: Motor | B5: ACQUISITION_JOURNEY | C5: 1 | D5: MOTOR_QUOTE_JOURNEY | E5: 4 | F5: Inbound sales contact
A6: Motor | B6: ACQUISITION_JOURNEY | C6: 1 | D6: MOTOR_QUOTE_JOURNEY | E6: 5 | F6: Outbound sales callback
A7: Motor | B7: ACQUISITION_JOURNEY | C7: 1 | D7: MOTOR_QUOTE_JOURNEY | E7: 6 | F7: Web assist engagement | I7: 1
A8: Motor | B8: ACQUISITION_JOURNEY | C8: 1 | D8: MOTOR_QUOTE_JOURNEY | E8: 7 | F8: Quote abandoned
A9: Motor | B9: ACQUISITION_JOURNEY | C9: 1 | D9: MOTOR_QUOTE_JOURNEY | E9: 8 | F9: Service Retrieve | G9: Not Sure | I9: 1
A10: Motor | B10: ACQUISITION_JOURNEY | C10: 1 | D10: MOTOR_QUOTE_JOURNEY | E10: 9 | F10: XP retrieve journey triggered
A11: Motor | B11: ACQUISITION_JOURNEY | C11: 1 | D11: MOTOR_QUOTE_JOURNEY | E11: 10 | F11: Payment attempted (with friction)
A12: Motor | B12: ACQUISITION_JOURNEY | C12: 1 | D12: MOTOR_QUOTE_JOURNEY | E12: 11 | F12: Payment successful | I12: 1
A13: Motor | B13: ACQUISITION_JOURNEY | C13: 1 | D13: MOTOR_QUOTE_JOURNEY | E13: 12 | F13: Post-sale document pack sent (TOB / Proposal / Quote Breakdown)
A14: Motor | B14: ACQUISITION_JOURNEY | C14: 2 | D14: MOTOR_ACQUISITION_CALL_CENTRE | E14: 1 | F14: Inbound sales contact (no MFQ match)
A15: Motor | B15: ACQUISITION_JOURNEY | C15: 2 | D15: MOTOR_ACQUISITION_CALL_CENTRE | E15: 2 | F15: Agent quotes in Genesis | I15: 1
A16: Motor | B16: ACQUISITION_JOURNEY | C16: 2 | D16: MOTOR_ACQUISITION_CALL_CENTRE | E16: 3 | F16: Payment successful | I16: 1
A17: Motor | B17: ACQUISITION_JOURNEY | C17: 2 | D17: MOTOR_ACQUISITION_CALL_CENTRE | E17: 4 | F17: Not proceeded with
A18: Motor | B18: ACQUISITION_JOURNEY | C18: 3 | D18: MOTOR_QUOTE_RETRIEVE | E18: 1 | F18: Quote retrieved / iterated | I18: 1
A19: Motor | B19: ACQUISITION_JOURNEY | C19: 3 | D19: MOTOR_QUOTE_RETRIEVE | E19: 2 | F19: Purchase
A20: Motor | B20: ACQUISITION_JOURNEY | C20: 3 | D20: MOTOR_QUOTE_RETRIEVE | E20: 3 | F20: Abandoned / expired
A21: Motor | B21: ACQUISITION_JOURNEY | C21: 4 | D21: MOTOR_DOCUMENT_INTAKE | E21: 1 | F21: Document request issued | I21: 1
A22: Motor | B22: ACQUISITION_JOURNEY | C22: 4 | D22: MOTOR_DOCUMENT_INTAKE | E22: 2 | F22: Customer submits documents
A23: Motor | B23: ACQUISITION_JOURNEY | C23: 4 | D23: MOTOR_DOCUMENT_INTAKE | E23: 3 | F23: Documents validated
A24: Motor | B24: ACQUISITION_JOURNEY | C24: 4 | D24: MOTOR_DOCUMENT_INTAKE | E24: 4 | F24: Chase — first reminder
A25: Motor | B25: ACQUISITION_JOURNEY | C25: 4 | D25: MOTOR_DOCUMENT_INTAKE | E25: 5 | F25: Chase — escalation
A26: Motor | B26: ACQUISITION_JOURNEY | C26: 4 | D26: MOTOR_DOCUMENT_INTAKE | E26: 6 | F26: Documents received & validated | I26: 1
A27: Motor | B27: ACQUISITION_JOURNEY | C27: 4 | D27: MOTOR_DOCUMENT_INTAKE | E27: 7 | F27: Cancellation — non-receipt | I27: 1
A28: Motor | B28: ACQUISITION_JOURNEY | C28: 5 | D28: MOTOR_PAYMENT_SETUP_LOAN | E28: 1 | F28: Loan initiated with finance provider | I28: 1
A29: Motor | B29: ACQUISITION_JOURNEY | C29: 5 | D29: MOTOR_PAYMENT_SETUP_LOAN | E29: 2 | F29: Finance application link sent (SMS + email from finance provider)
A30: Motor | B30: ACQUISITION_JOURNEY | C30: 5 | D30: MOTOR_PAYMENT_SETUP_LOAN | E30: 3 | F30: Customer completes application / DD setup (provider portal)
A31: Motor | B31: ACQUISITION_JOURNEY | C31: 5 | D31: MOTOR_PAYMENT_SETUP_LOAN | E31: 4 | F31: Chase — inconsistency resolution
A32: Motor | B32: ACQUISITION_JOURNEY | C32: 5 | D32: MOTOR_PAYMENT_SETUP_LOAN | E32: 5 | F32: Payment confirmed — loan path
A33: Motor | B33: ACQUISITION_JOURNEY | C33: 5 | D33: MOTOR_PAYMENT_SETUP_LOAN | E33: 6 | F33: Switched to pay-in-full
A34: Motor | B34: ACQUISITION_JOURNEY | C34: 5 | D34: MOTOR_PAYMENT_SETUP_LOAN | E34: 7 | F34: Cancellation — loan setup failed | I34: 1
A35: Motor | B35: ACQUISITION_JOURNEY | C35: 6 | D35: MOTOR_PAYMENT_SETUP_LOAN_PC | E35: 1 | F35: Loan initiated — integrated in the quote stage | I35: 1
A36: Motor | B36: ACQUISITION_JOURNEY | C36: 6 | D36: MOTOR_PAYMENT_SETUP_LOAN_PC | E36: 2 | F36: Finance application link sent (SMS + email from Premium Credit)
A37: Motor | B37: ACQUISITION_JOURNEY | C37: 6 | D37: MOTOR_PAYMENT_SETUP_LOAN_PC | E37: 3 | F37: Customer completes self-service application (docs uploaded in PC app)
A38: Motor | B38: ACQUISITION_JOURNEY | C38: 6 | D38: MOTOR_PAYMENT_SETUP_LOAN_PC | E38: 4 | F38: Document chase (provider chase + Chill chase)
A39: Motor | B39: ACQUISITION_JOURNEY | C39: 6 | D39: MOTOR_PAYMENT_SETUP_LOAN_PC | E39: 5 | F39: Payment confirmed — loan path
A40: Motor | B40: ACQUISITION_JOURNEY | C40: 6 | D40: MOTOR_PAYMENT_SETUP_LOAN_PC | E40: 6 | F40: Switched to pay-in-full
A41: Motor | B41: ACQUISITION_JOURNEY | C41: 6 | D41: MOTOR_PAYMENT_SETUP_LOAN_PC | E41: 7 | F41: Cancellation — loan setup failed | I41: 1
A42: Motor | B42: ACQUISITION_JOURNEY | C42: 7 | D42: MOTOR_CERT_AND_DISC | E42: 1 | F42: Cert & Disc dispatched | I42: 1
A43: Motor | B43: ACQUISITION_JOURNEY | C43: 7 | D43: MOTOR_CERT_AND_DISC | E43: 2 | F43: Document pack dispatched
A44: Motor | B44: ACQUISITION_JOURNEY | C44: 7 | D44: MOTOR_CERT_AND_DISC | E44: 3 | F44: Customer receipt — implicit
A45: Motor | B45: ACQUISITION_JOURNEY | C45: 7 | D45: MOTOR_CERT_AND_DISC | E45: 4 | F45: Non-arrival chase (inbound)
A46: Motor | B46: ACQUISITION_JOURNEY | C46: 7 | D46: MOTOR_CERT_AND_DISC | E46: 5 | F46: Replacement requested
A47: Motor | B47: ACQUISITION_JOURNEY | C47: 8 | D47: MOTOR_ADDITIONAL_RETURN_PREMIUM | E47: 1 | F47: Risk validation flags discrepancy
A48: Motor | B48: ACQUISITION_JOURNEY | C48: 8 | D48: MOTOR_ADDITIONAL_RETURN_PREMIUM | E48: 2 | F48: Customer notified of repricing
A49: Motor | B49: ACQUISITION_JOURNEY | C49: 8 | D49: MOTOR_ADDITIONAL_RETURN_PREMIUM | E49: 3 | F49: Customer response (AP stands — cannot be declined)
A50: Motor | B50: ACQUISITION_JOURNEY | C50: 8 | D50: MOTOR_ADDITIONAL_RETURN_PREMIUM | E50: 4 | F50: Additional premium paid | I50: 1
A51: Motor | B51: ACQUISITION_JOURNEY | C51: 8 | D51: MOTOR_ADDITIONAL_RETURN_PREMIUM | E51: 5 | F51: Return premium reversed (insurer-approved — rare, not a refund)
A52: Motor | B52: ACQUISITION_JOURNEY | C52: 8 | D52: MOTOR_ADDITIONAL_RETURN_PREMIUM | E52: 6 | F52: Cancellation — AP unresolved (any refund is the post-cancellation balance / time-on-risk) | I52: 1
A53: Motor | B53: RENEWALS | C53: 9 | D53: MOTOR_RENEWAL_ONLINE | E53: 1 | F53: Renewal window opens (T-40)
A54: Motor | B54: RENEWALS | C54: 9 | D54: MOTOR_RENEWAL_ONLINE | E54: 2 | F54: CPC notification issued | I54: 1
A55: Motor | B55: RENEWALS | C55: 9 | D55: MOTOR_RENEWAL_ONLINE | E55: 3 | F55: Renewal offer presented (T-30)
A56: Motor | B56: RENEWALS | C56: 9 | D56: MOTOR_RENEWAL_ONLINE | E56: 4 | F56: Renewal invitation email sent | I56: 1
A57: Motor | B57: RENEWALS | C57: 9 | D57: MOTOR_RENEWAL_ONLINE | E57: 5 | F57: Customer logs in to portal
A58: Motor | B58: RENEWALS | C58: 9 | D58: MOTOR_RENEWAL_ONLINE | E58: 6 | F58: Customer retrieves / re-quotes online
A59: Motor | B59: RENEWALS | C59: 9 | D59: MOTOR_RENEWAL_ONLINE | E59: 7 | F59: Renewal reminder / chase
A60: Motor | B60: RENEWALS | C60: 9 | D60: MOTOR_RENEWAL_ONLINE | E60: 8 | F60: Renewal accepted / payment taken | I60: 1
A61: Motor | B61: RENEWALS | C61: 9 | D61: MOTOR_RENEWAL_ONLINE | E61: 9 | F61: Renewal processed / policy continued
A62: Motor | B62: RENEWALS | C62: 9 | D62: MOTOR_RENEWAL_ONLINE | E62: 10 | F62: Lapsed (T+7)
A63: Motor | B63: RENEWALS | C63: 10 | D63: MOTOR_RENEWAL_CALL_CENTRE | E63: 1 | F63: Renewal window opens (T-40)
A64: Motor | B64: RENEWALS | C64: 10 | D64: MOTOR_RENEWAL_CALL_CENTRE | E64: 2 | F64: Renewal offer presented (T-30)
A65: Motor | B65: RENEWALS | C65: 10 | D65: MOTOR_RENEWAL_CALL_CENTRE | E65: 3 | F65: Renewal invitation issued
A66: Motor | B66: RENEWALS | C66: 10 | D66: MOTOR_RENEWAL_CALL_CENTRE | E66: 4 | F66: Customer calls Chill | I66: 1
A67: Motor | B67: RENEWALS | C67: 10 | D67: MOTOR_RENEWAL_CALL_CENTRE | E67: 5 | F67: Agent re-quotes / discusses
A68: Motor | B68: RENEWALS | C68: 10 | D68: MOTOR_RENEWAL_CALL_CENTRE | E68: 6 | F68: Renewal reminder / chase
A69: Motor | B69: RENEWALS | C69: 10 | D69: MOTOR_RENEWAL_CALL_CENTRE | E69: 7 | F69: Renewal accepted / payment taken
A70: Motor | B70: RENEWALS | C70: 10 | D70: MOTOR_RENEWAL_CALL_CENTRE | E70: 8 | F70: Renewal processed / policy continued
A71: Motor | B71: RENEWALS | C71: 10 | D71: MOTOR_RENEWAL_CALL_CENTRE | E71: 9 | F71: Lapsed (T+7)
A72: Motor | B72: RENEWALS | C72: 11 | D72: MOTOR_RENEWAL_DOCUMENTS | E72: 1 | F72: Renewal accepted / payment taken | I72: 1
A73: Motor | B73: RENEWALS | C73: 11 | D73: MOTOR_RENEWAL_DOCUMENTS | E73: 2 | F73: Renewal cover letter / suitability sent
A74: Motor | B74: RENEWALS | C74: 11 | D74: MOTOR_RENEWAL_DOCUMENTS | E74: 3 | F74: Renewal cert & disc dispatched
A75: Motor | B75: RENEWALS | C75: 12 | D75: MOTOR_RENEWAL_PAYMENT | E75: 1 | F75: Renewal accepted (rollover trigger)
A76: Motor | B76: RENEWALS | C76: 12 | D76: MOTOR_RENEWAL_PAYMENT | E76: 2 | F76: Pay-in-full path | I76: 1
A77: Motor | B77: RENEWALS | C77: 12 | D77: MOTOR_RENEWAL_PAYMENT | E77: 3 | F77: Loan rollover path — DD continues
A78: Motor | B78: RENEWALS | C78: 12 | D78: MOTOR_RENEWAL_PAYMENT | E78: 4 | F78: Loan re-setup path (new agreement)
A79: Motor | B79: RENEWALS | C79: 12 | D79: MOTOR_RENEWAL_PAYMENT | E79: 5 | F79: Payment friction (failed / abandoned)
A80: Motor | B80: RENEWALS | C80: 12 | D80: MOTOR_RENEWAL_PAYMENT | E80: 6 | F80: Cancellation — payment not resolved
A81: Motor | B81: RENEWALS | C81: 13 | D81: MOTOR_RENEWAL_PAYMENT_RESETUP | E81: 1 | F81: New loan agreement initiated | I81: 1
A82: Motor | B82: RENEWALS | C82: 13 | D82: MOTOR_RENEWAL_PAYMENT_RESETUP | E82: 2 | F82: KYC / mandate sent
A83: Motor | B83: RENEWALS | C83: 13 | D83: MOTOR_RENEWAL_PAYMENT_RESETUP | E83: 3 | F83: Customer signs new mandate
A84: Motor | B84: RENEWALS | C84: 13 | D84: MOTOR_RENEWAL_PAYMENT_RESETUP | E84: 4 | F84: Joint chase (Chill + finance provider)
A85: Motor | B85: RENEWALS | C85: 13 | D85: MOTOR_RENEWAL_PAYMENT_RESETUP | E85: 5 | F85: Payment confirmed (new agreement live) | I85: 1
A86: Motor | B86: RENEWALS | C86: 13 | D86: MOTOR_RENEWAL_PAYMENT_RESETUP | E86: 6 | F86: Cancellation — re-setup failed
A87: Motor | B87: IN_LIFE_SERVICE | C87: 14 | D87: MOTOR_MTA_PAYMENT_SCHEDULE | E87: 1 | F87: Payment schedule change request — to Chill (call) or direct to the finance provider
A88: Motor | B88: IN_LIFE_SERVICE | C88: 14 | D88: MOTOR_MTA_PAYMENT_SCHEDULE | E88: 2 | F88: Schedule change processed by finance provider
A89: Motor | B89: IN_LIFE_SERVICE | C89: 15 | D89: MOTOR_MTA_NAMED_DRIVER | E89: 1 | F89: Customer calls Chill — driver addition/removal request
A90: Motor | B90: IN_LIFE_SERVICE | C90: 15 | D90: MOTOR_MTA_NAMED_DRIVER | E90: 2 | F90: Agent quotes cost / refund + fee
A91: Motor | B91: IN_LIFE_SERVICE | C91: 15 | D91: MOTOR_MTA_NAMED_DRIVER | E91: 3 | F91: Customer accepts (proceeds)
A92: Motor | B92: IN_LIFE_SERVICE | C92: 15 | D92: MOTOR_MTA_NAMED_DRIVER | E92: 4 | F92: Licence document upload — foreign/EU licence only (exception)
A93: Motor | B93: IN_LIFE_SERVICE | C93: 15 | D93: MOTOR_MTA_NAMED_DRIVER | E93: 5 | F93: Payment taken | I93: 1
A94: Motor | B94: IN_LIFE_SERVICE | C94: 15 | D94: MOTOR_MTA_NAMED_DRIVER | E94: 6 | F94: MTA processed / cert reissued
A95: Motor | B95: IN_LIFE_SERVICE | C95: 15 | D95: MOTOR_MTA_NAMED_DRIVER | E95: 7 | F95: Cancellation — declined / NPW
A96: Motor | B96: IN_LIFE_SERVICE | C96: 16 | D96: MOTOR_MTA_VEHICLE_CHANGE | E96: 1 | F96: Customer calls Chill — vehicle change request
A97: Motor | B97: IN_LIFE_SERVICE | C97: 16 | D97: MOTOR_MTA_VEHICLE_CHANGE | E97: 2 | F97: Agent quotes new premium + fee
A98: Motor | B98: IN_LIFE_SERVICE | C98: 16 | D98: MOTOR_MTA_VEHICLE_CHANGE | E98: 3 | F98: Customer accepts
A99: Motor | B99: IN_LIFE_SERVICE | C99: 16 | D99: MOTOR_MTA_VEHICLE_CHANGE | E99: 4 | F99: Payment taken | I99: 1
A100: Motor | B100: IN_LIFE_SERVICE | C100: 16 | D100: MOTOR_MTA_VEHICLE_CHANGE | E100: 5 | F100: MTA processed / new cert dispatched
...

Sheet Summary
B2: Product | C2: Journey | D2: Priority Data Points | M2: Other Data Points | N2: Total Data Points | O2: Total Fabric Coverage | P2: Total Fabric Not Provided | Q2: Total Fabric Coverage % | R2: Is Data / Logic Available / accessible?
D3: Priority Total | E3: Reconciled | F3: Reconciled within acceptable variance | G3: Under Investigation | H3: No report data supplied | I3: No data Available | J3: Available in IGP (Fabric) | K3: % Coverage Missing in Fabric | L3: % Coverage in IGP (Fabric) | R3: Yes | S3: No | T3: Not a Data Point
B5: Motor | C5: Acquisition | D5: =COUNTIFS('Reconciliation Request'!$A$2:$A$755,Summary!$B5,'Reconciliation Request'!$B$2:$B$755,Summary!$C5,'Reconciliation Request'!$F$2:$F$755,"=1") -> 11 | E5: =COUNTIFS('Reconciliation Request'!$A$2:$A$755,Summary!$B5,'Reconciliation Request'!$B$2:$B$755,Summary!$C5,'Reconciliation Request'!$J$2:$J$755,Summary!E$3,'Reconciliation Request'!$F$2:$F$755,"=1") -> 3 | F5: =COUNTIFS('Reconciliation Request'!$A$2:$A$755,Summary!$B5,'Reconciliation Request'!$B$2:$B$755,Summary!$C5,'Reconciliation Request'!$J$2:$J$755,Summary!F$3,'Reconciliation Request'!$F$2:$F$755,"=1") -> 3 | G5: =COUNTIFS('Reconciliation Request'!$A$2:$A$755,Summary!$B5,'Reconciliation Request'!$B$2:$B$755,Summary!$C5,'Reconciliation Request'!$J$2:$J$755,Summary!G$3,'Reconciliation Request'!$F$2:$F$755,"=1") -> 0 | H5: =COUNTIFS('Reconciliation Request'!$A$2:$A$755,Summary!$B5,'Reconciliation Request'!$B$2:$B$755,Summary!$C5,'Reconciliation Request'!$J$2:$J$755,Summary!H$3,'Reconciliation Request'!$F$2:$F$755,"=1") -> 2 | I5: 0 | J5: =COUNTIFS('Reconciliation Request'!$A$2:$A$755,Summary!$B5,'Reconciliation Request'!$B$2:$B$755,Summary!$C5,'Reconciliation Request'!$H$2:$H$755,">0",'Reconciliation Request'!$F$2:$F$755,"=1") -> 11 | K5: =I5/D5 -> 0 | L5: =J5/D5 -> 1 | M5: =COUNTIFS('Reconciliation Request'!$A$2:$A$755,Summary!$B5,'Reconciliation Request'!$B$2:$B$755,Summary!$C5,'Reconciliation Request'!$F$2:$F$755,"<>1") -> 59 | N5: =M5+D5 -> 70 | O5: =COUNTIFS('Reconciliation Request'!$A$2:$A$755,Summary!$B5,'Reconciliation Request'!$B$2:$B$755,Summary!$C5,'Reconciliation Request'!$H$2:$H$755,">0") -> 40 | P5: =N5-O5 -> 30 | Q5: =O5/N5 -> 0.57142857 | R5: =COUNTIFS('Reconciliation Request'!$A$2:$A$755,Summary!$B5,'Reconciliation Request'!$B$2:$B$755,Summary!$C5,'Reconciliation Request'!$K$2:$K$755,R$3) -> 42 | S5: =COUNTIFS('Reconciliation Request'!$A$2:$A$755,Summary!$B5,'Reconciliation Request'!$B$2:$B$755,Summary!$C5,'Reconciliation Request'!$K$2:$K$755,S$3) -> 28 | T5: =COUNTIFS('Reconciliation Request'!$A$2:$A$755,Summary!$B5,'Reconciliation Request'!$B$2:$B$755,Summary!$C5,'Reconciliation Request'!$K$2:$K$755,T$3) -> 0
B6: Motor | C6: Renewal | D6: =COUNTIFS('Reconciliation Request'!$A$2:$A$755,Summary!$B6,'Reconciliation Request'!$B$2:$B$755,Summary!$C6,'Reconciliation Request'!$F$2:$F$755,"=1") -> 11 | E6: =COUNTIFS('Reconciliation Request'!$A$2:$A$755,Summary!$B6,'Reconciliation Request'!$B$2:$B$755,Summary!$C6,'Reconciliation Request'!$J$2:$J$755,Summary!E$3,'Reconciliation Request'!$F$2:$F$755,"=1") -> 0 | F6: =COUNTIFS('Reconciliation Request'!$A$2:$A$755,Summary!$B6,'Reconciliation Request'!$B$2:$B$755,Summary!$C6,'Reconciliation Request'!$J$2:$J$755,Summary!F$3,'Reconciliation Request'!$F$2:$F$755,"=1") -> 5 | G6: =COUNTIFS('Reconciliation Request'!$A$2:$A$755,Summary!$B6,'Reconciliation Request'!$B$2:$B$755,Summary!$C6,'Reconciliation Request'!$J$2:$J$755,Summary!G$3,'Reconciliation Request'!$F$2:$F$755,"=1") -> 1 | H6: =COUNTIFS('Reconciliation Request'!$A$2:$A$755,Summary!$B6,'Reconciliation Request'!$B$2:$B$755,Summary!$C6,'Reconciliation Request'!$J$2:$J$755,Summary!H$3,'Reconciliation Request'!$F$2:$F$755,"=1") -> 4 | I6: 1 | J6: 10 | K6: =I6/D6 -> 0.090909091 | L6: =J6/D6 -> 0.90909091 | M6: =COUNTIFS('Reconciliation Request'!$A$2:$A$755,Summary!$B6,'Reconciliation Request'!$B$2:$B$755,Summary!$C6,'Reconciliation Request'!$F$2:$F$755,"<>1") -> 72 | N6: =M6+D6 -> 83 | O6: =COUNTIFS('Reconciliation Request'!$A$2:$A$755,Summary!$B6,'Reconciliation Request'!$B$2:$B$755,Summary!$C6,'Reconciliation Request'!$H$2:$H$755,">0") -> 54 | P6: =N6-O6 -> 29 | Q6: =O6/N6 -> 0.65060241 | R6: =COUNTIFS('Reconciliation Request'!$A$2:$A$755,Summary!$B6,'Reconciliation Request'!$B$2:$B$755,Summary!$C6,'Reconciliation Request'!$K$2:$K$755,R$3) -> 57 | S6: =COUNTIFS('Reconciliation Request'!$A$2:$A$755,Summary!$B6,'Reconciliation Request'!$B$2:$B$755,Summary!$C6,'Reconciliation Request'!$K$2:$K$755,S$3) -> 14 | T6: =COUNTIFS('Reconciliation Request'!$A$2:$A$755,Summary!$B6,'Reconciliation Request'!$B$2:$B$755,Summary!$C6,'Reconciliation Request'!$K$2:$K$755,T$3) -> 9
B7: Home | C7: Acquisition | D7: 11 | E7: =COUNTIFS('Reconciliation Request'!$A$2:$A$755,Summary!$B7,'Reconciliation Request'!$B$2:$B$755,Summary!$C7,'Reconciliation Request'!$J$2:$J$755,Summary!E$3,'Reconciliation Request'!$F$2:$F$755,"=1") -> 3 | F7: =COUNTIFS('Reconciliation Request'!$A$2:$A$755,Summary!$B7,'Reconciliation Request'!$B$2:$B$755,Summary!$C7,'Reconciliation Request'!$J$2:$J$755,Summary!F$3,'Reconciliation Request'!$F$2:$F$755,"=1") -> 2 | G7: =COUNTIFS('Reconciliation Request'!$A$2:$A$755,Summary!$B7,'Reconciliation Request'!$B$2:$B$755,Summary!$C7,'Reconciliation Request'!$J$2:$J$755,Summary!G$3,'Reconciliation Request'!$F$2:$F$755,"=1") -> 0 | H7: =COUNTIFS('Reconciliation Request'!$A$2:$A$755,Summary!$B7,'Reconciliation Request'!$B$2:$B$755,Summary!$C7,'Reconciliation Request'!$J$2:$J$755,Summary!H$3,'Reconciliation Request'!$F$2:$F$755,"=1") -> 7 | I7: 0 | J7: 11 | K7: =I7/D7 -> 0 | L7: =J7/D7 -> 1 | M7: =COUNTIFS('Reconciliation Request'!$A$2:$A$755,Summary!$B7,'Reconciliation Request'!$B$2:$B$755,Summary!$C7,'Reconciliation Request'!$F$2:$F$755,"<>1") -> 44 | N7: =M7+D7 -> 55 | O7: =COUNTIFS('Reconciliation Request'!$A$2:$A$755,Summary!$B7,'Reconciliation Request'!$B$2:$B$755,Summary!$C7,'Reconciliation Request'!$H$2:$H$755,">0") -> 34 | P7: =N7-O7 -> 21 | Q7: =O7/N7 -> 0.61818182 | R7: =COUNTIFS('Reconciliation Request'!$A$2:$A$755,Summary!$B7,'Reconciliation Request'!$B$2:$B$755,Summary!$C7,'Reconciliation Request'!$K$2:$K$755,R$3) -> 38 | S7: =COUNTIFS('Reconciliation Request'!$A$2:$A$755,Summary!$B7,'Reconciliation Request'!$B$2:$B$755,Summary!$C7,'Reconciliation Request'!$K$2:$K$755,S$3) -> 17 | T7: =COUNTIFS('Reconciliation Request'!$A$2:$A$755,Summary!$B7,'Reconciliation Request'!$B$2:$B$755,Summary!$C7,'Reconciliation Request'!$K$2:$K$755,T$3) -> 1
B8: Home | C8: Renewal | D8: =COUNTIFS('Reconciliation Request'!$A$2:$A$755,Summary!$B8,'Reconciliation Request'!$B$2:$B$755,Summary!$C8,'Reconciliation Request'!$F$2:$F$755,"=1") -> 7 | E8: =COUNTIFS('Reconciliation Request'!$A$2:$A$755,Summary!$B8,'Reconciliation Request'!$B$2:$B$755,Summary!$C8,'Reconciliation Request'!$J$2:$J$755,Summary!E$3,'Reconciliation Request'!$F$2:$F$755,"=1") -> 1 | F8: =COUNTIFS('Reconciliation Request'!$A$2:$A$755,Summary!$B8,'Reconciliation Request'!$B$2:$B$755,Summary!$C8,'Reconciliation Request'!$J$2:$J$755,Summary!F$3,'Reconciliation Request'!$F$2:$F$755,"=1") -> 4 | G8: =COUNTIFS('Reconciliation Request'!$A$2:$A$755,Summary!$B8,'Reconciliation Request'!$B$2:$B$755,Summary!$C8,'Reconciliation Request'!$J$2:$J$755,Summary!G$3,'Reconciliation Request'!$F$2:$F$755,"=1") -> 0 | H8: =COUNTIFS('Reconciliation Request'!$A$2:$A$755,Summary!$B8,'Reconciliation Request'!$B$2:$B$755,Summary!$C8,'Reconciliation Request'!$J$2:$J$755,Summary!H$3,'Reconciliation Request'!$F$2:$F$755,"=1") -> 2 | I8: 1 | J8: =COUNTIFS('Reconciliation Request'!$A$2:$A$755,Summary!$B8,'Reconciliation Request'!$B$2:$B$755,Summary!$C8,'Reconciliation Request'!$H$2:$H$755,">0",'Reconciliation Request'!$F$2:$F$755,"=1") -> 6 | K8: =I8/D8 -> 0.14285714 | L8: =J8/D8 -> 0.85714286 | M8: =COUNTIFS('Reconciliation Request'!$A$2:$A$755,Summary!$B8,'Reconciliation Request'!$B$2:$B$755,Summary!$C8,'Reconciliation Request'!$F$2:$F$755,"<>1") -> 61 | N8: =M8+D8 -> 68 | O8: =COUNTIFS('Reconciliation Request'!$A$2:$A$755,Summary!$B8,'Reconciliation Request'!$B$2:$B$755,Summary!$C8,'Reconciliation Request'!$H$2:$H$755,">0") -> 49 | P8: =N8-O8 -> 19 | Q8: =O8/N8 -> 0.72058824 | R8: =COUNTIFS('Reconciliation Request'!$A$2:$A$755,Summary!$B8,'Reconciliation Request'!$B$2:$B$755,Summary!$C8,'Reconciliation Request'!$K$2:$K$755,R$3) -> 50 | S8: =COUNTIFS('Reconciliation Request'!$A$2:$A$755,Summary!$B8,'Reconciliation Request'!$B$2:$B$755,Summary!$C8,'Reconciliation Request'!$K$2:$K$755,S$3) -> 14 | T8: =COUNTIFS('Reconciliation Request'!$A$2:$A$755,Summary!$B8,'Reconciliation Request'!$B$2:$B$755,Summary!$C8,'Reconciliation Request'!$K$2:$K$755,T$3) -> 4
B9: Van | C9: Acquisition | D9: =COUNTIFS('Reconciliation Request'!$A$2:$A$755,Summary!$B9,'Reconciliation Request'!$B$2:$B$755,Summary!$C9,'Reconciliation Request'!$F$2:$F$755,"=1") -> 7 | E9: =COUNTIFS('Reconciliation Request'!$A$2:$A$755,Summary!$B9,'Reconciliation Request'!$B$2:$B$755,Summary!$C9,'Reconciliation Request'!$J$2:$J$755,Summary!E$3,'Reconciliation Request'!$F$2:$F$755,"=1") -> 1 | F9: =COUNTIFS('Reconciliation Request'!$A$2:$A$755,Summary!$B9,'Reconciliation Request'!$B$2:$B$755,Summary!$C9,'Reconciliation Request'!$J$2:$J$755,Summary!F$3,'Reconciliation Request'!$F$2:$F$755,"=1") -> 2 | G9: =COUNTIFS('Reconciliation Request'!$A$2:$A$755,Summary!$B9,'Reconciliation Request'!$B$2:$B$755,Summary!$C9,'Reconciliation Request'!$J$2:$J$755,Summary!G$3,'Reconciliation Request'!$F$2:$F$755,"=1") -> 0 | H9: =COUNTIFS('Reconciliation Request'!$A$2:$A$755,Summary!$B9,'Reconciliation Request'!$B$2:$B$755,Summary!$C9,'Reconciliation Request'!$J$2:$J$755,Summary!H$3,'Reconciliation Request'!$F$2:$F$755,"=1") -> 4 | I9: 0 | J9: =COUNTIFS('Reconciliation Request'!$A$2:$A$755,Summary!$B9,'Reconciliation Request'!$B$2:$B$755,Summary!$C9,'Reconciliation Request'!$H$2:$H$755,">0",'Reconciliation Request'!$F$2:$F$755,"=1") -> 7 | K9: =I9/D9 -> 0 | L9: =J9/D9 -> 1 | M9: =COUNTIFS('Reconciliation Request'!$A$2:$A$755,Summary!$B9,'Reconciliation Request'!$B$2:$B$755,Summary!$C9,'Reconciliation Request'!$F$2:$F$755,"<>1") -> 30 | N9: =M9+D9 -> 37 | O9: =COUNTIFS('Reconciliation Request'!$A$2:$A$755,Summary!$B9,'Reconciliation Request'!$B$2:$B$755,Summary!$C9,'Reconciliation Request'!$H$2:$H$755,">0") -> 22 | P9: =N9-O9 -> 15 | Q9: =O9/N9 -> 0.59459459 | R9: =COUNTIFS('Reconciliation Request'!$A$2:$A$755,Summary!$B9,'Reconciliation Request'!$B$2:$B$755,Summary!$C9,'Reconciliation Request'!$K$2:$K$755,R$3) -> 23 | S9: =COUNTIFS('Reconciliation Request'!$A$2:$A$755,Summary!$B9,'Reconciliation Request'!$B$2:$B$755,Summary!$C9,'Reconciliation Request'!$K$2:$K$755,S$3) -> 11 | T9: =COUNTIFS('Reconciliation Request'!$A$2:$A$755,Summary!$B9,'Reconciliation Request'!$B$2:$B$755,Summary!$C9,'Reconciliation Request'!$K$2:$K$755,T$3) -> 3
B10: Van | C10: Renewal | D10: =COUNTIFS('Reconciliation Request'!$A$2:$A$755,Summary!$B10,'Reconciliation Request'!$B$2:$B$755,Summary!$C10,'Reconciliation Request'!$F$2:$F$755,"=1") -> 8 | E10: =COUNTIFS('Reconciliation Request'!$A$2:$A$755,Summary!$B10,'Reconciliation Request'!$B$2:$B$755,Summary!$C10,'Reconciliation Request'!$J$2:$J$755,Summary!E$3,'Reconciliation Request'!$F$2:$F$755,"=1") -> 1 | F10: =COUNTIFS('Reconciliation Request'!$A$2:$A$755,Summary!$B10,'Reconciliation Request'!$B$2:$B$755,Summary!$C10,'Reconciliation Request'!$J$2:$J$755,Summary!F$3,'Reconciliation Request'!$F$2:$F$755,"=1") -> 3 | G10: =COUNTIFS('Reconciliation Request'!$A$2:$A$755,Summary!$B10,'Reconciliation Request'!$B$2:$B$755,Summary!$C10,'Reconciliation Request'!$J$2:$J$755,Summary!G$3,'Reconciliation Request'!$F$2:$F$755,"=1") -> 0 | H10: =COUNTIFS('Reconciliation Request'!$A$2:$A$755,Summary!$B10,'Reconciliation Request'!$B$2:$B$755,Summary!$C10,'Reconciliation Request'!$J$2:$J$755,Summary!H$3,'Reconciliation Request'!$F$2:$F$755,"=1") -> 4 | I10: 1 | J10: =COUNTIFS('Reconciliation Request'!$A$2:$A$755,Summary!$B10,'Reconciliation Request'!$B$2:$B$755,Summary!$C10,'Reconciliation Request'!$H$2:$H$755,">0",'Reconciliation Request'!$F$2:$F$755,"=1") -> 7 | K10: =I10/D10 -> 0.125 | L10: =J10/D10 -> 0.875 | M10: =COUNTIFS('Reconciliation Request'!$A$2:$A$755,Summary!$B10,'Reconciliation Request'!$B$2:$B$755,Summary!$C10,'Reconciliation Request'!$F$2:$F$755,"<>1") -> 49 | N10: =M10+D10 -> 57 | O10: =COUNTIFS('Reconciliation Request'!$A$2:$A$755,Summary!$B10,'Reconciliation Request'!$B$2:$B$755,Summary!$C10,'Reconciliation Request'!$H$2:$H$755,">0") -> 25 | P10: =N10-O10 -> 32 | Q10: =O10/N10 -> 0.43859649 | R10: =COUNTIFS('Reconciliation Request'!$A$2:$A$755,Summary!$B10,'Reconciliation Request'!$B$2:$B$755,Summary!$C10,'Reconciliation Request'!$K$2:$K$755,R$3) -> 29 | S10: =COUNTIFS('Reconciliation Request'!$A$2:$A$755,Summary!$B10,'Reconciliation Request'!$B$2:$B$755,Summary!$C10,'Reconciliation Request'!$K$2:$K$755,S$3) -> 28 | T10: =COUNTIFS('Reconciliation Request'!$A$2:$A$755,Summary!$B10,'Reconciliation Request'!$B$2:$B$755,Summary!$C10,'Reconciliation Request'!$K$2:$K$755,T$3) -> 0
B11: Travel | C11: Acquisition | D11: =COUNTIFS('Reconciliation Request'!$A$2:$A$755,Summary!$B11,'Reconciliation Request'!$B$2:$B$755,Summary!$C11,'Reconciliation Request'!$F$2:$F$755,"=1") -> 6 | E11: =COUNTIFS('Reconciliation Request'!$A$2:$A$755,Summary!$B11,'Reconciliation Request'!$B$2:$B$755,Summary!$C11,'Reconciliation Request'!$J$2:$J$755,Summary!E$3,'Reconciliation Request'!$F$2:$F$755,"=1") -> 0 | F11: =COUNTIFS('Reconciliation Request'!$A$2:$A$755,Summary!$B11,'Reconciliation Request'!$B$2:$B$755,Summary!$C11,'Reconciliation Request'!$J$2:$J$755,Summary!F$3,'Reconciliation Request'!$F$2:$F$755,"=1") -> 1 | G11: =COUNTIFS('Reconciliation Request'!$A$2:$A$755,Summary!$B11,'Reconciliation Request'!$B$2:$B$755,Summary!$C11,'Reconciliation Request'!$J$2:$J$755,Summary!G$3,'Reconciliation Request'!$F$2:$F$755,"=1") -> 1 | H11: =COUNTIFS('Reconciliation Request'!$A$2:$A$755,Summary!$B11,'Reconciliation Request'!$B$2:$B$755,Summary!$C11,'Reconciliation Request'!$J$2:$J$755,Summary!H$3,'Reconciliation Request'!$F$2:$F$755,"=1") -> 4 | I11: 3 | J11: =COUNTIFS('Reconciliation Request'!$A$2:$A$755,Summary!$B11,'Reconciliation Request'!$B$2:$B$755,Summary!$C11,'Reconciliation Request'!$H$2:$H$755,">0",'Reconciliation Request'!$F$2:$F$755,"=1") -> 3 | K11: =I11/D11 -> 0.5 | L11: =J11/D11 -> 0.5 | M11: =COUNTIFS('Reconciliation Request'!$A$2:$A$755,Summary!$B11,'Reconciliation Request'!$B$2:$B$755,Summary!$C11,'Reconciliation Request'!$F$2:$F$755,"<>1") -> 16 | N11: =M11+D11 -> 22 | O11: =COUNTIFS('Reconciliation Request'!$A$2:$A$755,Summary!$B11,'Reconciliation Request'!$B$2:$B$755,Summary!$C11,'Reconciliation Request'!$H$2:$H$755,">0") -> 5 | P11: =N11-O11 -> 17 | Q11: =O11/N11 -> 0.22727273 | R11: =COUNTIFS('Reconciliation Request'!$A$2:$A$755,Summary!$B11,'Reconciliation Request'!$B$2:$B$755,Summary!$C11,'Reconciliation Request'!$K$2:$K$755,R$3) -> 9 | S11: =COUNTIFS('Reconciliation Request'!$A$2:$A$755,Summary!$B11,'Reconciliation Request'!$B$2:$B$755,Summary!$C11,'Reconciliation Request'!$K$2:$K$755,S$3) -> 9 | T11: =COUNTIFS('Reconciliation Request'!$A$2:$A$755,Summary!$B11,'Reconciliation Request'!$B$2:$B$755,Summary!$C11,'Reconciliation Request'!$K$2:$K$755,T$3) -> 4
B12: Travel | C12: Renewal | D12: =COUNTIFS('Reconciliation Request'!$A$2:$A$755,Summary!$B12,'Reconciliation Request'!$B$2:$B$755,Summary!$C12,'Reconciliation Request'!$F$2:$F$755,"=1") -> 6 | E12: =COUNTIFS('Reconciliation Request'!$A$2:$A$755,Summary!$B12,'Reconciliation Request'!$B$2:$B$755,Summary!$C12,'Reconciliation Request'!$J$2:$J$755,Summary!E$3,'Reconciliation Request'!$F$2:$F$755,"=1") -> 0 | F12: =COUNTIFS('Reconciliation Request'!$A$2:$A$755,Summary!$B12,'Reconciliation Request'!$B$2:$B$755,Summary!$C12,'Reconciliation Request'!$J$2:$J$755,Summary!F$3,'Reconciliation Request'!$F$2:$F$755,"=1") -> 2 | G12: =COUNTIFS('Reconciliation Request'!$A$2:$A$755,Summary!$B12,'Reconciliation Request'!$B$2:$B$755,Summary!$C12,'Reconciliation Request'!$J$2:$J$755,Summary!G$3,'Reconciliation Request'!$F$2:$F$755,"=1") -> 0 | H12: =COUNTIFS('Reconciliation Request'!$A$2:$A$755,Summary!$B12,'Reconciliation Request'!$B$2:$B$755,Summary!$C12,'Reconciliation Request'!$J$2:$J$755,Summary!H$3,'Reconciliation Request'!$F$2:$F$755,"=1") -> 4 | I12: 2 | J12: =COUNTIFS('Reconciliation Request'!$A$2:$A$755,Summary!$B12,'Reconciliation Request'!$B$2:$B$755,Summary!$C12,'Reconciliation Request'!$H$2:$H$755,">0",'Reconciliation Request'!$F$2:$F$755,"=1") -> 4 | K12: =I12/D12 -> 0.33333333 | L12: =J12/D12 -> 0.66666667 | M12: =COUNTIFS('Reconciliation Request'!$A$2:$A$755,Summary!$B12,'Reconciliation Request'!$B$2:$B$755,Summary!$C12,'Reconciliation Request'!$F$2:$F$755,"<>1") -> 13 | N12: =M12+D12 -> 19 | O12: =COUNTIFS('Reconciliation Request'!$A$2:$A$755,Summary!$B12,'Reconciliation Request'!$B$2:$B$755,Summary!$C12,'Reconciliation Request'!$H$2:$H$755,">0") -> 4 | P12: =N12-O12 -> 15 | Q12: =O12/N12 -> 0.21052632 | R12: =COUNTIFS('Reconciliation Request'!$A$2:$A$755,Summary!$B12,'Reconciliation Request'!$B$2:$B$755,Summary!$C12,'Reconciliation Request'!$K$2:$K$755,R$3) -> 5 | S12: =COUNTIFS('Reconciliation Request'!$A$2:$A$755,Summary!$B12,'Reconciliation Request'!$B$2:$B$755,Summary!$C12,'Reconciliation Request'!$K$2:$K$755,S$3) -> 12 | T12: =COUNTIFS('Reconciliation Request'!$A$2:$A$755,Summary!$B12,'Reconciliation Request'!$B$2:$B$755,Summary!$C12,'Reconciliation Request'!$K$2:$K$755,T$3) -> 2
J13: =COUNTIFS('Reconciliation Request'!$A$2:$A$755,Summary!$B13,'Reconciliation Request'!$B$2:$B$755,Summary!$C13,'Reconciliation Request'!$H$2:$H$755,">0",'Reconciliation Request'!$F$2:$F$755,"=1") -> 0 | N13: =M13+D13 -> 0
J14: =COUNTIFS('Reconciliation Request'!$A$2:$A$755,Summary!$B14,'Reconciliation Request'!$B$2:$B$755,Summary!$C14,'Reconciliation Request'!$H$2:$H$755,">0",'Reconciliation Request'!$F$2:$F$755,"=1") -> 0 | N14: =M14+D14 -> 0
B15: Home | C15: MTA | D15: =COUNTIFS('Reconciliation Request'!$A$2:$A$755,Summary!$B15,'Reconciliation Request'!$B$2:$B$755,Summary!$C15,'Reconciliation Request'!$F$2:$F$755,"=1") -> 4 | E15: =COUNTIFS('Reconciliation Request'!$A$2:$A$755,Summary!$B15,'Reconciliation Request'!$B$2:$B$755,Summary!$C15,'Reconciliation Request'!$J$2:$J$755,Summary!E$3,'Reconciliation Request'!$F$2:$F$755,"=1") -> 0 | F15: =COUNTIFS('Reconciliation Request'!$A$2:$A$755,Summary!$B15,'Reconciliation Request'!$B$2:$B$755,Summary!$C15,'Reconciliation Request'!$J$2:$J$755,Summary!F$3,'Reconciliation Request'!$F$2:$F$755,"=1") -> 0 | G15: =COUNTIFS('Reconciliation Request'!$A$2:$A$755,Summary!$B15,'Reconciliation Request'!$B$2:$B$755,Summary!$C15,'Reconciliation Request'!$J$2:$J$755,Summary!G$3,'Reconciliation Request'!$F$2:$F$755,"=1") -> 0 | H15: =COUNTIFS('Reconciliation Request'!$A$2:$A$755,Summary!$B15,'Reconciliation Request'!$B$2:$B$755,Summary!$C15,'Reconciliation Request'!$J$2:$J$755,Summary!H$3,'Reconciliation Request'!$F$2:$F$755,"=1") -> 4 | I15: 0 | J15: 4 | K15: =I15/D15 -> 0 | L15: =J15/D15 -> 1 | M15: =COUNTIFS('Reconciliation Request'!$A$2:$A$755,Summary!$B15,'Reconciliation Request'!$B$2:$B$755,Summary!$C15,'Reconciliation Request'!$F$2:$F$755,"<>1") -> 40 | N15: =M15+D15 -> 44 | O15: =COUNTIFS('Reconciliation Request'!$A$2:$A$755,Summary!$B15,'Reconciliation Request'!$B$2:$B$755,Summary!$C15,'Reconciliation Request'!$H$2:$H$755,">0") -> 23 | P15: =N15-O15 -> 21 | Q15: =O15/N15 -> 0.52272727 | R15: =COUNTIFS('Reconciliation Request'!$A$2:$A$755,Summary!$B15,'Reconciliation Request'!$B$2:$B$755,Summary!$C15,'Reconciliation Request'!$K$2:$K$755,R$3) -> 24 | S15: =COUNTIFS('Reconciliation Request'!$A$2:$A$755,Summary!$B15,'Reconciliation Request'!$B$2:$B$755,Summary!$C15,'Reconciliation Request'!$K$2:$K$755,S$3) -> 17 | T15: =COUNTIFS('Reconciliation Request'!$A$2:$A$755,Summary!$B15,'Reconciliation Request'!$B$2:$B$755,Summary!$C15,'Reconciliation Request'!$K$2:$K$755,T$3) -> 3
B16: Home | C16: Cancellation | D16: =COUNTIFS('Reconciliation Request'!$A$2:$A$755,Summary!$B16,'Reconciliation Request'!$B$2:$B$755,Summary!$C16,'Reconciliation Request'!$F$2:$F$755,"=1") -> 3 | E16: =COUNTIFS('Reconciliation Request'!$A$2:$A$755,Summary!$B16,'Reconciliation Request'!$B$2:$B$755,Summary!$C16,'Reconciliation Request'!$J$2:$J$755,Summary!E$3,'Reconciliation Request'!$F$2:$F$755,"=1") -> 0 | F16: =COUNTIFS('Reconciliation Request'!$A$2:$A$755,Summary!$B16,'Reconciliation Request'!$B$2:$B$755,Summary!$C16,'Reconciliation Request'!$J$2:$J$755,Summary!F$3,'Reconciliation Request'!$F$2:$F$755,"=1") -> 0 | G16: =COUNTIFS('Reconciliation Request'!$A$2:$A$755,Summary!$B16,'Reconciliation Request'!$B$2:$B$755,Summary!$C16,'Reconciliation Request'!$J$2:$J$755,Summary!G$3,'Reconciliation Request'!$F$2:$F$755,"=1") -> 0 | H16: =COUNTIFS('Reconciliation Request'!$A$2:$A$755,Summary!$B16,'Reconciliation Request'!$B$2:$B$755,Summary!$C16,'Reconciliation Request'!$J$2:$J$755,Summary!H$3,'Reconciliation Request'!$F$2:$F$755,"=1") -> 3 | I16: 1 | J16: 3 | K16: =I16/D16 -> 0.33333333 | L16: =J16/D16 -> 1 | M16: =COUNTIFS('Reconciliation Request'!$A$2:$A$755,Summary!$B16,'Reconciliation Request'!$B$2:$B$755,Summary!$C16,'Reconciliation Request'!$F$2:$F$755,"<>1") -> 20 | N16: =M16+D16 -> 23 | O16: =COUNTIFS('Reconciliation Request'!$A$2:$A$755,Summary!$B16,'Reconciliation Request'!$B$2:$B$755,Summary!$C16,'Reconciliation Request'!$H$2:$H$755,">0") -> 6 | P16: =N16-O16 -> 17 | Q16: =O16/N16 -> 0.26086957 | R16: =COUNTIFS('Reconciliation Request'!$A$2:$A$755,Summary!$B16,'Reconciliation Request'!$B$2:$B$755,Summary!$C16,'Reconciliation Request'!$K$2:$K$755,R$3) -> 16 | S16: =COUNTIFS('Reconciliation Request'!$A$2:$A$755,Summary!$B16,'Reconciliation Request'!$B$2:$B$755,Summary!$C16,'Reconciliation Request'!$K$2:$K$755,S$3) -> 6 | T16: =COUNTIFS('Reconciliation Request'!$A$2:$A$755,Summary!$B16,'Reconciliation Request'!$B$2:$B$755,Summary!$C16,'Reconciliation Request'!$K$2:$K$755,T$3) -> 1
B17: Home | C17: Arrears | D17: =COUNTIFS('Reconciliation Request'!$A$2:$A$755,Summary!$B17,'Reconciliation Request'!$B$2:$B$755,Summary!$C17,'Reconciliation Request'!$F$2:$F$755,"=1") -> 3 | E17: =COUNTIFS('Reconciliation Request'!$A$2:$A$755,Summary!$B17,'Reconciliation Request'!$B$2:$B$755,Summary!$C17,'Reconciliation Request'!$J$2:$J$755,Summary!E$3,'Reconciliation Request'!$F$2:$F$755,"=1") -> 0 | F17: =COUNTIFS('Reconciliation Request'!$A$2:$A$755,Summary!$B17,'Reconciliation Request'!$B$2:$B$755,Summary!$C17,'Reconciliation Request'!$J$2:$J$755,Summary!F$3,'Reconciliation Request'!$F$2:$F$755,"=1") -> 0 | G17: =COUNTIFS('Reconciliation Request'!$A$2:$A$755,Summary!$B17,'Reconciliation Request'!$B$2:$B$755,Summary!$C17,'Reconciliation Request'!$J$2:$J$755,Summary!G$3,'Reconciliation Request'!$F$2:$F$755,"=1") -> 0 | H17: =COUNTIFS('Reconciliation Request'!$A$2:$A$755,Summary!$B17,'Reconciliation Request'!$B$2:$B$755,Summary!$C17,'Reconciliation Request'!$J$2:$J$755,Summary!H$3,'Reconciliation Request'!$F$2:$F$755,"=1") -> 3 | I17: 1 | J17: 2 | K17: =I17/D17 -> 0.33333333 | L17: =J17/D17 -> 0.66666667 | M17: =COUNTIFS('Reconciliation Request'!$A$2:$A$755,Summary!$B17,'Reconciliation Request'!$B$2:$B$755,Summary!$C17,'Reconciliation Request'!$F$2:$F$755,"<>1") -> 12 | N17: =M17+D17 -> 15 | O17: =COUNTIFS('Reconciliation Request'!$A$2:$A$755,Summary!$B17,'Reconciliation Request'!$B$2:$B$755,Summary!$C17,'Reconciliation Request'!$H$2:$H$755,">0") -> 4 | P17: =N17-O17 -> 11 | Q17: =O17/N17 -> 0.26666667 | R17: =COUNTIFS('Reconciliation Request'!$A$2:$A$755,Summary!$B17,'Reconciliation Request'!$B$2:$B$755,Summary!$C17,'Reconciliation Request'!$K$2:$K$755,R$3) -> 5 | S17: =COUNTIFS('Reconciliation Request'!$A$2:$A$755,Summary!$B17,'Reconciliation Request'!$B$2:$B$755,Summary!$C17,'Reconciliation Request'!$K$2:$K$755,S$3) -> 8 | T17: =COUNTIFS('Reconciliation Request'!$A$2:$A$755,Summary!$B17,'Reconciliation Request'!$B$2:$B$755,Summary!$C17,'Reconciliation Request'!$K$2:$K$755,T$3) -> 1
B18: Home | C18: Doc Request | D18: =COUNTIFS('Reconciliation Request'!$A$2:$A$755,Summary!$B18,'Reconciliation Request'!$B$2:$B$755,Summary!$C18,'Reconciliation Request'!$F$2:$F$755,"=1") -> 2 | E18: =COUNTIFS('Reconciliation Request'!$A$2:$A$755,Summary!$B18,'Reconciliation Request'!$B$2:$B$755,Summary!$C18,'Reconciliation Request'!$J$2:$J$755,Summary!E$3,'Reconciliation Request'!$F$2:$F$755,"=1") -> 0 | F18: =COUNTIFS('Reconciliation Request'!$A$2:$A$755,Summary!$B18,'Reconciliation Request'!$B$2:$B$755,Summary!$C18,'Reconciliation Request'!$J$2:$J$755,Summary!F$3,'Reconciliation Request'!$F$2:$F$755,"=1") -> 0 | G18: =COUNTIFS('Reconciliation Request'!$A$2:$A$755,Summary!$B18,'Reconciliation Request'!$B$2:$B$755,Summary!$C18,'Reconciliation Request'!$J$2:$J$755,Summary!G$3,'Reconciliation Request'!$F$2:$F$755,"=1") -> 0 | H18: =COUNTIFS('Reconciliation Request'!$A$2:$A$755,Summary!$B18,'Reconciliation Request'!$B$2:$B$755,Summary!$C18,'Reconciliation Request'!$J$2:$J$755,Summary!H$3,'Reconciliation Request'!$F$2:$F$755,"=1") -> 2 | I18: 1 | J18: =COUNTIFS('Reconciliation Request'!$A$2:$A$755,Summary!$B18,'Reconciliation Request'!$B$2:$B$755,Summary!$C18,'Reconciliation Request'!$H$2:$H$755,">0",'Reconciliation Request'!$F$2:$F$755,"=1") -> 2 | K18: =I18/D18 -> 0.5 | L18: =J18/D18 -> 1 | M18: =COUNTIFS('Reconciliation Request'!$A$2:$A$755,Summary!$B18,'Reconciliation Request'!$B$2:$B$755,Summary!$C18,'Reconciliation Request'!$F$2:$F$755,"<>1") -> 12 | N18: =M18+D18 -> 14 | O18: =COUNTIFS('Reconciliation Request'!$A$2:$A$755,Summary!$B18,'Reconciliation Request'!$B$2:$B$755,Summary!$C18,'Reconciliation Request'!$H$2:$H$755,">0") -> 5 | P18: =N18-O18 -> 9 | Q18: =O18/N18 -> 0.35714286 | R18: =COUNTIFS('Reconciliation Request'!$A$2:$A$755,Summary!$B18,'Reconciliation Request'!$B$2:$B$755,Summary!$C18,'Reconciliation Request'!$K$2:$K$755,R$3) -> 4 | S18: =COUNTIFS('Reconciliation Request'!$A$2:$A$755,Summary!$B18,'Reconciliation Request'!$B$2:$B$755,Summary!$C18,'Reconciliation Request'!$K$2:$K$755,S$3) -> 0 | T18: =COUNTIFS('Reconciliation Request'!$A$2:$A$755,Summary!$B18,'Reconciliation Request'!$B$2:$B$755,Summary!$C18,'Reconciliation Request'!$K$2:$K$755,T$3) -> 2
B19: Home | C19: In-Life | D19: =COUNTIFS('Reconciliation Request'!$A$2:$A$755,Summary!$B19,'Reconciliation Request'!$B$2:$B$755,Summary!$C19,'Reconciliation Request'!$F$2:$F$755,"=1") -> 1 | E19: =COUNTIFS('Reconciliation Request'!$A$2:$A$755,Summary!$B19,'Reconciliation Request'!$B$2:$B$755,Summary!$C19,'Reconciliation Request'!$J$2:$J$755,Summary!E$3,'Reconciliation Request'!$F$2:$F$755,"=1") -> 0 | F19: =COUNTIFS('Reconciliation Request'!$A$2:$A$755,Summary!$B19,'Reconciliation Request'!$B$2:$B$755,Summary!$C19,'Reconciliation Request'!$J$2:$J$755,Summary!F$3,'Reconciliation Request'!$F$2:$F$755,"=1") -> 0 | G19: =COUNTIFS('Reconciliation Request'!$A$2:$A$755,Summary!$B19,'Reconciliation Request'!$B$2:$B$755,Summary!$C19,'Reconciliation Request'!$J$2:$J$755,Summary!G$3,'Reconciliation Request'!$F$2:$F$755,"=1") -> 0 | H19: =COUNTIFS('Reconciliation Request'!$A$2:$A$755,Summary!$B19,'Reconciliation Request'!$B$2:$B$755,Summary!$C19,'Reconciliation Request'!$J$2:$J$755,Summary!H$3,'Reconciliation Request'!$F$2:$F$755,"=1") -> 1 | J19: =COUNTIFS('Reconciliation Request'!$A$2:$A$755,Summary!$B19,'Reconciliation Request'!$B$2:$B$755,Summary!$C19,'Reconciliation Request'!$H$2:$H$755,">0",'Reconciliation Request'!$F$2:$F$755,"=1") -> 0 | K19: =I19/D19 -> 0 | L19: =J19/D19 -> 0 | M19: =COUNTIFS('Reconciliation Request'!$A$2:$A$755,Summary!$B19,'Reconciliation Request'!$B$2:$B$755,Summary!$C19,'Reconciliation Request'!$F$2:$F$755,"<>1") -> 0 | N19: =M19+D19 -> 1 | O19: =COUNTIFS('Reconciliation Request'!$A$2:$A$755,Summary!$B19,'Reconciliation Request'!$B$2:$B$755,Summary!$C19,'Reconciliation Request'!$H$2:$H$755,">0") -> 0 | P19: =N19-O19 -> 1 | Q19: =O19/N19 -> 0 | R19: =COUNTIFS('Reconciliation Request'!$A$2:$A$755,Summary!$B19,'Reconciliation Request'!$B$2:$B$755,Summary!$C19,'Reconciliation Request'!$K$2:$K$755,R$3) -> 0 | S19: =COUNTIFS('Reconciliation Request'!$A$2:$A$755,Summary!$B19,'Reconciliation Request'!$B$2:$B$755,Summary!$C19,'Reconciliation Request'!$K$2:$K$755,S$3) -> 1 | T19: =COUNTIFS('Reconciliation Request'!$A$2:$A$755,Summary!$B19,'Reconciliation Request'!$B$2:$B$755,Summary!$C19,'Reconciliation Request'!$K$2:$K$755,T$3) -> 0
B20: Home | C20: Claims | D20: =COUNTIFS('Reconciliation Request'!$A$2:$A$755,Summary!$B20,'Reconciliation Request'!$B$2:$B$755,Summary!$C20,'Reconciliation Request'!$F$2:$F$755,"=1") -> 3 | E20: =COUNTIFS('Reconciliation Request'!$A$2:$A$755,Summary!$B20,'Reconciliation Request'!$B$2:$B$755,Summary!$C20,'Reconciliation Request'!$J$2:$J$755,Summary!E$3,'Reconciliation Request'!$F$2:$F$755,"=1") -> 0 | F20: =COUNTIFS('Reconciliation Request'!$A$2:$A$755,Summary!$B20,'Reconciliation Request'!$B$2:$B$755,Summary!$C20,'Reconciliation Request'!$J$2:$J$755,Summary!F$3,'Reconciliation Request'!$F$2:$F$755,"=1") -> 0 | G20: =COUNTIFS('Reconciliation Request'!$A$2:$A$755,Summary!$B20,'Reconciliation Request'!$B$2:$B$755,Summary!$C20,'Reconciliation Request'!$J$2:$J$755,Summary!G$3,'Reconciliation Request'!$F$2:$F$755,"=1") -> 0 | H20: =COUNTIFS('Reconciliation Request'!$A$2:$A$755,Summary!$B20,'Reconciliation Request'!$B$2:$B$755,Summary!$C20,'Reconciliation Request'!$J$2:$J$755,Summary!H$3,'Reconciliation Request'!$F$2:$F$755,"=1") -> 3 | I20: 0 | J20: 3 | K20: =I20/D20 -> 0 | L20: =J20/D20 -> 1 | M20: =COUNTIFS('Reconciliation Request'!$A$2:$A$755,Summary!$B20,'Reconciliation Request'!$B$2:$B$755,Summary!$C20,'Reconciliation Request'!$F$2:$F$755,"<>1") -> 8 | N20: =M20+D20 -> 11 | O20: =COUNTIFS('Reconciliation Request'!$A$2:$A$755,Summary!$B20,'Reconciliation Request'!$B$2:$B$755,Summary!$C20,'Reconciliation Request'!$H$2:$H$755,">0") -> 5 | P20: =N20-O20 -> 6 | Q20: =O20/N20 -> 0.45454545 | R20: =COUNTIFS('Reconciliation Request'!$A$2:$A$755,Summary!$B20,'Reconciliation Request'!$B$2:$B$755,Summary!$C20,'Reconciliation Request'!$K$2:$K$755,R$3) -> 7 | S20: =COUNTIFS('Reconciliation Request'!$A$2:$A$755,Summary!$B20,'Reconciliation Request'!$B$2:$B$755,Summary!$C20,'Reconciliation Request'!$K$2:$K$755,S$3) -> 4 | T20: =COUNTIFS('Reconciliation Request'!$A$2:$A$755,Summary!$B20,'Reconciliation Request'!$B$2:$B$755,Summary!$C20,'Reconciliation Request'!$K$2:$K$755,T$3) -> 0
B21: Motor | C21: MTA | D21: =COUNTIFS('Reconciliation Request'!$A$2:$A$755,Summary!$B21,'Reconciliation Request'!$B$2:$B$755,Summary!$C21,'Reconciliation Request'!$F$2:$F$755,"=1") -> 6 | E21: =COUNTIFS('Reconciliation Request'!$A$2:$A$755,Summary!$B21,'Reconciliation Request'!$B$2:$B$755,Summary!$C21,'Reconciliation Request'!$J$2:$J$755,Summary!E$3,'Reconciliation Request'!$F$2:$F$755,"=1") -> 0 | F21: =COUNTIFS('Reconciliation Request'!$A$2:$A$755,Summary!$B21,'Reconciliation Request'!$B$2:$B$755,Summary!$C21,'Reconciliation Request'!$J$2:$J$755,Summary!F$3,'Reconciliation Request'!$F$2:$F$755,"=1") -> 1 | G21: =COUNTIFS('Reconciliation Request'!$A$2:$A$755,Summary!$B21,'Reconciliation Request'!$B$2:$B$755,Summary!$C21,'Reconciliation Request'!$J$2:$J$755,Summary!G$3,'Reconciliation Request'!$F$2:$F$755,"=1") -> 0 | H21: =COUNTIFS('Reconciliation Request'!$A$2:$A$755,Summary!$B21,'Reconciliation Request'!$B$2:$B$755,Summary!$C21,'Reconciliation Request'!$J$2:$J$755,Summary!H$3,'Reconciliation Request'!$F$2:$F$755,"=1") -> 5 | I21: 1 | J21: 5 | K21: =I21/D21 -> 0.16666667 | L21: =J21/D21 -> 0.83333333 | M21: =COUNTIFS('Reconciliation Request'!$A$2:$A$755,Summary!$B21,'Reconciliation Request'!$B$2:$B$755,Summary!$C21,'Reconciliation Request'!$F$2:$F$755,"<>1") -> 37 | N21: =M21+D21 -> 43 | O21: =COUNTIFS('Reconciliation Request'!$A$2:$A$755,Summary!$B21,'Reconciliation Request'!$B$2:$B$755,Summary!$C21,'Reconciliation Request'!$H$2:$H$755,">0") -> 17 | P21: =N21-O21 -> 26 | Q21: =O21/N21 -> 0.39534884 | R21: =COUNTIFS('Reconciliation Request'!$A$2:$A$755,Summary!$B21,'Reconciliation Request'!$B$2:$B$755,Summary!$C21,'Reconciliation Request'!$K$2:$K$755,R$3) -> 25 | S21: =COUNTIFS('Reconciliation Request'!$A$2:$A$755,Summary!$B21,'Reconciliation Request'!$B$2:$B$755,Summary!$C21,'Reconciliation Request'!$K$2:$K$755,S$3) -> 16 | T21: =COUNTIFS('Reconciliation Request'!$A$2:$A$755,Summary!$B21,'Reconciliation Request'!$B$2:$B$755,Summary!$C21,'Reconciliation Request'!$K$2:$K$755,T$3) -> 2
B22: Motor | C22: Cancellation | D22: =COUNTIFS('Reconciliation Request'!$A$2:$A$755,Summary!$B22,'Reconciliation Request'!$B$2:$B$755,Summary!$C22,'Reconciliation Request'!$F$2:$F$755,"=1") -> 6 | E22: =COUNTIFS('Reconciliation Request'!$A$2:$A$755,Summary!$B22,'Reconciliation Request'!$B$2:$B$755,Summary!$C22,'Reconciliation Request'!$J$2:$J$755,Summary!E$3,'Reconciliation Request'!$F$2:$F$755,"=1") -> 0 | F22: =COUNTIFS('Reconciliation Request'!$A$2:$A$755,Summary!$B22,'Reconciliation Request'!$B$2:$B$755,Summary!$C22,'Reconciliation Request'!$J$2:$J$755,Summary!F$3,'Reconciliation Request'!$F$2:$F$755,"=1") -> 0 | G22: =COUNTIFS('Reconciliation Request'!$A$2:$A$755,Summary!$B22,'Reconciliation Request'!$B$2:$B$755,Summary!$C22,'Reconciliation Request'!$J$2:$J$755,Summary!G$3,'Reconciliation Request'!$F$2:$F$755,"=1") -> 0 | H22: =COUNTIFS('Reconciliation Request'!$A$2:$A$755,Summary!$B22,'Reconciliation Request'!$B$2:$B$755,Summary!$C22,'Reconciliation Request'!$J$2:$J$755,Summary!H$3,'Reconciliation Request'!$F$2:$F$755,"=1") -> 6 | I22: 1 | J22: 5 | K22: =I22/D22 -> 0.16666667 | L22: =J22/D22 -> 0.83333333 | M22: =COUNTIFS('Reconciliation Request'!$A$2:$A$755,Summary!$B22,'Reconciliation Request'!$B$2:$B$755,Summary!$C22,'Reconciliation Request'!$F$2:$F$755,"<>1") -> 10 | N22: =M22+D22 -> 16 | O22: =COUNTIFS('Reconciliation Request'!$A$2:$A$755,Summary!$B22,'Reconciliation Request'!$B$2:$B$755,Summary!$C22,'Reconciliation Request'!$H$2:$H$755,">0") -> 7 | P22: =N22-O22 -> 9 | Q22: =O22/N22 -> 0.4375 | R22: =COUNTIFS('Reconciliation Request'!$A$2:$A$755,Summary!$B22,'Reconciliation Request'!$B$2:$B$755,Summary!$C22,'Reconciliation Request'!$K$2:$K$755,R$3) -> 9 | S22: =COUNTIFS('Reconciliation Request'!$A$2:$A$755,Summary!$B22,'Reconciliation Request'!$B$2:$B$755,Summary!$C22,'Reconciliation Request'!$K$2:$K$755,S$3) -> 5 | T22: =COUNTIFS('Reconciliation Request'!$A$2:$A$755,Summary!$B22,'Reconciliation Request'!$B$2:$B$755,Summary!$C22,'Reconciliation Request'!$K$2:$K$755,T$3) -> 2
B23: Motor | C23: Arrears | D23: =COUNTIFS('Reconciliation Request'!$A$2:$A$755,Summary!$B23,'Reconciliation Request'!$B$2:$B$755,Summary!$C23,'Reconciliation Request'!$F$2:$F$755,"=1") -> 3 | E23: =COUNTIFS('Reconciliation Request'!$A$2:$A$755,Summary!$B23,'Reconciliation Request'!$B$2:$B$755,Summary!$C23,'Reconciliation Request'!$J$2:$J$755,Summary!E$3,'Reconciliation Request'!$F$2:$F$755,"=1") -> 0 | F23: =COUNTIFS('Reconciliation Request'!$A$2:$A$755,Summary!$B23,'Reconciliation Request'!$B$2:$B$755,Summary!$C23,'Reconciliation Request'!$J$2:$J$755,Summary!F$3,'Reconciliation Request'!$F$2:$F$755,"=1") -> 0 | G23: =COUNTIFS('Reconciliation Request'!$A$2:$A$755,Summary!$B23,'Reconciliation Request'!$B$2:$B$755,Summary!$C23,'Reconciliation Request'!$J$2:$J$755,Summary!G$3,'Reconciliation Request'!$F$2:$F$755,"=1") -> 0 | H23: =COUNTIFS('Reconciliation Request'!$A$2:$A$755,Summary!$B23,'Reconciliation Request'!$B$2:$B$755,Summary!$C23,'Reconciliation Request'!$J$2:$J$755,Summary!H$3,'Reconciliation Request'!$F$2:$F$755,"=1") -> 3 | I23: 1 | J23: 2 | K23: =I23/D23 -> 0.33333333 | L23: =J23/D23 -> 0.66666667 | M23: =COUNTIFS('Reconciliation Request'!$A$2:$A$755,Summary!$B23,'Reconciliation Request'!$B$2:$B$755,Summary!$C23,'Reconciliation Request'!$F$2:$F$755,"<>1") -> 12 | N23: =M23+D23 -> 15 | O23: =COUNTIFS('Reconciliation Request'!$A$2:$A$755,Summary!$B23,'Reconciliation Request'!$B$2:$B$755,Summary!$C23,'Reconciliation Request'!$H$2:$H$755,">0") -> 5 | P23: =N23-O23 -> 10 | Q23: =O23/N23 -> 0.33333333 | R23: =COUNTIFS('Reconciliation Request'!$A$2:$A$755,Summary!$B23,'Reconciliation Request'!$B$2:$B$755,Summary!$C23,'Reconciliation Request'!$K$2:$K$755,R$3) -> 5 | S23: =COUNTIFS('Reconciliation Request'!$A$2:$A$755,Summary!$B23,'Reconciliation Request'!$B$2:$B$755,Summary!$C23,'Reconciliation Request'!$K$2:$K$755,S$3) -> 8 | T23: =COUNTIFS('Reconciliation Request'!$A$2:$A$755,Summary!$B23,'Reconciliation Request'!$B$2:$B$755,Summary!$C23,'Reconciliation Request'!$K$2:$K$755,T$3) -> 2
B24: Motor | C24: In-Life | D24: =COUNTIFS('Reconciliation Request'!$A$2:$A$755,Summary!$B24,'Reconciliation Request'!$B$2:$B$755,Summary!$C24,'Reconciliation Request'!$F$2:$F$755,"=1") -> 1 | E24: =COUNTIFS('Reconciliation Request'!$A$2:$A$755,Summary!$B24,'Reconciliation Request'!$B$2:$B$755,Summary!$C24,'Reconciliation Request'!$J$2:$J$755,Summary!E$3,'Reconciliation Request'!$F$2:$F$755,"=1") -> 0 | F24: =COUNTIFS('Reconciliation Request'!$A$2:$A$755,Summary!$B24,'Reconciliation Request'!$B$2:$B$755,Summary!$C24,'Reconciliation Request'!$J$2:$J$755,Summary!F$3,'Reconciliation Request'!$F$2:$F$755,"=1") -> 0 | G24: =COUNTIFS('Reconciliation Request'!$A$2:$A$755,Summary!$B24,'Reconciliation Request'!$B$2:$B$755,Summary!$C24,'Reconciliation Request'!$J$2:$J$755,Summary!G$3,'Reconciliation Request'!$F$2:$F$755,"=1") -> 0 | H24: =COUNTIFS('Reconciliation Request'!$A$2:$A$755,Summary!$B24,'Reconciliation Request'!$B$2:$B$755,Summary!$C24,'Reconciliation Request'!$J$2:$J$755,Summary!H$3,'Reconciliation Request'!$F$2:$F$755,"=1") -> 1 | J24: =COUNTIFS('Reconciliation Request'!$A$2:$A$755,Summary!$B24,'Reconciliation Request'!$B$2:$B$755,Summary!$C24,'Reconciliation Request'!$H$2:$H$755,">0",'Reconciliation Request'!$F$2:$F$755,"=1") -> 0 | K24: =I24/D24 -> 0 | L24: =J24/D24 -> 0 | M24: =COUNTIFS('Reconciliation Request'!$A$2:$A$755,Summary!$B24,'Reconciliation Request'!$B$2:$B$755,Summary!$C24,'Reconciliation Request'!$F$2:$F$755,"<>1") -> 5 | N24: =M24+D24 -> 6 | O24: =COUNTIFS('Reconciliation Request'!$A$2:$A$755,Summary!$B24,'Reconciliation Request'!$B$2:$B$755,Summary!$C24,'Reconciliation Request'!$H$2:$H$755,">0") -> 0 | P24: =N24-O24 -> 6 | Q24: =O24/N24 -> 0 | R24: =COUNTIFS('Reconciliation Request'!$A$2:$A$755,Summary!$B24,'Reconciliation Request'!$B$2:$B$755,Summary!$C24,'Reconciliation Request'!$K$2:$K$755,R$3) -> 0 | S24: =COUNTIFS('Reconciliation Request'!$A$2:$A$755,Summary!$B24,'Reconciliation Request'!$B$2:$B$755,Summary!$C24,'Reconciliation Request'!$K$2:$K$755,S$3) -> 6 | T24: =COUNTIFS('Reconciliation Request'!$A$2:$A$755,Summary!$B24,'Reconciliation Request'!$B$2:$B$755,Summary!$C24,'Reconciliation Request'!$K$2:$K$755,T$3) -> 0
B25: Motor | C25: Claims | D25: =COUNTIFS('Reconciliation Request'!$A$2:$A$755,Summary!$B25,'Reconciliation Request'!$B$2:$B$755,Summary!$C25,'Reconciliation Request'!$F$2:$F$755,"=1") -> 4 | E25: =COUNTIFS('Reconciliation Request'!$A$2:$A$755,Summary!$B25,'Reconciliation Request'!$B$2:$B$755,Summary!$C25,'Reconciliation Request'!$J$2:$J$755,Summary!E$3,'Reconciliation Request'!$F$2:$F$755,"=1") -> 0 | F25: =COUNTIFS('Reconciliation Request'!$A$2:$A$755,Summary!$B25,'Reconciliation Request'!$B$2:$B$755,Summary!$C25,'Reconciliation Request'!$J$2:$J$755,Summary!F$3,'Reconciliation Request'!$F$2:$F$755,"=1") -> 0 | G25: =COUNTIFS('Reconciliation Request'!$A$2:$A$755,Summary!$B25,'Reconciliation Request'!$B$2:$B$755,Summary!$C25,'Reconciliation Request'!$J$2:$J$755,Summary!G$3,'Reconciliation Request'!$F$2:$F$755,"=1") -> 0 | H25: =COUNTIFS('Reconciliation Request'!$A$2:$A$755,Summary!$B25,'Reconciliation Request'!$B$2:$B$755,Summary!$C25,'Reconciliation Request'!$J$2:$J$755,Summary!H$3,'Reconciliation Request'!$F$2:$F$755,"=1") -> 4 | I25: 0 | J25: 4 | K25: =I25/D25 -> 0 | L25: =J25/D25 -> 1 | M25: =COUNTIFS('Reconciliation Request'!$A$2:$A$755,Summary!$B25,'Reconciliation Request'!$B$2:$B$755,Summary!$C25,'Reconciliation Request'!$F$2:$F$755,"<>1") -> 7 | N25: =M25+D25 -> 11 | O25: =COUNTIFS('Reconciliation Request'!$A$2:$A$755,Summary!$B25,'Reconciliation Request'!$B$2:$B$755,Summary!$C25,'Reconciliation Request'!$H$2:$H$755,">0") -> 1 | P25: =N25-O25 -> 10 | Q25: =O25/N25 -> 0.090909091 | R25: =COUNTIFS('Reconciliation Request'!$A$2:$A$755,Summary!$B25,'Reconciliation Request'!$B$2:$B$755,Summary!$C25,'Reconciliation Request'!$K$2:$K$755,R$3) -> 4 | S25: =COUNTIFS('Reconciliation Request'!$A$2:$A$755,Summary!$B25,'Reconciliation Request'!$B$2:$B$755,Summary!$C25,'Reconciliation Request'!$K$2:$K$755,S$3) -> 6 | T25: =COUNTIFS('Reconciliation Request'!$A$2:$A$755,Summary!$B25,'Reconciliation Request'!$B$2:$B$755,Summary!$C25,'Reconciliation Request'!$K$2:$K$755,T$3) -> 1
B26: Motor | C26: Doc Request | D26: =COUNTIFS('Reconciliation Request'!$A$2:$A$755,Summary!$B26,'Reconciliation Request'!$B$2:$B$755,Summary!$C26,'Reconciliation Request'!$F$2:$F$755,"=1") -> 2 | E26: =COUNTIFS('Reconciliation Request'!$A$2:$A$755,Summary!$B26,'Reconciliation Request'!$B$2:$B$755,Summary!$C26,'Reconciliation Request'!$J$2:$J$755,Summary!E$3,'Reconciliation Request'!$F$2:$F$755,"=1") -> 0 | F26: =COUNTIFS('Reconciliation Request'!$A$2:$A$755,Summary!$B26,'Reconciliation Request'!$B$2:$B$755,Summary!$C26,'Reconciliation Request'!$J$2:$J$755,Summary!F$3,'Reconciliation Request'!$F$2:$F$755,"=1") -> 0 | G26: =COUNTIFS('Reconciliation Request'!$A$2:$A$755,Summary!$B26,'Reconciliation Request'!$B$2:$B$755,Summary!$C26,'Reconciliation Request'!$J$2:$J$755,Summary!G$3,'Reconciliation Request'!$F$2:$F$755,"=1") -> 0 | H26: =COUNTIFS('Reconciliation Request'!$A$2:$A$755,Summary!$B26,'Reconciliation Request'!$B$2:$B$755,Summary!$C26,'Reconciliation Request'!$J$2:$J$755,Summary!H$3,'Reconciliation Request'!$F$2:$F$755,"=1") -> 2 | I26: 0 | J26: =COUNTIFS('Reconciliation Request'!$A$2:$A$755,Summary!$B26,'Reconciliation Request'!$B$2:$B$755,Summary!$C26,'Reconciliation Request'!$H$2:$H$755,">0",'Reconciliation Request'!$F$2:$F$755,"=1") -> 2 | K26: =I26/D26 -> 0 | L26: =J26/D26 -> 1 | M26: =COUNTIFS('Reconciliation Request'!$A$2:$A$755,Summary!$B26,'Reconciliation Request'!$B$2:$B$755,Summary!$C26,'Reconciliation Request'!$F$2:$F$755,"<>1") -> 12 | N26: =M26+D26 -> 14 | O26: =COUNTIFS('Reconciliation Request'!$A$2:$A$755,Summary!$B26,'Reconciliation Request'!$B$2:$B$755,Summary!$C26,'Reconciliation Request'!$H$2:$H$755,">0") -> 6 | P26: =N26-O26 -> 8 | Q26: =O26/N26 -> 0.42857143 | R26: =COUNTIFS('Reconciliation Request'!$A$2:$A$755,Summary!$B26,'Reconciliation Request'!$B$2:$B$755,Summary!$C26,'Reconciliation Request'!$K$2:$K$755,R$3) -> 12 | S26: =COUNTIFS('Reconciliation Request'!$A$2:$A$755,Summary!$B26,'Reconciliation Request'!$B$2:$B$755,Summary!$C26,'Reconciliation Request'!$K$2:$K$755,S$3) -> 1 | T26: =COUNTIFS('Reconciliation Request'!$A$2:$A$755,Summary!$B26,'Reconciliation Request'!$B$2:$B$755,Summary!$C26,'Reconciliation Request'!$K$2:$K$755,T$3) -> 1
B27: Van | C27: MTA | D27: =COUNTIFS('Reconciliation Request'!$A$2:$A$755,Summary!$B27,'Reconciliation Request'!$B$2:$B$755,Summary!$C27,'Reconciliation Request'!$F$2:$F$755,"=1") -> 5 | E27: =COUNTIFS('Reconciliation Request'!$A$2:$A$755,Summary!$B27,'Reconciliation Request'!$B$2:$B$755,Summary!$C27,'Reconciliation Request'!$J$2:$J$755,Summary!E$3,'Reconciliation Request'!$F$2:$F$755,"=1") -> 0 | F27: =COUNTIFS('Reconciliation Request'!$A$2:$A$755,Summary!$B27,'Reconciliation Request'!$B$2:$B$755,Summary!$C27,'Reconciliation Request'!$J$2:$J$755,Summary!F$3,'Reconciliation Request'!$F$2:$F$755,"=1") -> 0 | G27: =COUNTIFS('Reconciliation Request'!$A$2:$A$755,Summary!$B27,'Reconciliation Request'!$B$2:$B$755,Summary!$C27,'Reconciliation Request'!$J$2:$J$755,Summary!G$3,'Reconciliation Request'!$F$2:$F$755,"=1") -> 0 | H27: =COUNTIFS('Reconciliation Request'!$A$2:$A$755,Summary!$B27,'Reconciliation Request'!$B$2:$B$755,Summary!$C27,'Reconciliation Request'!$J$2:$J$755,Summary!H$3,'Reconciliation Request'!$F$2:$F$755,"=1") -> 5 | I27: 2 | J27: 3 | K27: =I27/D27 -> 0.4 | L27: =J27/D27 -> 0.6 | M27: =COUNTIFS('Reconciliation Request'!$A$2:$A$755,Summary!$B27,'Reconciliation Request'!$B$2:$B$755,Summary!$C27,'Reconciliation Request'!$F$2:$F$755,"<>1") -> 39 | N27: =M27+D27 -> 44 | O27: =COUNTIFS('Reconciliation Request'!$A$2:$A$755,Summary!$B27,'Reconciliation Request'!$B$2:$B$755,Summary!$C27,'Reconciliation Request'!$H$2:$H$755,">0") -> 13 | P27: =N27-O27 -> 31 | Q27: =O27/N27 -> 0.29545455 | R27: =COUNTIFS('Reconciliation Request'!$A$2:$A$755,Summary!$B27,'Reconciliation Request'!$B$2:$B$755,Summary!$C27,'Reconciliation Request'!$K$2:$K$755,R$3) -> 21 | S27: =COUNTIFS('Reconciliation Request'!$A$2:$A$755,Summary!$B27,'Reconciliation Request'!$B$2:$B$755,Summary!$C27,'Reconciliation Request'!$K$2:$K$755,S$3) -> 20 | T27: =COUNTIFS('Reconciliation Request'!$A$2:$A$755,Summary!$B27,'Reconciliation Request'!$B$2:$B$755,Summary!$C27,'Reconciliation Request'!$K$2:$K$755,T$3) -> 3
B28: Van | C28: Cancellation | D28: =COUNTIFS('Reconciliation Request'!$A$2:$A$755,Summary!$B28,'Reconciliation Request'!$B$2:$B$755,Summary!$C28,'Reconciliation Request'!$F$2:$F$755,"=1") -> 3 | E28: =COUNTIFS('Reconciliation Request'!$A$2:$A$755,Summary!$B28,'Reconciliation Request'!$B$2:$B$755,Summary!$C28,'Reconciliation Request'!$J$2:$J$755,Summary!E$3,'Reconciliation Request'!$F$2:$F$755,"=1") -> 0 | F28: =COUNTIFS('Reconciliation Request'!$A$2:$A$755,Summary!$B28,'Reconciliation Request'!$B$2:$B$755,Summary!$C28,'Reconciliation Request'!$J$2:$J$755,Summary!F$3,'Reconciliation Request'!$F$2:$F$755,"=1") -> 0 | G28: =COUNTIFS('Reconciliation Request'!$A$2:$A$755,Summary!$B28,'Reconciliation Request'!$B$2:$B$755,Summary!$C28,'Reconciliation Request'!$J$2:$J$755,Summary!G$3,'Reconciliation Request'!$F$2:$F$755,"=1") -> 0 | H28: =COUNTIFS('Reconciliation Request'!$A$2:$A$755,Summary!$B28,'Reconciliation Request'!$B$2:$B$755,Summary!$C28,'Reconciliation Request'!$J$2:$J$755,Summary!H$3,'Reconciliation Request'!$F$2:$F$755,"=1") -> 3 | I28: 0 | J28: 3 | K28: =I28/D28 -> 0 | L28: =J28/D28 -> 1 | M28: =COUNTIFS('Reconciliation Request'!$A$2:$A$755,Summary!$B28,'Reconciliation Request'!$B$2:$B$755,Summary!$C28,'Reconciliation Request'!$F$2:$F$755,"<>1") -> 20 | N28: =M28+D28 -> 23 | O28: =COUNTIFS('Reconciliation Request'!$A$2:$A$755,Summary!$B28,'Reconciliation Request'!$B$2:$B$755,Summary!$C28,'Reconciliation Request'!$H$2:$H$755,">0") -> 6 | P28: =N28-O28 -> 17 | Q28: =O28/N28 -> 0.26086957 | R28: =COUNTIFS('Reconciliation Request'!$A$2:$A$755,Summary!$B28,'Reconciliation Request'!$B$2:$B$755,Summary!$C28,'Reconciliation Request'!$K$2:$K$755,R$3) -> 15 | S28: =COUNTIFS('Reconciliation Request'!$A$2:$A$755,Summary!$B28,'Reconciliation Request'!$B$2:$B$755,Summary!$C28,'Reconciliation Request'!$K$2:$K$755,S$3) -> 5 | T28: =COUNTIFS('Reconciliation Request'!$A$2:$A$755,Summary!$B28,'Reconciliation Request'!$B$2:$B$755,Summary!$C28,'Reconciliation Request'!$K$2:$K$755,T$3) -> 3
B29: Van | C29: Arrears | D29: =COUNTIFS('Reconciliation Request'!$A$2:$A$755,Summary!$B29,'Reconciliation Request'!$B$2:$B$755,Summary!$C29,'Reconciliation Request'!$F$2:$F$755,"=1") -> 2 | E29: =COUNTIFS('Reconciliation Request'!$A$2:$A$755,Summary!$B29,'Reconciliation Request'!$B$2:$B$755,Summary!$C29,'Reconciliation Request'!$J$2:$J$755,Summary!E$3,'Reconciliation Request'!$F$2:$F$755,"=1") -> 0 | F29: =COUNTIFS('Reconciliation Request'!$A$2:$A$755,Summary!$B29,'Reconciliation Request'!$B$2:$B$755,Summary!$C29,'Reconciliation Request'!$J$2:$J$755,Summary!F$3,'Reconciliation Request'!$F$2:$F$755,"=1") -> 0 | G29: =COUNTIFS('Reconciliation Request'!$A$2:$A$755,Summary!$B29,'Reconciliation Request'!$B$2:$B$755,Summary!$C29,'Reconciliation Request'!$J$2:$J$755,Summary!G$3,'Reconciliation Request'!$F$2:$F$755,"=1") -> 0 | H29: =COUNTIFS('Reconciliation Request'!$A$2:$A$755,Summary!$B29,'Reconciliation Request'!$B$2:$B$755,Summary!$C29,'Reconciliation Request'!$J$2:$J$755,Summary!H$3,'Reconciliation Request'!$F$2:$F$755,"=1") -> 2 | I29: 0 | J29: 2 | K29: =I29/D29 -> 0 | L29: =J29/D29 -> 1 | M29: =COUNTIFS('Reconciliation Request'!$A$2:$A$755,Summary!$B29,'Reconciliation Request'!$B$2:$B$755,Summary!$C29,'Reconciliation Request'!$F$2:$F$755,"<>1") -> 13 | N29: =M29+D29 -> 15 | O29: =COUNTIFS('Reconciliation Request'!$A$2:$A$755,Summary!$B29,'Reconciliation Request'!$B$2:$B$755,Summary!$C29,'Reconciliation Request'!$H$2:$H$755,">0") -> 4 | P29: =N29-O29 -> 11 | Q29: =O29/N29 -> 0.26666667 | R29: =COUNTIFS('Reconciliation Request'!$A$2:$A$755,Summary!$B29,'Reconciliation Request'!$B$2:$B$755,Summary!$C29,'Reconciliation Request'!$K$2:$K$755,R$3) -> 6 | S29: =COUNTIFS('Reconciliation Request'!$A$2:$A$755,Summary!$B29,'Reconciliation Request'!$B$2:$B$755,Summary!$C29,'Reconciliation Request'!$K$2:$K$755,S$3) -> 8 | T29: =COUNTIFS('Reconciliation Request'!$A$2:$A$755,Summary!$B29,'Reconciliation Request'!$B$2:$B$755,Summary!$C29,'Reconciliation Request'!$K$2:$K$755,T$3) -> 1
B30: Van | C30: In-Life | D30: =COUNTIFS('Reconciliation Request'!$A$2:$A$755,Summary!$B30,'Reconciliation Request'!$B$2:$B$755,Summary!$C30,'Reconciliation Request'!$F$2:$F$755,"=1") -> 1 | E30: =COUNTIFS('Reconciliation Request'!$A$2:$A$755,Summary!$B30,'Reconciliation Request'!$B$2:$B$755,Summary!$C30,'Reconciliation Request'!$J$2:$J$755,Summary!E$3,'Reconciliation Request'!$F$2:$F$755,"=1") -> 0 | F30: =COUNTIFS('Reconciliation Request'!$A$2:$A$755,Summary!$B30,'Reconciliation Request'!$B$2:$B$755,Summary!$C30,'Reconciliation Request'!$J$2:$J$755,Summary!F$3,'Reconciliation Request'!$F$2:$F$755,"=1") -> 0 | G30: =COUNTIFS('Reconciliation Request'!$A$2:$A$755,Summary!$B30,'Reconciliation Request'!$B$2:$B$755,Summary!$C30,'Reconciliation Request'!$J$2:$J$755,Summary!G$3,'Reconciliation Request'!$F$2:$F$755,"=1") -> 0 | H30: =COUNTIFS('Reconciliation Request'!$A$2:$A$755,Summary!$B30,'Reconciliation Request'!$B$2:$B$755,Summary!$C30,'Reconciliation Request'!$J$2:$J$755,Summary!H$3,'Reconciliation Request'!$F$2:$F$755,"=1") -> 1 | J30: =COUNTIFS('Reconciliation Request'!$A$2:$A$755,Summary!$B30,'Reconciliation Request'!$B$2:$B$755,Summary!$C30,'Reconciliation Request'!$H$2:$H$755,">0",'Reconciliation Request'!$F$2:$F$755,"=1") -> 0 | K30: =I30/D30 -> 0 | L30: =J30/D30 -> 0 | M30: =COUNTIFS('Reconciliation Request'!$A$2:$A$755,Summary!$B30,'Reconciliation Request'!$B$2:$B$755,Summary!$C30,'Reconciliation Request'!$F$2:$F$755,"<>1") -> 0 | N30: =M30+D30 -> 1 | O30: =COUNTIFS('Reconciliation Request'!$A$2:$A$755,Summary!$B30,'Reconciliation Request'!$B$2:$B$755,Summary!$C30,'Reconciliation Request'!$H$2:$H$755,">0") -> 0 | P30: =N30-O30 -> 1 | Q30: =O30/N30 -> 0 | R30: =COUNTIFS('Reconciliation Request'!$A$2:$A$755,Summary!$B30,'Reconciliation Request'!$B$2:$B$755,Summary!$C30,'Reconciliation Request'!$K$2:$K$755,R$3) -> 0 | S30: =COUNTIFS('Reconciliation Request'!$A$2:$A$755,Summary!$B30,'Reconciliation Request'!$B$2:$B$755,Summary!$C30,'Reconciliation Request'!$K$2:$K$755,S$3) -> 1 | T30: =COUNTIFS('Reconciliation Request'!$A$2:$A$755,Summary!$B30,'Reconciliation Request'!$B$2:$B$755,Summary!$C30,'Reconciliation Request'!$K$2:$K$755,T$3) -> 0
B31: Van | C31: Claims | D31: =COUNTIFS('Reconciliation Request'!$A$2:$A$755,Summary!$B31,'Reconciliation Request'!$B$2:$B$755,Summary!$C31,'Reconciliation Request'!$F$2:$F$755,"=1") -> 3 | E31: =COUNTIFS('Reconciliation Request'!$A$2:$A$755,Summary!$B31,'Reconciliation Request'!$B$2:$B$755,Summary!$C31,'Reconciliation Request'!$J$2:$J$755,Summary!E$3,'Reconciliation Request'!$F$2:$F$755,"=1") -> 0 | F31: =COUNTIFS('Reconciliation Request'!$A$2:$A$755,Summary!$B31,'Reconciliation Request'!$B$2:$B$755,Summary!$C31,'Reconciliation Request'!$J$2:$J$755,Summary!F$3,'Reconciliation Request'!$F$2:$F$755,"=1") -> 0 | G31: =COUNTIFS('Reconciliation Request'!$A$2:$A$755,Summary!$B31,'Reconciliation Request'!$B$2:$B$755,Summary!$C31,'Reconciliation Request'!$J$2:$J$755,Summary!G$3,'Reconciliation Request'!$F$2:$F$755,"=1") -> 0 | H31: =COUNTIFS('Reconciliation Request'!$A$2:$A$755,Summary!$B31,'Reconciliation Request'!$B$2:$B$755,Summary!$C31,'Reconciliation Request'!$J$2:$J$755,Summary!H$3,'Reconciliation Request'!$F$2:$F$755,"=1") -> 3 | I31: 0 | J31: 3 | K31: =I31/D31 -> 0 | L31: =J31/D31 -> 1 | M31: =COUNTIFS('Reconciliation Request'!$A$2:$A$755,Summary!$B31,'Reconciliation Request'!$B$2:$B$755,Summary!$C31,'Reconciliation Request'!$F$2:$F$755,"<>1") -> 8 | N31: =M31+D31 -> 11 | O31: =COUNTIFS('Reconciliation Request'!$A$2:$A$755,Summary!$B31,'Reconciliation Request'!$B$2:$B$755,Summary!$C31,'Reconciliation Request'!$H$2:$H$755,">0") -> 1 | P31: =N31-O31 -> 10 | Q31: =O31/N31 -> 0.090909091 | R31: =COUNTIFS('Reconciliation Request'!$A$2:$A$755,Summary!$B31,'Reconciliation Request'!$B$2:$B$755,Summary!$C31,'Reconciliation Request'!$K$2:$K$755,R$3) -> 2 | S31: =COUNTIFS('Reconciliation Request'!$A$2:$A$755,Summary!$B31,'Reconciliation Request'!$B$2:$B$755,Summary!$C31,'Reconciliation Request'!$K$2:$K$755,S$3) -> 7 | T31: =COUNTIFS('Reconciliation Request'!$A$2:$A$755,Summary!$B31,'Reconciliation Request'!$B$2:$B$755,Summary!$C31,'Reconciliation Request'!$K$2:$K$755,T$3) -> 2
B32: Van | C32: Doc Request | D32: =COUNTIFS('Reconciliation Request'!$A$2:$A$755,Summary!$B32,'Reconciliation Request'!$B$2:$B$755,Summary!$C32,'Reconciliation Request'!$F$2:$F$755,"=1") -> 2 | E32: =COUNTIFS('Reconciliation Request'!$A$2:$A$755,Summary!$B32,'Reconciliation Request'!$B$2:$B$755,Summary!$C32,'Reconciliation Request'!$J$2:$J$755,Summary!E$3,'Reconciliation Request'!$F$2:$F$755,"=1") -> 0 | F32: =COUNTIFS('Reconciliation Request'!$A$2:$A$755,Summary!$B32,'Reconciliation Request'!$B$2:$B$755,Summary!$C32,'Reconciliation Request'!$J$2:$J$755,Summary!F$3,'Reconciliation Request'!$F$2:$F$755,"=1") -> 0 | G32: =COUNTIFS('Reconciliation Request'!$A$2:$A$755,Summary!$B32,'Reconciliation Request'!$B$2:$B$755,Summary!$C32,'Reconciliation Request'!$J$2:$J$755,Summary!G$3,'Reconciliation Request'!$F$2:$F$755,"=1") -> 0 | H32: =COUNTIFS('Reconciliation Request'!$A$2:$A$755,Summary!$B32,'Reconciliation Request'!$B$2:$B$755,Summary!$C32,'Reconciliation Request'!$J$2:$J$755,Summary!H$3,'Reconciliation Request'!$F$2:$F$755,"=1") -> 2 | I32: 0 | J32: =COUNTIFS('Reconciliation Request'!$A$2:$A$755,Summary!$B32,'Reconciliation Request'!$B$2:$B$755,Summary!$C32,'Reconciliation Request'!$H$2:$H$755,">0",'Reconciliation Request'!$F$2:$F$755,"=1") -> 2 | K32: =I32/D32 -> 0 | L32: =J32/D32 -> 1 | M32: =COUNTIFS('Reconciliation Request'!$A$2:$A$755,Summary!$B32,'Reconciliation Request'!$B$2:$B$755,Summary!$C32,'Reconciliation Request'!$F$2:$F$755,"<>1") -> 12 | N32: =M32+D32 -> 14 | O32: =COUNTIFS('Reconciliation Request'!$A$2:$A$755,Summary!$B32,'Reconciliation Request'!$B$2:$B$755,Summary!$C32,'Reconciliation Request'!$H$2:$H$755,">0") -> 6 | P32: =N32-O32 -> 8 | Q32: =O32/N32 -> 0.42857143 | R32: =COUNTIFS('Reconciliation Request'!$A$2:$A$755,Summary!$B32,'Reconciliation Request'!$B$2:$B$755,Summary!$C32,'Reconciliation Request'!$K$2:$K$755,R$3) -> 12 | S32: =COUNTIFS('Reconciliation Request'!$A$2:$A$755,Summary!$B32,'Reconciliation Request'!$B$2:$B$755,Summary!$C32,'Reconciliation Request'!$K$2:$K$755,S$3) -> 1 | T32: =COUNTIFS('Reconciliation Request'!$A$2:$A$755,Summary!$B32,'Reconciliation Request'!$B$2:$B$755,Summary!$C32,'Reconciliation Request'!$K$2:$K$755,T$3) -> 1
B33: Travel | C33: MTA | D33: =COUNTIFS('Reconciliation Request'!$A$2:$A$755,Summary!$B33,'Reconciliation Request'!$B$2:$B$755,Summary!$C33,'Reconciliation Request'!$F$2:$F$755,"=1") -> 3 | E33: =COUNTIFS('Reconciliation Request'!$A$2:$A$755,Summary!$B33,'Reconciliation Request'!$B$2:$B$755,Summary!$C33,'Reconciliation Request'!$J$2:$J$755,Summary!E$3,'Reconciliation Request'!$F$2:$F$755,"=1") -> 0 | F33: =COUNTIFS('Reconciliation Request'!$A$2:$A$755,Summary!$B33,'Reconciliation Request'!$B$2:$B$755,Summary!$C33,'Reconciliation Request'!$J$2:$J$755,Summary!F$3,'Reconciliation Request'!$F$2:$F$755,"=1") -> 0 | G33: =COUNTIFS('Reconciliation Request'!$A$2:$A$755,Summary!$B33,'Reconciliation Request'!$B$2:$B$755,Summary!$C33,'Reconciliation Request'!$J$2:$J$755,Summary!G$3,'Reconciliation Request'!$F$2:$F$755,"=1") -> 0 | H33: =COUNTIFS('Reconciliation Request'!$A$2:$A$755,Summary!$B33,'Reconciliation Request'!$B$2:$B$755,Summary!$C33,'Reconciliation Request'!$J$2:$J$755,Summary!H$3,'Reconciliation Request'!$F$2:$F$755,"=1") -> 3 | I33: 3 | J33: =COUNTIFS('Reconciliation Request'!$A$2:$A$755,Summary!$B33,'Reconciliation Request'!$B$2:$B$755,Summary!$C33,'Reconciliation Request'!$H$2:$H$755,">0",'Reconciliation Request'!$F$2:$F$755,"=1") -> 0 | K33: =I33/D33 -> 1 | L33: =J33/D33 -> 0 | M33: =COUNTIFS('Reconciliation Request'!$A$2:$A$755,Summary!$B33,'Reconciliation Request'!$B$2:$B$755,Summary!$C33,'Reconciliation Request'!$F$2:$F$755,"<>1") -> 5 | N33: =M33+D33 -> 8 | O33: =COUNTIFS('Reconciliation Request'!$A$2:$A$755,Summary!$B33,'Reconciliation Request'!$B$2:$B$755,Summary!$C33,'Reconciliation Request'!$H$2:$H$755,">0") -> 0 | P33: =N33-O33 -> 8 | Q33: =O33/N33 -> 0 | R33: =COUNTIFS('Reconciliation Request'!$A$2:$A$755,Summary!$B33,'Reconciliation Request'!$B$2:$B$755,Summary!$C33,'Reconciliation Request'!$K$2:$K$755,R$3) -> 0 | S33: =COUNTIFS('Reconciliation Request'!$A$2:$A$755,Summary!$B33,'Reconciliation Request'!$B$2:$B$755,Summary!$C33,'Reconciliation Request'!$K$2:$K$755,S$3) -> 7 | T33: =COUNTIFS('Reconciliation Request'!$A$2:$A$755,Summary!$B33,'Reconciliation Request'!$B$2:$B$755,Summary!$C33,'Reconciliation Request'!$K$2:$K$755,T$3) -> 1
B34: Travel | C34: Cancellation | D34: =COUNTIFS('Reconciliation Request'!$A$2:$A$755,Summary!$B34,'Reconciliation Request'!$B$2:$B$755,Summary!$C34,'Reconciliation Request'!$F$2:$F$755,"=1") -> 3 | E34: =COUNTIFS('Reconciliation Request'!$A$2:$A$755,Summary!$B34,'Reconciliation Request'!$B$2:$B$755,Summary!$C34,'Reconciliation Request'!$J$2:$J$755,Summary!E$3,'Reconciliation Request'!$F$2:$F$755,"=1") -> 0 | F34: =COUNTIFS('Reconciliation Request'!$A$2:$A$755,Summary!$B34,'Reconciliation Request'!$B$2:$B$755,Summary!$C34,'Reconciliation Request'!$J$2:$J$755,Summary!F$3,'Reconciliation Request'!$F$2:$F$755,"=1") -> 0 | G34: =COUNTIFS('Reconciliation Request'!$A$2:$A$755,Summary!$B34,'Reconciliation Request'!$B$2:$B$755,Summary!$C34,'Reconciliation Request'!$J$2:$J$755,Summary!G$3,'Reconciliation Request'!$F$2:$F$755,"=1") -> 0 | H34: =COUNTIFS('Reconciliation Request'!$A$2:$A$755,Summary!$B34,'Reconciliation Request'!$B$2:$B$755,Summary!$C34,'Reconciliation Request'!$J$2:$J$755,Summary!H$3,'Reconciliation Request'!$F$2:$F$755,"=1") -> 3 | I34: 2 | J34: 1 | K34: =I34/D34 -> 0.66666667 | L34: =J34/D34 -> 0.33333333 | M34: =COUNTIFS('Reconciliation Request'!$A$2:$A$755,Summary!$B34,'Reconciliation Request'!$B$2:$B$755,Summary!$C34,'Reconciliation Request'!$F$2:$F$755,"<>1") -> 4 | N34: =M34+D34 -> 7 | O34: =COUNTIFS('Reconciliation Request'!$A$2:$A$755,Summary!$B34,'Reconciliation Request'!$B$2:$B$755,Summary!$C34,'Reconciliation Request'!$H$2:$H$755,">0") -> 0 | P34: =N34-O34 -> 7 | Q34: =O34/N34 -> 0 | R34: =COUNTIFS('Reconciliation Request'!$A$2:$A$755,Summary!$B34,'Reconciliation Request'!$B$2:$B$755,Summary!$C34,'Reconciliation Request'!$K$2:$K$755,R$3) -> 1 | S34: =COUNTIFS('Reconciliation Request'!$A$2:$A$755,Summary!$B34,'Reconciliation Request'!$B$2:$B$755,Summary!$C34,'Reconciliation Request'!$K$2:$K$755,S$3) -> 6 | T34: =COUNTIFS('Reconciliation Request'!$A$2:$A$755,Summary!$B34,'Reconciliation Request'!$B$2:$B$755,Summary!$C34,'Reconciliation Request'!$K$2:$K$755,T$3) -> 0
B35: Travel | C35: Claims | D35: =COUNTIFS('Reconciliation Request'!$A$2:$A$755,Summary!$B35,'Reconciliation Request'!$B$2:$B$755,Summary!$C35,'Reconciliation Request'!$F$2:$F$755,"=1") -> 2 | E35: =COUNTIFS('Reconciliation Request'!$A$2:$A$755,Summary!$B35,'Reconciliation Request'!$B$2:$B$755,Summary!$C35,'Reconciliation Request'!$J$2:$J$755,Summary!E$3,'Reconciliation Request'!$F$2:$F$755,"=1") -> 0 | F35: =COUNTIFS('Reconciliation Request'!$A$2:$A$755,Summary!$B35,'Reconciliation Request'!$B$2:$B$755,Summary!$C35,'Reconciliation Request'!$J$2:$J$755,Summary!F$3,'Reconciliation Request'!$F$2:$F$755,"=1") -> 0 | G35: =COUNTIFS('Reconciliation Request'!$A$2:$A$755,Summary!$B35,'Reconciliation Request'!$B$2:$B$755,Summary!$C35,'Reconciliation Request'!$J$2:$J$755,Summary!G$3,'Reconciliation Request'!$F$2:$F$755,"=1") -> 0 | H35: =COUNTIFS('Reconciliation Request'!$A$2:$A$755,Summary!$B35,'Reconciliation Request'!$B$2:$B$755,Summary!$C35,'Reconciliation Request'!$J$2:$J$755,Summary!H$3,'Reconciliation Request'!$F$2:$F$755,"=1") -> 2 | I35: 2 | J35: =COUNTIFS('Reconciliation Request'!$A$2:$A$755,Summary!$B35,'Reconciliation Request'!$B$2:$B$755,Summary!$C35,'Reconciliation Request'!$H$2:$H$755,">0",'Reconciliation Request'!$F$2:$F$755,"=1") -> 0 | K35: =I35/D35 -> 1 | L35: =J35/D35 -> 0 | M35: =COUNTIFS('Reconciliation Request'!$A$2:$A$755,Summary!$B35,'Reconciliation Request'!$B$2:$B$755,Summary!$C35,'Reconciliation Request'!$F$2:$F$755,"<>1") -> 4 | N35: =M35+D35 -> 6 | O35: =COUNTIFS('Reconciliation Request'!$A$2:$A$755,Summary!$B35,'Reconciliation Request'!$B$2:$B$755,Summary!$C35,'Reconciliation Request'!$H$2:$H$755,">0") -> 0 | P35: =N35-O35 -> 6 | Q35: =O35/N35 -> 0 | R35: =COUNTIFS('Reconciliation Request'!$A$2:$A$755,Summary!$B35,'Reconciliation Request'!$B$2:$B$755,Summary!$C35,'Reconciliation Request'!$K$2:$K$755,R$3) -> 0 | S35: =COUNTIFS('Reconciliation Request'!$A$2:$A$755,Summary!$B35,'Reconciliation Request'!$B$2:$B$755,Summary!$C35,'Reconciliation Request'!$K$2:$K$755,S$3) -> 6 | T35: =COUNTIFS('Reconciliation Request'!$A$2:$A$755,Summary!$B35,'Reconciliation Request'!$B$2:$B$755,Summary!$C35,'Reconciliation Request'!$K$2:$K$755,T$3) -> 0
C38: Data Gaps
C39: Loans
C40: MTA Gaps
C41: Cancellations
C42: Van
C43: Travel
C46: Doc Request | D46: What defines the record as customer requested than business process initiated?
C47: Cancellation reversed | D47: What is the appropriate logic / tables that confirm a cancellation has been reversed on a policy? .. Over time // cross month end boundaries / Sl03 )lowish volumes) | K47: rebook vs reinstatement
C48: Additional or return / refund of premium | D48: How we can identify from relay that additional premium is requested from customer (and is paid) or refunding of additional premium has happened? | K48: Endorsements (fee or premium) / returns (fees / premium)
C49: BO Agent Quotes | D49: We see multiple records per session / how does that work?
C50: Van | D50: MTA information -- detailed data / payment info available in Relay?

Sheet Reconciliation Request
A1: Product | B1: Journey | C1: step_id | D1: Step | E1: Source for recon | F1: Priority | G1: Reporting - Volumes | H1: Fabric Volumes | I1: %Variance | J1: Status | K1: Is data available? | L1: Status Description | M1: Source | N1: Notes | O1: Notes-Chill DataTeam
A2: Motor | B2: Acquisition | C2: A0.C | D2: Entry channel | K2: No | S2: Reconciled
A3: Motor | B3: Acquisition | C3: A0.C.F1 | D3: Existing client rebooked and written as new business | J3: Under Investigation | K3: Yes | N3: Got logic from Data team but needs work to resolve | S3: Reconciled within acceptable variance
A4: Motor | B4: Acquisition | C4: A1 | D4: Quote initiated ONLINE | E4: SL10 | F4: 1 | G4: 79441 | H4: 79689 | I4: =1-(H4/G4) -> -0.0031218137 | J4: Reconciled within acceptable variance | K4: Yes | M4: MFQ | N4: SL10 -Total Quotes All - no filters applied | O4: No action for DataTeam | S4: Under Investigation
A5: Motor | B5: Acquisition | C5: A1.E1 | D5: Service retrieve | J5: Source Not Accessible (yet) | K5: No | M5: SendGrid | N5: Service Message so all quotes are assumed to receive service retrieve message - Will be resolved when Sendgrid data is extracted | S5: No report data supplied
A6: Motor | B6: Acquisition | C6: A0 | D6: Straight into the CALL CENTRE | F6: 1 | G6: 7157 | H6: 6977 | I6: =1-H6/G6 -> 0.025150203 | J6: Reconciled with Reasons supplied | K6: Yes | M6: Genesys | N6: WebAssist - 1202 -- Unique in Fabric - Nikita to check transformaiton steps / Data team to review code and confirm - use that INBOUND genesys logic 765 are removed from SQL09 matching after they were GDPR-ed We can confirm 3557 is true as of end of July (3rd of August) | O6: Shared script in chat. | S6: Not Started
A7: Motor | B7: Acquisition | C7: A0.1 | D7: Site landing page viewed | J7: Data unstructured but available | K7: No | M7: GA4 / MFQ | N7: List of landing pages to be agreed | S7: Data unstructured but available
A8: Motor | B8: Acquisition | C8: A0.F1 | D8: Call wait time, or fails to make contact | G8: 841 | H8: 841 | J8: Reconciled | K8: Yes | M8: Genesys | N8: abandoned calls -- To include anyone who is waiting for more than 5 minutes | S8: Reconciled with Reasons supplied
A9: Motor | B9: Acquisition | C9: A2 | D9: Customer details complete | H9: 61876 | J9: No report data supplied | K9: Yes | M9: MFQ | S9: New Source
A10: Motor | B10: Acquisition | C10: A2.F1 | D10: Drop off before completing the details | H10: 17813 | J10: No report data supplied | K10: Yes | M10: MFQ | S10: Source Not Accessible (yet)
A11: Motor | B11: Acquisition | C11: A2.E1 | D11: This year retrieve (TYR) | H11: 46375 | J11: No report data supplied | K11: Yes | M11: CRM | N11: Total SMS + Email sends | S11: Identify Source
A12: Motor | B12: Acquisition | C12: A2.E1.F1 | D12: Retrieve link does not connect, or the price has changed | J12: No report data supplied | K12: No | N12: Retrieve failures not abservable in GA4 - MFQ linked data. Raw GA4 is needed for that | S12: Yes
A13: Motor | B13: Acquisition | C13: A2.E1.F2 | D13: Price has moved since the customer saw it | J13: No report data supplied | K13: No | S13: No
A14: Motor | B14: Acquisition | C14: A3 | D14: Customer gets a price | E14: SL10 | F14: 1 | G14: 35918 | H14: 35551 | I14: =1-H14/G14 -> 0.010217718 | J14: Reconciled within acceptable variance | K14: Yes | M14: MFQ | O14: No action for DataTeam | S14: Not a Data Point
A15: Motor | B15: Acquisition | C15: A3.F1 | D15: No price returned, told to call us | H15: 943 | J15: No report data supplied | K15: Yes | M15: MFQ | N15: Step 5 completed in first attempt + Insurer quoted flag = N from SL10 - If further filters to bne applied, please confirm
A16: Motor | B16: Acquisition | C16: A3.B1 | D16: Quote retrieve and re-quote cycles | H16: 16287 | J16: No report data supplied | K16: Yes | M16: MFQ
A17: Motor | B17: Acquisition | C17: A3.B1.F1 | D17: Number of cycles through A1 to A3 | K17: Yes | N17: how to show cycles here ? Some quotes get retrieved more often than some (retrieval count) Event Stream will capture the cycles but presenting the number here is not clean
A18: Motor | B18: Acquisition | C18: A3.E1 | D18: Outbound sales callback | H18: 24 | J18: No report data supplied | K18: Yes | M18: Genesys | N18: very low
A19: Motor | B19: Acquisition | C19: A3.E2 | D19: In-flight price improvement: promo code, fee reduction, or agent alters a web-assisted quote | J19: No report data supplied | K19: No | N19: Data not captured
A20: Motor | B20: Acquisition | C20: A4a | D20: Customer buys ONLINE | E20: SL10 | F20: 1 | G20: 2587 | H20: 2525 | I20: =1-H20/G20 -> 0.023965984 | J20: Reconciled with Reasons supplied | K20: Yes | M20: MFQ Payments | N20: SL10 - MFQ Sales - no filters applied - 2946 2587 in SL06 - the difference is the sales getting assigned to renewals (against 3010 to 2587) and 66 QQGuids are from June | O20: No action for DataTeam
A21: Motor | B21: Acquisition | C21: A4b | D21: Agent quotes and converts on the CALL | E21: SL06 | F21: 1 | G21: 685 | H21: 685 | I21: =1-H21/G21 -> 0 | J21: Reconciled | K21: Yes | M21: Relay derivation / Realex not available | N21: Nikita - to provide matching logic - use that INBOUND genesys logic Not exactly from Genesys but inferred from Relay | O21: Shared logic on chat.
A22: Motor | B22: Acquisition | C22: A4.F1 | D22: Web assist: starts online, then calls to complete | G22: 671 | H22: 671 | I22: =1-H22/G22 -> 0 | J22: Reconciled | K22: Yes | M22: MFQ - Relay derivation / Realex not available | N22: Not exactly from Genesys but inferred from Relay
A23: Motor | B23: Acquisition | C23: A4.F2 | D23: Customer buys the wrong policy. They cannot evidence NCD - Repurchase after a failed purchase - doc validation | J23: No report data supplied | K23: No
A24: Motor | B24: Acquisition | C24: A4b.O1 | D24: Not proceeded with | H24: =H6-H21-H22-H8 -> 4780 | J24: No report data supplied | K24: Yes | M24: MFQ
A25: Motor | B25: Acquisition | C25: A5a | D25: Payment attempted ONLINE | H25: 4058 | J25: No report data supplied | K25: Yes | M25: MFQ Payments | N25: Refers to online only (same person multiple Guids potentially)
A26: Motor | B26: Acquisition | C26: A5b | D26: Payment attempted on the CALL | H26: - | J26: Source Not Accessible (yet) | K26: No | M26: Realex Potentially | N26: not recorded anywhere we have access to - Global Realex might have -- new source
A27: Motor | B27: Acquisition | C27: A5.F1 | D27: Payment failed | H27: 1586 | J27: No report data supplied | K27: Yes | M27: MFQ Payments | N27: a failure can be successful later
A28: Motor | B28: Acquisition | C28: A5.B1 | D28: Loan setup with the finance provider | F28: 1 | H28: 1198 | J28: No report data supplied | K28: Yes | L28: Chill Data Team supplied some info. UAT not complete on Chill Side. Rapier working on reconciliation | M28: MFQ Payments | N28: Nikita - to provide the historic DD logic (diaries) - PC pipeline going forwards Online finance request is captured. Call centre loan request is not captured From MFQ Payments options - No followup info | O28: Shared ODS table names on chat and PaymentType logic for historic data is still in UAT.
A29: Motor | B29: Acquisition | C29: A5.B1.F1 | D29: Mandate not signed, or the loan is not set up | H29: - | J29: No report data supplied | K29: No | N29: Loan information not available
A30: Motor | B30: Acquisition | C30: A5.B1.F2 | D30: Time taken to complete loan setup | J30: No report data supplied | K30: No | N30: Loan information not available
A31: Motor | B31: Acquisition | C31: A5.B1.F3 | D31: Repeat visits to the loan setup step | J31: No report data supplied | K31: No | N31: Loan information not available
A32: Motor | B32: Acquisition | C32: A5.B2 | D32: Submit docs in the online journey | J32: No report data supplied | K32: No | N32: Loan information not available
A33: Motor | B33: Acquisition | C33: A5.B3 | D33: Credit worthiness check | J33: No report data supplied | K33: No | N33: Loan information not available
A34: Motor | B34: Acquisition | C34: A5.B3.F1 | D34: Credit check failed | J34: No report data supplied | K34: No | N34: Loan information not available
A35: Motor | B35: Acquisition | C35: A5.1 | D35: Purchase confirmation sent | G35: 2890 | H35: 2890 | I35: 0 | J35: Reconciled | K35: Yes | M35: CRM (XP / CDA) | N35: 2890 (Email) / 3623 (SMS) sql07 - cda - SMS Message Delivered / Email is XP 'Hi, thanks for choosing us, we really appreciate it.%be sending out your welcome pack shortly. Thanks, Chill Insurance.' 2890 online bind confirmation
A36: Motor | B36: Acquisition | C36: A6 | D36: Documents requested | F36: 1 | G36: 2580 | H36: 2580 | I36: 0 | J36: Reconciled | K36: Yes | M36: Relay Events | O36: No tableau figures provided, please provide or state not available
A37: Motor | B37: Acquisition | C37: A6.F1 | D37: Chases before the customer submits, and documents never submitted | F37: 1 | G37: 1178 | H37: 1178 | I37: 0 | J37: Reconciled | K37: Yes | M37: CRM (XP) | N37: Nikita - to provide document chase diaries / Vijay Ewan to do use EXP_MyChill_Chase_Daily_Snapshot_MotorVan Nikita supplied the document diary table - this is a live table and there is no history also the related campaigns are not in xp response tables -- further question for Nikita - Future data can be extracted but past history is not possible as of now - Data Team to help to investigate | O37: Shared on chat - Home, Motor, and Van chase diary list , table name , join criteria and SP for more details. Rapier to confirm the diary names with Darragh. Shared snapshot table name from DWH.
A38: Motor | B38: Acquisition | C38: A6.F2 | D38: Customer has no smartphone, so document upload falls back to a manual process | J38: No report data supplied | K38: No | N38: not captured
A39: Motor | B39: Acquisition | C39: A6.B1 | D39: Document intake | H39: 1646 | J39: No report data supplied | K39: Yes | M39: MyChill Uploads | N39: Nikita - to provide document chase diaries / Vijay Ewan to do Nikita supplied the document diary table - this is a live table and there is no history also the related campaigns are not in xp response tables -- further question for Nikita - Future data can be extracted but past history is not possible as of now - Data Team to help to investigate | O39: Shared on chat - Home, Motor, and Van chase diary list , table name , join criteria and SP for more details. Rapier to confirm the diary names with Darragh. Shared snapshot table name from DWH.
A40: Motor | B40: Acquisition | C40: A6.B1.F1 | D40: Documents never submitted, policy at risk. Bites A5a customers hardest | H40: 1178 | J40: No report data supplied | K40: Yes | M40: CRM (XP) / Relay Events
A41: Motor | B41: Acquisition | C41: A7 | D41: Cert and disc sent | F41: 1 | H41: 3924 | J41: No report data supplied | K41: Yes | M41: Relay Events | N41: Vijay to send samples of Sold Policies -- with and without C&D sent . Anna to check with business | O41: Pending with Vijay
A42: Motor | B42: Acquisition | C42: A7.F1 | D42: Non-arrival, and time taken to receive | H42: 28 | J42: No report data supplied | K42: Yes | M42: Genesys (but not direct) | N42: duplicates sent
A43: Motor | B43: Acquisition | C43: A7.B1 | D43: Cert and disc dispatch | H43: 3918 | J43: No report data supplied | K43: Yes | M43: Relay Events | N43: total sends
A44: Motor | B44: Acquisition | C44: A3.B1.1 | D44: Quote retrieved or iterated | F44: 1 | G44: 15231 | H44: 14919 | I44: =1-H44/G44 -> 0.020484538 | J44: Reconciled with Reasons supplied | K44: Yes | M44: MFQ | N44: include quotes started in previous month but retrieved in the current month for reconciliation - / Vijay Ewan to do | O44: No action for DataTeam
A45: Motor | B45: Acquisition | C45: A3.B1.2 | D45: Purchase | F45: 1 | G45: 1485 | H45: 1507 | I45: =1-H45/G45 -> -0.014814815 | J45: Reconciled within acceptable variance | K45: Yes | M45: MFQ | N45: assuming one quote per converted policy as successful) | O45: No action for DataTeam
A46: Motor | B46: Acquisition | C46: A3.B1.O1 | D46: Abandoned or expired | H46: =H44-H45 -> 13412 | J46: No report data supplied | K46: Yes | N46: Quotes (
A47: Motor | B47: Acquisition | C47: A5.B1.1 | D47: Loan initiated with the finance provider | J47: No report data supplied | K47: No | N47: Not available at this level - Discussed
A48: Motor | B48: Acquisition | C48: A5.B1.2 | D48: Finance application link sent | J48: No report data supplied | K48: No
A49: Motor | B49: Acquisition | C49: A5.B1.3 | D49: Customer completes the application and DD setup | J49: No report data supplied | K49: No
A50: Motor | B50: Acquisition | C50: A5.B1.4 | D50: Chase, inconsistency resolution | J50: No report data supplied | K50: No
A51: Motor | B51: Acquisition | C51: A5.B1.5 | D51: Payment confirmed on the loan path | J51: No report data supplied | K51: No
A52: Motor | B52: Acquisition | C52: A5.B1.O1 | D52: Switched to pay in full | J52: No report data supplied | K52: No
A53: Motor | B53: Acquisition | C53: A5.B1.O2 | D53: Cancellation, loan setup failed | J53: No report data supplied | K53: No
A54: Motor | B54: Acquisition | C54: A5.B1.PC1 | D54: Loan initiated, integrated at the quote stage | J54: No report data supplied | K54: No
A55: Motor | B55: Acquisition | C55: A5.B1.PC2 | D55: Finance application link sent by Premium Credit | J55: No report data supplied | K55: No
A56: Motor | B56: Acquisition | C56: A5.B1.PC3 | D56: Customer completes the self service application | J56: No report data supplied | K56: No
A57: Motor | B57: Acquisition | C57: A5.B1.PC4 | D57: Document chase, provider and Chill | J57: No report data supplied | K57: No
A58: Motor | B58: Acquisition | C58: A5.B1.PC5 | D58: Payment confirmed on the loan path | J58: No report data supplied | K58: No
A59: Motor | B59: Acquisition | C59: A5.B1.PC.O1 | D59: Switched to pay in full, or cancellation | J59: No report data supplied | K59: No
A60: Motor | B60: Acquisition | C60: A6.B1.1 | D60: Document request issued | H60: 2580 | J60: No report data supplied | K60: Yes | M60: Relay Events | N60: Should this align with A6 ?
A61: Motor | B61: Acquisition | C61: A6.B1.2 | D61: Customer submits documents | H61: 1646 | J61: No report data supplied | K61: Yes | M61: MyChill Uploads | N61: we captured until 6th august - think it goes further -- this is from mychill
A62: Motor | B62: Acquisition | C62: A6.B1.4 | D62: Chase, first reminder | H62: 9662 | J62: No report data supplied | K62: Yes | M62: CRM XP
A63: Motor | B63: Acquisition | C63: A6.B1.5 | D63: Chase, escalation | H63: 4345 | J63: No report data supplied | K63: Yes | M63: CRM XP | N63: ongoing (we collected up to 6th August) - from Relay Events
A64: Motor | B64: Acquisition | C64: A6.B1.3 | D64: Documents validated | H64: 1088 | J64: No report data supplied | K64: Yes | M64: MyChill Status | N64: 1088 accepted / 456 rejected (not mutually exclusive)
A65: Motor | B65: Acquisition | C65: A6.B1.O1 | D65: Cancellation, non-receipt | H65: 107 | J65: No report data supplied | K65: Yes | M65: Relay Events
A66: Motor | B66: Acquisition | C66: A6.B1.6 | D66: Documents received and validated | H66: 1088 | J66: No report data supplied | K66: Yes | M66: MyChill Status | N66: How is this different from A6.B1.3 ?
A67: Motor | B67: Acquisition | C67: A7.B1.1 | D67: Cert and disc dispatched | H67: 3918 | J67: No report data supplied | K67: Yes | M67: Relay Events
A68: Motor | B68: Acquisition | C68: A7.B1.2 | D68: Document pack dispatched | H68: =3863 + 61 -> 3924 | J68: No report data supplied | K68: Yes | M68: Relay Events
A69: Motor | B69: Acquisition | C69: A7.B1.3 | D69: Customer receipt, implicit | H69: 3924 | J69: No report data supplied | K69: Yes | M69: Relay Renewals
A70: Motor | B70: Acquisition | C70: A7.B1.4 | D70: Non-arrival chase, inbound | H70: 253 | J70: No report data supplied | K70: Yes | M70: Genesys (not direct) | N70: the number of inbound calls is disproportionate to the duplicate dics sent.. So better not to flag them as non arrival chase
A71: Motor | B71: Acquisition | C71: A7.B1.5 | D71: Replacement requested | H71: 28 | J71: No report data supplied | K71: Yes | M71: Relay Events
A72: Motor | B72: Renewal | C72: R0 | D72: Pre-renewal notification, 60 days | J72: No report data supplied | K72: Not a Data Point | M72: Not a data point
A73: Motor | B73: Renewal | C73: RO.F1 | D73: Not sent - no terms from Insurer | H73: 2132 | J73: No report data supplied | K73: Yes | M73: Relay Events | N73: is this held letter too?
A74: Motor | B74: Renewal | C74: R0.B1 | D74: Renewal held letter | H74: 2132 | J74: No report data supplied | K74: Yes | M74: Relay Events
A75: Motor | B75: Renewal | C75: RO.F2 | D75: Declared claims not recorded | H75: 176 | J75: No report data supplied | K75: Yes | M75: Relay Claims
A76: Motor | B76: Renewal | C76: R1a | D76: Renewal invitation sent by EMAIL | F76: 1 | G76: 15552 (not split) | H76: 15204 | I76: =(15552-(15204+410-34))/15552 -> -0.0018004115 | J76: Reconciled within acceptable variance | K76: Yes | M76: Relay Events | N76: use DWH.tbl_ref_Mapping_RenewalPrepDocs to identify the documents and split according to event type - Use the renewal eligible month and count the offers sent in the previous 2 months (translates to roughly 3 full months) | O76: No action for DataTeam
A77: Motor | B77: Renewal | C77: R1b | D77: Renewal invitation sent by POST | F77: 1 | H77: 410 | J77: Reconciled within acceptable variance | K77: Yes | M77: Relay Events | N77: use DWH.tbl_ref_Mapping_RenewalPrepDocs to identify the documents and split according to event type - Use the renewal eligible month and count the offers sent in the previous 2 months (translates to roughly 3 full months) | O77: No action for DataTeam
A78: Motor | B78: Renewal | C78: R1.B1 | D78: Behaviour check on the offer | J78: No report data supplied | K78: Not a Data Point | M78: Not a data point
A79: Motor | B79: Renewal | C79: R1.B2 | D79: Alternative offer sent | H79: 6367 | J79: No report data supplied | K79: Yes | M79: Relay - RBSFCREN data
A80: Motor | B80: Renewal | C80: R1.E1 | D80: Renewal campaigns: CRM | H80: 12493 | J80: No report data supplied | K80: Yes | M80: CRM XP
A81: Motor | B81: Renewal | C81: R1.E1.F1 | D81: Complaints about the renewal programme | J81: No report data supplied | K81: No | M81: Complaints | N81: Data to be supplied by Chill
A82: Motor | B82: Renewal | C82: R1.E1.F2 | D82: Programme fails and the renewal date is missed | J82: No report data supplied | K82: No | M82: Complaints
A83: Motor | B83: Renewal | C83: R1.E1.F3 | D83: Renewal customer in an acquisition campaign audience | H83: 504 | J83: No report data supplied | K83: Yes | M83: CRM XP | N83: to be derived
A84: Motor | B84: Renewal | C84: R2 | D84: Customer logs in to portal | E84: SL04 | F84: 1 | G84: 11788 | H84: 11765 | I84: =1-H84/G84 -> 0.0019511367 | J84: Reconciled within acceptable variance | K84: Yes | M84: RSS Login | O84: No action for DataTeam | P84: 2471
A85: Motor | B85: Renewal | C85: R2.F1 | D85: Failed login | F85: 1 | G85: 1832 | H85: 1888 | I85: =1-H85/G85 -> -0.030567686 | J85: Under Investigation | K85: Yes | M85: RSS Login | N85: smaller volume - to be investigated | O85: No action for DataTeam
A86: Motor | B86: Renewal | C86: R2.F2 | D86: Customer does not accept the price | J86: No report data supplied | K86: Not a Data Point | N86: no data point
A87: Motor | B87: Renewal | C87: R2.F3 | D87: Portal detail updates do not persist | J87: No report data supplied | K87: Not a Data Point | N87: no data point
A88: Motor | B88: Renewal | C88: R2.B1 | D88: Online re-quote (MFQ) for another price | H88: 1616 | J88: No report data supplied | K88: Yes | M88: MFQ | N88: 1616 policies doiing 3152 quotes
A89: Motor | B89: Renewal | C89: R2.B1.F1 | D89: New quote does not beat the renewal price, or the quote is abandoned | H89: 1276 | J89: No report data supplied | K89: Yes | M89: MFQ | N89: 340 policies bought off MFQ directly, which could go into R3a probably (359 marked from acq)
A90: Motor | B90: Renewal | C90: R2.E1 | D90: In-flight price improvement: promo code, or the agent reduces the fee | H90: 4536 | J90: No report data supplied | K90: Yes | M90: Offer Price vs Final Price comparison in Relay
A91: Motor | B91: Renewal | C91: R2.E1.F1 | D91: The better price only appeared after the customer pushed back | J91: No report data supplied | K91: Not a Data Point | N91: no data point
A92: Motor | B92: Renewal | C92: R3a | D92: Customer renews ONLINE | E92: SL04 Online Payment Count | F92: 1 | G92: 7971 | H92: 7995 | I92: =1-H92/G92 -> -0.0030109146 | J92: Reconciled within acceptable variance | K92: Yes | M92: RSS Payments | N92: Compare Policy keys -- old figure 7468 -- Nikita Query gives 7971 / Compared now -- 7448 rss Sales | O92: No action for DataTeam | P92: 152
A93: Motor | B93: Renewal | C93: R3b | D93: Customer renews on an INBOUND call | F93: 1 | G93: 3959 | H93: 3943 | I93: 0.00037636432 | J93: Reconciled within acceptable variance | K93: Yes | M93: Relay Newarchive | N93: Compare Policy keys -- Anna to confirm the PolicyKeys / Nikita will check with / Compared now | O93: Shared query in chat for Motor as well, same as Home.
A94: Motor | B94: Renewal | C94: R3c | D94: Customer renews on an OUTBOUND call | F94: 1 | K94: Yes | N94: VV: | O94: No action for DataTeam
A95: Motor | B95: Renewal | C95: R3d | D95: Customer renews on CHAT | J95: No report data supplied | K95: Not a Data Point | N95: No reliable data point (checked with Gavin)
A96: Motor | B96: Renewal | C96: --- | D96: Web assist: starts online, then calls to complete | G96: 24 | H96: 22 | I96: =1-H96/G96 -> 0.083333333 | J96: Under Investigation | K96: Yes | M96: Relay newarchive - Inference | N96: only 2 diff - Lower priority to investigate
A97: Motor | B97: Renewal | C97: R3b.F1 | D97: Call wait time, or fails to make contact | H97: 969 | J97: No report data supplied | K97: Yes | M97: Genesys | N97: 1194 = Number of calls , number in volumes is phone numbers
A98: Motor | B98: Renewal | C98: R3.F2 | D98: Change friction: adjustments at renewal | K98: Not a Data Point | N98: What are the rules to derive this?
A99: Motor | B99: Renewal | C99: R3.B1 | D99: This year lapsed | H99: 1729 | J99: No report data supplied | K99: Yes | M99: CRM XP | N99: needs to break this down - marked as lapsed in relay policy physical
A100: Motor | B100: Renewal | C100: R3.B2 | D100: Offer withdrawn and re-issued | J100: No report data supplied | K100: New Source | M100: Need Source | N100: What is the source for this?
...

Sheet VanREnewalDocs
A1: EventDescription | B1: count(DISTINCT PolicyCode)
A2: New Business - Printed Document - CD Issue Letter CV | B2: 1203
A3: New Business - Sent To Document Processing - CD Issue Letter CV | B3: 1203
A4: New Business - Saved Document - CD Issue Letter CV | B4: 1203
A5: Prior Year Quotes - Saved Document - C&D Email | B5: 1051
A6: Prior Year Quotes - Sent To Document Processing - C&D Email | B6: 1051
A7: Prior Year Quotes - Emailed Document - C&D Email | B7: 1051
A8: Renewal Offer - Sent To Document Processing - 05 - Terms Of Business | B8: 955
A9: Renewal Offer - Saved Document - Statement of Risk Van | B9: 955
A10: Renewal Offer - Sent To Document Processing - Statement of Risk Van | B10: 955
A11: Renewal Offer - Saved Document - 05 - Terms Of Business | B11: 955
A12: Policy Renewal Window Started | B12: 954
A13: Renewal Offer - Saved Document - Attachment 1 | B13: 953
... A321: New Business - Sent To Document Processing - ZU1 - Zur Breakdown Van | B321: 1

Sheet DOCREQUESTS
A1: PolicyTypeGroup | B1: EventDescription | C1: PolicyCount | D1: EventCount
A2: Home | B2: New Business - Emailed Document - 300 NB Home Email | C2: 36 | D2: 47
A3: Home | B3: New Business - Emailed Document - Terms Of Business | C3: 36 | D3: 49
A4: Home | B4: New Business - Emailed Document - Cover Letter | C4: 34 | D4: 45
A5: Home | B5: New Business - Emailed Document - 04 - Suitability Statement | C5: 34 | D5: 45
A6: Home | B6: Document Chase - Document Transmitted - 02P - Client Bank Letter_Edit Template | C6: 23 | D6: 29
A7: Home | B7: New Business - Emailed Document - Receipt | C7: 20 | D7: 26
A8: Home | B8: New Business - Emailed Document - Statement Of Fact | C8: 18 | D8: 24
A9: Home | B9: New Business - Emailed Document - Schedule | C9: 18 | D9: 24
A10: Home | B10: New Business - Emailed Document - InsuranceProductInformationDocument | C10: 16 | D10: 21
A11: Home | B11: New Business - Emailed Document - PremiumBreakdown | C11: 16 | D11: 21
A12: Home | B12: Document Chase - Document Transmitted - Insurer Doc 2_Placeholder | C12: 16 | D12: 20
A13: Home | B13: New Business - Emailed Document - StatementOfFact | C13: 16 | D13: 21
... A234: Van | B234: Document Chase - Document Transmitted - Client Cancellation Letter | C234: 1 | D234: 1

Sheet Reconciliation Summary
A1: Product | B1: Journey | C1: step_id | D1: Step | E1: Reporting - Volumes | F1: Fabric Volumes | G1: %Variance | H1: Notes | I1: Discrepancy Classification
A2: Home | B2: ACQUISITION | C2: HA1 | D2: Quote initiated ONLINE | E2: 15019 | F2: 15398 | G2: -0.0252347 | H2: The differences are eligible for the logic as presented. So have asked data team to validate why the quotes are excluded | I2: Needs further investigation
A3: Home | B3: ACQUISITION | C3: HA4a | D3: Customer buys ONLINE | E3: 632 | F3: 637 | G3: -0.0079114 | I3: Reconciled within acceptable variance
A4: Home | B4: ACQUISITION | C4: HA0 | D4: Straight into the CALL CENTRE | E4: 921 | F4: 924 | G4: -0.0032573 | I4: Reconciled within acceptable variance
A5: Home | B5: ACQUISITION | C5: HA4b | D5: Agent quotes and converts on the CALL | E5: 466 | F5: 466 | G5: 0 | I5: No Discrepancy
A6: Home | B6: ACQUISITION | C6: HA4.F1 | D6: Web assist: starts online, then calls to complete | E6: 23 | F6: 23 | G6: 0 | I6: No Discrepancy
A7: Home | B7: RENEWALS | C7: HR1a + HR1b | D7: Renewal invitation sent by EMAIL / Post | E7: 6463 | F7: 6479 | G7: -0.0024756 | H7: Some are sent both by email and post. Counting them separate includes them on both channels. Tableau does not split them by channel. Fabric splits them by channel | I7: Reconciled within acceptable variance
A8: Home | B8: RENEWALS | C8: HR3b | D8: Customer renews on an INBOUND call | E8: 1513 | F8: 1509 | G8: 0.00264375 | I8: Reconciled within acceptable variance
A9: Home | B9: RENEWALS | C9: HR3a | D9: Customer renews ONLINE | E9: 2769 | F9: 2749 | G9: 0.00722282 | I9: Reconciled within acceptable variance
A10: Home | B10: RENEWALS | C10: HR2 | D10: Customer logs in to portal | E10: 4489 | F10: 4432 | G10: 0.0126977 | I10: Reconciled within acceptable variance
A11: Motor | B11: Acquisition | C11: A3.B1.2 | D11: Purchase | E11: 1485 | F11: 1507 | G11: -0.0148148 | I11: Reconciled within acceptable variance
A12: Motor | B12: Acquisition | C12: A0 | D12: Straight into the CALL CENTRE | E12: 4325 | F12: 3557 | G12: 0.1775723 | H12: 765 MFQ records which are GDPR-ed do not connect with genesys records. This leads to the MFQ records being not considered in the SQL09 report. Fabric data is as of August 6 which keeps those MFQ records without them being GDPR-ed so they connect with Genesys call records and reduce the metric's volume | I12: Reconciled outside variance but understood
A13: Motor | B13: RENEWALS | C13: R2.F1 | D13: Failed login | E13: 1855 | F13: 1888 | G13: =(Table2[[#This Row],[Reporting - Volumes]]-Table2[[#This Row],[Fabric Volumes]])/Table2[[#This Row],[Reporting - Volumes]] -> -0.017789757 | H13: Reports apply only for offered customers, Fabric counted all failed logins | I13: Reconciled within acceptable variance
A14: Motor | B14: RENEWALS | C14: R1a + R1b | D14: Renewal invitation sent by EMAIL | E14: 15552 | F14: 15614 | G14: -0.0039866 | H14: Some are sent both by email and post. Counting them separate includes them on both channels. Tableau does not split them by channel. Fabric splits them by channel | I14: Reconciled within acceptable variance
A15: Motor | B15: RENEWALS | C15: A1 | D15: Quote initiated ONLINE | E15: 79441 | F15: 79689 | G15: -0.0031218 | H15: The differences are eligible for the logic as presented. So have asked data team to validate why the quotes are excluded | I15: Reconciled within acceptable variance
A16: Motor | B16: RENEWALS | C16: R3a | D16: Customer renews ONLINE | E16: 7971 | F16: 7995 | G16: -0.0030109 | I16: Reconciled within acceptable variance
A17: Motor | B17: RENEWALS | C17: A4b | D17: Agent quotes and converts on the CALL | E17: 685 | F17: 685 | G17: 0 | I17: No Discrepancy
A18: Motor | B18: RENEWALS | C18: A6 | D18: Documents requested | E18: 2580 | F18: 2580 | G18: 0 | I18: No Discrepancy
A19: Motor | B19: RENEWALS | C19: A6.F1 | D19: Chases before the customer submits, and documents never submitted | E19: 1178 | F19: 1178 | G19: 0 | I19: No Discrepancy
A20: Motor | B20: RENEWALS | C20: R2 | D20: Customer logs in to portal | E20: 11788 | F20: 11765 | G20: =(Table2[[#This Row],[Reporting - Volumes]]-Table2[[#This Row],[Fabric Volumes]])/Table2[[#This Row],[Reporting - Volumes]] -> 0.0019511367 | I20: Reconciled within acceptable variance
A21: Motor | B21: RENEWALS | C21: R3b + R3c | D21: Customer renews on an INBOUND call | E21: 3959 | F21: 3943 | G21: 0.00404142 | I21: Reconciled within acceptable variance
A22: Motor | B22: RENEWALS | C22: A3 | D22: Customer gets a price | E22: 35918 | F22: 35551 | G22: 0.0102177 | I22: Reconciled within acceptable variance
A23: Motor | B23: RENEWALS | C23: A3.B1.1 | D23: Quote retrieved or iterated | E23: 15231 | F23: 14919 | G23: 0.0204845 | H23: Fabric counts retrieval of quotes created in the current month while SQL09 includes quotes created in previous month but retrieved in currrent month. Since the rest of the metrics are covering July quotes only, this was left unchanged | I23: Reconciled outside variance but understood
A24: Motor | B24: RENEWALS | C24: A4a | D24: Customer buys ONLINE | E24: 2587 | F24: 2525 | G24: 0.023966 | H24: Fabric counts sales based on quotes started in July. SQL09 counts Sales where a corresponding quote is in June as well. Since the rest of the metrics are covering July quotes only, this was left unchanged | I24: Reconciled outside variance but understood

Sheet Metrics from Chill
A1: Motor | B1: Renewal | C1: Failed login after sent campaign | D1: 1551
A2: Motor | B2: Renewal | C2: Successful login after sent campaign | D2: 9963
A3: Motor | B3: Renewal | C3: Attempted login after sent campaign | D3: 10185
A4: Home | B4: Renewal | C4: Failed login after sent campaign | D4: 606
A5: Home | B5: Renewal | C5: Successful login after sent campaign | D5: 3491
A6: Home | B6: Renewal | C6: Attempted login after sent campaign | D6: 3664
A7: Van | B7: Renewal | C7: Failed login after sent campaign | D7: 238
A8: Van | B8: Renewal | C8: Successful login after sent campaign | D8: 915
A9: Van | B9: Renewal | C9: Attempted login after sent campaign | D9: 973

Sheet Correspondence Log
A1: Date | B1: Person | C1: Channel | D1: Type | E1: Content
A2: 17.08.2026 | B2: Kamran | C2: Email | D2: Ask for sign-off | E2: Shared Motor_Journey_Frameworks.xlsx workbook, with Motor done
A3: 17.08.2026 | B3: Amber | C3: Email | D3: Notes | E3: Renewal Flow R2.B1.F1 I would argue that regardless of whether the price does or does not beat renewal price it is a friction point, not just circumstances where the new quote does not beat the renewal price i. Does beat renewal price – customer will either book as a new policy which has manual overheads/might lead to a pattern of behaviour of doing this every year and effectively try to “beat the system” or go elsewhere as they don’t “trust” that we do what we advertise which is getting the customer the best price ii. Does not beat renewal price – customer may go elsewhere as they were potentially looking for a cheaper price in the first place R2.F3 – Darragh confirmed it goes nowhere R1.E1 – another point of friction would be when these don’t work, a customer misses their renewal date and they’re no longer covered – we do get complaints along these lines KeyCare question – I would say this is a renewal/new business incentive, you can only buy it when you purchase a new policy or renew an existing one R3B1.2 – Winback, LYR, LYQ are not part of this Episode – they should be counted as the start of the online Happy Path in acquisition flow R4.B2.2 – yes Digital Acquisition Flow A1.E1 – this is an email AND an SMS, both sent 7 minutes after hitting continue in Step 1 A2.E1.F1 – the quote ref doesn’t need to be inputted by the customer, this is pre-populated in the URL however the customer does have submit either their DOB or Reg plate, so either of these could be inputted incorrectly and lead to friction A4a or A5a – should there not be another point of friction when the payment fails? This could be a technical error within Chill or payment details incorrect/no funds A5.1 – the email doesn’t say Motor whatever product was bought, we have separate Home, Motor and Van ones Branch Journey 3 – ‘standard provider’ isn’t the right terminology, Close Brothers Finance are our old finance provider, so you’ll see data slowly start to stop as the current loans filter out and are transferred to Premium Credit loans. Premium Credit are our new provider and your best contact on where to find the data would be Gavin Branch Journey 4 – this process is being changed over the next month or so and will be fully automated and sent via XP – will you need to know when this goes live? MTA Flow M5 – there is currently no confirmation email sent when the MTA is processed, so a friction point is when customers ring back to double check it all went through – especially if no changes to premium/reversal. The only email that is sent is a receipt when the premium increases. MTA Types – I believe there are a lot more than 5 MTA types, who has this been checked with? Cancellation Flow Our old provider Close Brothers Finance don’t do any chases, this is all done by the Arrears Chase campaign in Chill Premium Credit Finance do do their own chases, and there are no additional chases from Chill Arrears Flow As above re. Close Brothers Finance and Premium Credit Finance chases Claims Flow CL3.F1 – we don’t send any follow ups during/after claims process so customers may not always know it’s being actioned as I am not sure the insurer provide these updates either Doc Request Flow There is an ongoing project to digitise this called “DigiDocs” part of it is already in-flight, I think it would be worth speaking to Darragh about this and ensuring the data points you need to capture are, as I would say someone repeatedly downloading the same document over and over, especially NCB certificate, is an indicator of churn
A4: 18.08.2026 | B4: Alex | C4: Email | D4: Notes | E4: Acquisition entry points – PPC generic or brand, SEO generic or brand, direct to site, CRM – brand vs generic a key potential indicator On MTA / change – we looked at website search (page visits to specific pages) as an indicator before / start point – shows digital engagement, would have done it online but no call etc
A5: 19.08.2026 | B5: Kamran | C5: Email | D5: Ask for sign-off | E5: Shared Chill_Episode_Frameworks.xlsx, with Home, Van & Travel
A6: 21.08.2026 | B6: Alex | C6: Email | D6: Notes | E6: Motor Need the Day 60 comm clarified – people may call in off that – Amber Need the immediate post-payment portal doc capture step New business pack sent immediate post payment Loan and doc upload run in parallel Loan – app download, doc upload partial, doc upload complete, approved Home – acquisition Step 1 to Step 6 shown in Sl12 – I’ll confirm step 6 is quote display – same entry points etc Doc upload – not the same requirements as motor – need to check with ops ToB and Policy docs sent – need to check these are different steps - Ops
A7: 21.08.2027 | B7: Alex | C7: Email | D7: Questions | E7: Home – renewals Needs the Day 60 – Amber Not sure what the presented step with no data you’re highlighting is? Failed log in – this is tracked, SL8. Amber the figures – unique log in success / failure / total – total and success are often similar. Does this mean people failed but eventually got through? Online requote – this is on HFQ – the issue we’ve flagged on SCV is the high volumes. There is a path where people then buy through HFQ (as with MFQ) – this creates back end complexity. Not sure how it changes customer journey – one for Ops team Are we tracking engagement with CRM? Its not friction but is an behavioural indicator – comms engaged etc Payment success / fail- this should be tracked Roll-over – a much higher proportion of Home rolls over – this would be another happy path – offer / rollover. Amber – for roll over customers, do we still send the chase comms / how tailored? Home – aquisition Service retrieve – is that still Amber - sendgrid / same as motor Web assist – not recorded – you should be able to see same phone number etc log in, may have a better view than us?
A8: 21.08.2027 | B8: Amber | C8: Email | D8: Notes | E8: Renewals Day 60 comm – this is product agnostic, everyone gets the same email regardless of product; it is only within the copy that we dynamically pull in product name. Total send volume in July was 21,651 and this is all products excluding Travel. Home Roll Over – these customers are still in the Renewal chase as there is no way to identify them accurately in the DWH to exclude them. Home Service Retrieve is sent by Send Grid in the same way as Motor

Sheet Home Renewal Documents
B1: EventDescription | C1: Volume
A2: 0 | B2: Renewal Transfer - Emailed Document - RE3 Home Ext Cover email Receipt | C2: 2772
A3: 1 | B3: Renewal Transfer - Emailed Document - Receipt Batch Email | C3: 2455
A4: 2 | B4: New Business - Emailed Document - 04 - Suitability Statement | C4: 1162
A5: 3 | B5: New Business - Emailed Document - Terms Of Business | C5: 1152
A6: 4 | B6: New Business - Emailed Document - 300 NB Home Email | C6: 1129
A7: 5 | B7: New Business - Emailed Document - Cover Letter | C7: 1124
A8: 6 | B8: Renewal Confirmation - Emailed Document - Home SOF / Proposal_Placeholder | C8: 1104
A9: 7 | B9: Renewal Confirmation - Emailed Document - Receipt_Template | C9: 1092
A10: 8 | B10: Renewal Transfer - Emailed Document - Rnl Conf Cover Email Home Rollover v2 | C10: 1081
A11: 9 | B11: Renewal Confirmation - Emailed Document - 04 - Suitability Statement | C11: 971
A12: 10 | B12: New Business - Emailed Document - Statement Of Fact | C12: 860
A13: 11 | B13: New Business - Emailed Document - Schedule | C13: 860
... A18: 16 | B18: New Business - Emailed Document - Insurance Product Information Document | C18: 473
A19: 17 | B19: Prior Year Quotes - Emailed Document - Auto Rollover Email fix | C19: 441 | D19: Rollover -- Finance?
A20: 18 | B20: Document Chase - Emailed Document Failed - Chase Final Notice Email | C20: 414 | D20: Final chase from Chill to Customer?
A21: 19 | B21: Document Chase - Emailed Document - Chase Final Notice Email | C21: 414
A22: 20 | B22: Renewal Confirmation - Emailed Document - Home LOI_Placeholder | C22: 363
A23: 21 | B23: New Business - Emailed Document - Interested Party | C23: 288
A24: 22 | B24: New Business - Emailed Document - PremiumBreakdown | C24: 263
A25: 23 | B25: New Business - Emailed Document - InsuranceProductInformationDocument | C25: 263
A26: 24 | B26: New Business - Emailed Document - StatementOfFact | C26: 263
A27: 25 | B27: Renewal Confirmation - Emailed Document - Email - Home Renewal Confirmation (roll over) V1 | C27: 241
A28: 26 | B28: Renewal Confirmation - Document Transmitted - Receipt_Template | C28: 223
A29: 27 | B29: New Business - Emailed Document - Premium Breakdown | C29: 159
A30: 28 | B30: New Business - Emailed Document - Key Facts | C30: 159
A31: 29 | B31: Renewal Confirmation - Document Transmitted - Home Ext Cover Letter_Receipt | C31: 159
A32: 30 | B32: Document Chase - Document Transmitted - 02P - Client Bank Letter_Edit Template | C32: 111
... A105: 103 | B105: Renewal Transfer - Document Transmitted - Rnl Conf Cover Email Home Rollover v2 | C105: 1
