Workbook
Name DeltaList: 'Status key'!$C$29:$C$31
Name MigrationList: 'Status key'!$D$29:$D$35
Name SourceList: 'Status key'!$B$29:$B$30
Name StatusList: 'Status key'!$A$29:$A$36

Sheet Status summary
A1: Status by product and episode
A2: Every figure is a live formula over the Event stream steps tab, so this updates as the steps tab is filled in. Percentages are of the steps in that row. Status is progress through the work; source change and delta change describe the work itself and were filled in from the code.
D5: Status (column G) | M5: Source change (column I) | P5: Delta change (column K)
A6: Product | B6: Episode | C6: Steps | D6: Unchecked | E6: Triaged | F6: Blocked | G6: In progress | H6: In review | I6: Reconciled | J6: Done | K6: Not required | M6: Already ods | N6: Needs re-sourcing | P6: Windowed in query | Q6: Watermark sits upstream | R6: Needs a watermark
A7: Motor | B7: Acquisition | C7: =COUNTIFS('Event stream steps'!$C$2:$C$331,$A7,'Event stream steps'!$D$2:$D$331,$B7) -> 35 | D7: =IFERROR(COUNTIFS('Event stream steps'!$C$2:$C$331,$A7,'Event stream steps'!$D$2:$D$331,$B7,'Event stream steps'!$G$2:$G$331,D$6)/$C7,0) -> 1 | E7: =IFERROR(COUNTIFS('Event stream steps'!$C$2:$C$331,$A7,'Event stream steps'!$D$2:$D$331,$B7,'Event stream steps'!$G$2:$G$331,E$6)/$C7,0) -> 0 | F7: =IFERROR(COUNTIFS('Event stream steps'!$C$2:$C$331,$A7,'Event stream steps'!$D$2:$D$331,$B7,'Event stream steps'!$G$2:$G$331,F$6)/$C7,0) -> 0 | G7: =IFERROR(COUNTIFS('Event stream steps'!$C$2:$C$331,$A7,'Event stream steps'!$D$2:$D$331,$B7,'Event stream steps'!$G$2:$G$331,G$6)/$C7,0) -> 0 | H7: =IFERROR(COUNTIFS('Event stream steps'!$C$2:$C$331,$A7,'Event stream steps'!$D$2:$D$331,$B7,'Event stream steps'!$G$2:$G$331,H$6)/$C7,0) -> 0 | I7: =IFERROR(COUNTIFS('Event stream steps'!$C$2:$C$331,$A7,'Event stream steps'!$D$2:$D$331,$B7,'Event stream steps'!$G$2:$G$331,I$6)/$C7,0) -> 0 | J7: =IFERROR(COUNTIFS('Event stream steps'!$C$2:$C$331,$A7,'Event stream steps'!$D$2:$D$331,$B7,'Event stream steps'!$G$2:$G$331,J$6)/$C7,0) -> 0 | K7: =IFERROR(COUNTIFS('Event stream steps'!$C$2:$C$331,$A7,'Event stream steps'!$D$2:$D$331,$B7,'Event stream steps'!$G$2:$G$331,K$6)/$C7,0) -> 0 | M7: =IFERROR(COUNTIFS('Event stream steps'!$C$2:$C$331,$A7,'Event stream steps'!$D$2:$D$331,$B7,'Event stream steps'!$I$2:$I$331,M$6)/$C7,0) -> 0 | N7: =IFERROR(COUNTIFS('Event stream steps'!$C$2:$C$331,$A7,'Event stream steps'!$D$2:$D$331,$B7,'Event stream steps'!$I$2:$I$331,N$6)/$C7,0) -> 1 | P7: =IFERROR(COUNTIFS('Event stream steps'!$C$2:$C$331,$A7,'Event stream steps'!$D$2:$D$331,$B7,'Event stream steps'!$K$2:$K$331,P$6)/$C7,0) -> 0.71428571 | Q7: =IFERROR(COUNTIFS('Event stream steps'!$C$2:$C$331,$A7,'Event stream steps'!$D$2:$D$331,$B7,'Event stream steps'!$K$2:$K$331,Q$6)/$C7,0) -> 0.28571429 | R7: =IFERROR(COUNTIFS('Event stream steps'!$C$2:$C$331,$A7,'Event stream steps'!$D$2:$D$331,$B7,'Event stream steps'!$K$2:$K$331,R$6)/$C7,0) -> 0
A8: Motor | B8: Renewal | C8: =COUNTIFS('Event stream steps'!$C$2:$C$331,$A8,'Event stream steps'!$D$2:$D$331,$B8) -> 56 | D8: =IFERROR(COUNTIFS('Event stream steps'!$C$2:$C$331,$A8,'Event stream steps'!$D$2:$D$331,$B8,'Event stream steps'!$G$2:$G$331,D$6)/$C8,0) -> 1 | E8: =IFERROR(COUNTIFS('Event stream steps'!$C$2:$C$331,$A8,'Event stream steps'!$D$2:$D$331,$B8,'Event stream steps'!$G$2:$G$331,E$6)/$C8,0) -> 0 | F8: =IFERROR(COUNTIFS('Event stream steps'!$C$2:$C$331,$A8,'Event stream steps'!$D$2:$D$331,$B8,'Event stream steps'!$G$2:$G$331,F$6)/$C8,0) -> 0 | G8: =IFERROR(COUNTIFS('Event stream steps'!$C$2:$C$331,$A8,'Event stream steps'!$D$2:$D$331,$B8,'Event stream steps'!$G$2:$G$331,G$6)/$C8,0) -> 0 | H8: =IFERROR(COUNTIFS('Event stream steps'!$C$2:$C$331,$A8,'Event stream steps'!$D$2:$D$331,$B8,'Event stream steps'!$G$2:$G$331,H$6)/$C8,0) -> 0 | I8: =IFERROR(COUNTIFS('Event stream steps'!$C$2:$C$331,$A8,'Event stream steps'!$D$2:$D$331,$B8,'Event stream steps'!$G$2:$G$331,I$6)/$C8,0) -> 0 | J8: =IFERROR(COUNTIFS('Event stream steps'!$C$2:$C$331,$A8,'Event stream steps'!$D$2:$D$331,$B8,'Event stream steps'!$G$2:$G$331,J$6)/$C8,0) -> 0 | K8: =IFERROR(COUNTIFS('Event stream steps'!$C$2:$C$331,$A8,'Event stream steps'!$D$2:$D$331,$B8,'Event stream steps'!$G$2:$G$331,K$6)/$C8,0) -> 0 | M8: =IFERROR(COUNTIFS('Event stream steps'!$C$2:$C$331,$A8,'Event stream steps'!$D$2:$D$331,$B8,'Event stream steps'!$I$2:$I$331,M$6)/$C8,0) -> 0.035714286 | N8: =IFERROR(COUNTIFS('Event stream steps'!$C$2:$C$331,$A8,'Event stream steps'!$D$2:$D$331,$B8,'Event stream steps'!$I$2:$I$331,N$6)/$C8,0) -> 0.96428571 | P8: =IFERROR(COUNTIFS('Event stream steps'!$C$2:$C$331,$A8,'Event stream steps'!$D$2:$D$331,$B8,'Event stream steps'!$K$2:$K$331,P$6)/$C8,0) -> 0.53571429 | Q8: =IFERROR(COUNTIFS('Event stream steps'!$C$2:$C$331,$A8,'Event stream steps'!$D$2:$D$331,$B8,'Event stream steps'!$K$2:$K$331,Q$6)/$C8,0) -> 0.46428571 | R8: =IFERROR(COUNTIFS('Event stream steps'!$C$2:$C$331,$A8,'Event stream steps'!$D$2:$D$331,$B8,'Event stream steps'!$K$2:$K$331,R$6)/$C8,0) -> 0
A9: Motor | B9: MTA | C9: =COUNTIFS('Event stream steps'!$C$2:$C$331,$A9,'Event stream steps'!$D$2:$D$331,$B9) -> 16 | D9: =IFERROR(COUNTIFS('Event stream steps'!$C$2:$C$331,$A9,'Event stream steps'!$D$2:$D$331,$B9,'Event stream steps'!$G$2:$G$331,D$6)/$C9,0) -> 1 | E9: =IFERROR(COUNTIFS('Event stream steps'!$C$2:$C$331,$A9,'Event stream steps'!$D$2:$D$331,$B9,'Event stream steps'!$G$2:$G$331,E$6)/$C9,0) -> 0 | F9: =IFERROR(COUNTIFS('Event stream steps'!$C$2:$C$331,$A9,'Event stream steps'!$D$2:$D$331,$B9,'Event stream steps'!$G$2:$G$331,F$6)/$C9,0) -> 0 | G9: =IFERROR(COUNTIFS('Event stream steps'!$C$2:$C$331,$A9,'Event stream steps'!$D$2:$D$331,$B9,'Event stream steps'!$G$2:$G$331,G$6)/$C9,0) -> 0 | H9: =IFERROR(COUNTIFS('Event stream steps'!$C$2:$C$331,$A9,'Event stream steps'!$D$2:$D$331,$B9,'Event stream steps'!$G$2:$G$331,H$6)/$C9,0) -> 0 | I9: =IFERROR(COUNTIFS('Event stream steps'!$C$2:$C$331,$A9,'Event stream steps'!$D$2:$D$331,$B9,'Event stream steps'!$G$2:$G$331,I$6)/$C9,0) -> 0 | J9: =IFERROR(COUNTIFS('Event stream steps'!$C$2:$C$331,$A9,'Event stream steps'!$D$2:$D$331,$B9,'Event stream steps'!$G$2:$G$331,J$6)/$C9,0) -> 0 | K9: =IFERROR(COUNTIFS('Event stream steps'!$C$2:$C$331,$A9,'Event stream steps'!$D$2:$D$331,$B9,'Event stream steps'!$G$2:$G$331,K$6)/$C9,0) -> 0 | M9: =IFERROR(COUNTIFS('Event stream steps'!$C$2:$C$331,$A9,'Event stream steps'!$D$2:$D$331,$B9,'Event stream steps'!$I$2:$I$331,M$6)/$C9,0) -> 0 | N9: =IFERROR(COUNTIFS('Event stream steps'!$C$2:$C$331,$A9,'Event stream steps'!$D$2:$D$331,$B9,'Event stream steps'!$I$2:$I$331,N$6)/$C9,0) -> 1 | P9: =IFERROR(COUNTIFS('Event stream steps'!$C$2:$C$331,$A9,'Event stream steps'!$D$2:$D$331,$B9,'Event stream steps'!$K$2:$K$331,P$6)/$C9,0) -> 0.4375 | Q9: =IFERROR(COUNTIFS('Event stream steps'!$C$2:$C$331,$A9,'Event stream steps'!$D$2:$D$331,$B9,'Event stream steps'!$K$2:$K$331,Q$6)/$C9,0) -> 0.5625 | R9: =IFERROR(COUNTIFS('Event stream steps'!$C$2:$C$331,$A9,'Event stream steps'!$D$2:$D$331,$B9,'Event stream steps'!$K$2:$K$331,R$6)/$C9,0) -> 0
A10: Motor | B10: Cancellation | C10: =COUNTIFS('Event stream steps'!$C$2:$C$331,$A10,'Event stream steps'!$D$2:$D$331,$B10) -> 7 | D10: =IFERROR(COUNTIFS('Event stream steps'!$C$2:$C$331,$A10,'Event stream steps'!$D$2:$D$331,$B10,'Event stream steps'!$G$2:$G$331,D$6)/$C10,0) -> 1 | E10: =IFERROR(COUNTIFS('Event stream steps'!$C$2:$C$331,$A10,'Event stream steps'!$D$2:$D$331,$B10,'Event stream steps'!$G$2:$G$331,E$6)/$C10,0) -> 0 | F10: =IFERROR(COUNTIFS('Event stream steps'!$C$2:$C$331,$A10,'Event stream steps'!$D$2:$D$331,$B10,'Event stream steps'!$G$2:$G$331,F$6)/$C10,0) -> 0 | G10: =IFERROR(COUNTIFS('Event stream steps'!$C$2:$C$331,$A10,'Event stream steps'!$D$2:$D$331,$B10,'Event stream steps'!$G$2:$G$331,G$6)/$C10,0) -> 0 | H10: =IFERROR(COUNTIFS('Event stream steps'!$C$2:$C$331,$A10,'Event stream steps'!$D$2:$D$331,$B10,'Event stream steps'!$G$2:$G$331,H$6)/$C10,0) -> 0 | I10: =IFERROR(COUNTIFS('Event stream steps'!$C$2:$C$331,$A10,'Event stream steps'!$D$2:$D$331,$B10,'Event stream steps'!$G$2:$G$331,I$6)/$C10,0) -> 0 | J10: =IFERROR(COUNTIFS('Event stream steps'!$C$2:$C$331,$A10,'Event stream steps'!$D$2:$D$331,$B10,'Event stream steps'!$G$2:$G$331,J$6)/$C10,0) -> 0 | K10: =IFERROR(COUNTIFS('Event stream steps'!$C$2:$C$331,$A10,'Event stream steps'!$D$2:$D$331,$B10,'Event stream steps'!$G$2:$G$331,K$6)/$C10,0) -> 0 | M10: =IFERROR(COUNTIFS('Event stream steps'!$C$2:$C$331,$A10,'Event stream steps'!$D$2:$D$331,$B10,'Event stream steps'!$I$2:$I$331,M$6)/$C10,0) -> 0.14285714 | N10: =IFERROR(COUNTIFS('Event stream steps'!$C$2:$C$331,$A10,'Event stream steps'!$D$2:$D$331,$B10,'Event stream steps'!$I$2:$I$331,N$6)/$C10,0) -> 0.85714286 | P10: =IFERROR(COUNTIFS('Event stream steps'!$C$2:$C$331,$A10,'Event stream steps'!$D$2:$D$331,$B10,'Event stream steps'!$K$2:$K$331,P$6)/$C10,0) -> 1 | Q10: =IFERROR(COUNTIFS('Event stream steps'!$C$2:$C$331,$A10,'Event stream steps'!$D$2:$D$331,$B10,'Event stream steps'!$K$2:$K$331,Q$6)/$C10,0) -> 0 | R10: =IFERROR(COUNTIFS('Event stream steps'!$C$2:$C$331,$A10,'Event stream steps'!$D$2:$D$331,$B10,'Event stream steps'!$K$2:$K$331,R$6)/$C10,0) -> 0
A11: Motor | B11: Arrears | C11: =COUNTIFS('Event stream steps'!$C$2:$C$331,$A11,'Event stream steps'!$D$2:$D$331,$B11) -> 5 | D11: =IFERROR(COUNTIFS('Event stream steps'!$C$2:$C$331,$A11,'Event stream steps'!$D$2:$D$331,$B11,'Event stream steps'!$G$2:$G$331,D$6)/$C11,0) -> 1 | E11: =IFERROR(COUNTIFS('Event stream steps'!$C$2:$C$331,$A11,'Event stream steps'!$D$2:$D$331,$B11,'Event stream steps'!$G$2:$G$331,E$6)/$C11,0) -> 0 | F11: =IFERROR(COUNTIFS('Event stream steps'!$C$2:$C$331,$A11,'Event stream steps'!$D$2:$D$331,$B11,'Event stream steps'!$G$2:$G$331,F$6)/$C11,0) -> 0 | G11: =IFERROR(COUNTIFS('Event stream steps'!$C$2:$C$331,$A11,'Event stream steps'!$D$2:$D$331,$B11,'Event stream steps'!$G$2:$G$331,G$6)/$C11,0) -> 0 | H11: =IFERROR(COUNTIFS('Event stream steps'!$C$2:$C$331,$A11,'Event stream steps'!$D$2:$D$331,$B11,'Event stream steps'!$G$2:$G$331,H$6)/$C11,0) -> 0 | I11: =IFERROR(COUNTIFS('Event stream steps'!$C$2:$C$331,$A11,'Event stream steps'!$D$2:$D$331,$B11,'Event stream steps'!$G$2:$G$331,I$6)/$C11,0) -> 0 | J11: =IFERROR(COUNTIFS('Event stream steps'!$C$2:$C$331,$A11,'Event stream steps'!$D$2:$D$331,$B11,'Event stream steps'!$G$2:$G$331,J$6)/$C11,0) -> 0 | K11: =IFERROR(COUNTIFS('Event stream steps'!$C$2:$C$331,$A11,'Event stream steps'!$D$2:$D$331,$B11,'Event stream steps'!$G$2:$G$331,K$6)/$C11,0) -> 0 | M11: =IFERROR(COUNTIFS('Event stream steps'!$C$2:$C$331,$A11,'Event stream steps'!$D$2:$D$331,$B11,'Event stream steps'!$I$2:$I$331,M$6)/$C11,0) -> 0 | N11: =IFERROR(COUNTIFS('Event stream steps'!$C$2:$C$331,$A11,'Event stream steps'!$D$2:$D$331,$B11,'Event stream steps'!$I$2:$I$331,N$6)/$C11,0) -> 1 | P11: =IFERROR(COUNTIFS('Event stream steps'!$C$2:$C$331,$A11,'Event stream steps'!$D$2:$D$331,$B11,'Event stream steps'!$K$2:$K$331,P$6)/$C11,0) -> 1 | Q11: =IFERROR(COUNTIFS('Event stream steps'!$C$2:$C$331,$A11,'Event stream steps'!$D$2:$D$331,$B11,'Event stream steps'!$K$2:$K$331,Q$6)/$C11,0) -> 0 | R11: =IFERROR(COUNTIFS('Event stream steps'!$C$2:$C$331,$A11,'Event stream steps'!$D$2:$D$331,$B11,'Event stream steps'!$K$2:$K$331,R$6)/$C11,0) -> 0
A12: Motor | B12: Claims | C12: =COUNTIFS('Event stream steps'!$C$2:$C$331,$A12,'Event stream steps'!$D$2:$D$331,$B12) -> 1 | D12: =IFERROR(COUNTIFS('Event stream steps'!$C$2:$C$331,$A12,'Event stream steps'!$D$2:$D$331,$B12,'Event stream steps'!$G$2:$G$331,D$6)/$C12,0) -> 1 | E12: =IFERROR(COUNTIFS('Event stream steps'!$C$2:$C$331,$A12,'Event stream steps'!$D$2:$D$331,$B12,'Event stream steps'!$G$2:$G$331,E$6)/$C12,0) -> 0 | F12: =IFERROR(COUNTIFS('Event stream steps'!$C$2:$C$331,$A12,'Event stream steps'!$D$2:$D$331,$B12,'Event stream steps'!$G$2:$G$331,F$6)/$C12,0) -> 0 | G12: =IFERROR(COUNTIFS('Event stream steps'!$C$2:$C$331,$A12,'Event stream steps'!$D$2:$D$331,$B12,'Event stream steps'!$G$2:$G$331,G$6)/$C12,0) -> 0 | H12: =IFERROR(COUNTIFS('Event stream steps'!$C$2:$C$331,$A12,'Event stream steps'!$D$2:$D$331,$B12,'Event stream steps'!$G$2:$G$331,H$6)/$C12,0) -> 0 | I12: =IFERROR(COUNTIFS('Event stream steps'!$C$2:$C$331,$A12,'Event stream steps'!$D$2:$D$331,$B12,'Event stream steps'!$G$2:$G$331,I$6)/$C12,0) -> 0 | J12: =IFERROR(COUNTIFS('Event stream steps'!$C$2:$C$331,$A12,'Event stream steps'!$D$2:$D$331,$B12,'Event stream steps'!$G$2:$G$331,J$6)/$C12,0) -> 0 | K12: =IFERROR(COUNTIFS('Event stream steps'!$C$2:$C$331,$A12,'Event stream steps'!$D$2:$D$331,$B12,'Event stream steps'!$G$2:$G$331,K$6)/$C12,0) -> 0 | M12: =IFERROR(COUNTIFS('Event stream steps'!$C$2:$C$331,$A12,'Event stream steps'!$D$2:$D$331,$B12,'Event stream steps'!$I$2:$I$331,M$6)/$C12,0) -> 0 | N12: =IFERROR(COUNTIFS('Event stream steps'!$C$2:$C$331,$A12,'Event stream steps'!$D$2:$D$331,$B12,'Event stream steps'!$I$2:$I$331,N$6)/$C12,0) -> 1 | P12: =IFERROR(COUNTIFS('Event stream steps'!$C$2:$C$331,$A12,'Event stream steps'!$D$2:$D$331,$B12,'Event stream steps'!$K$2:$K$331,P$6)/$C12,0) -> 0 | Q12: =IFERROR(COUNTIFS('Event stream steps'!$C$2:$C$331,$A12,'Event stream steps'!$D$2:$D$331,$B12,'Event stream steps'!$K$2:$K$331,Q$6)/$C12,0) -> 1 | R12: =IFERROR(COUNTIFS('Event stream steps'!$C$2:$C$331,$A12,'Event stream steps'!$D$2:$D$331,$B12,'Event stream steps'!$K$2:$K$331,R$6)/$C12,0) -> 0
A13: Motor | B13: Doc Request | C13: =COUNTIFS('Event stream steps'!$C$2:$C$331,$A13,'Event stream steps'!$D$2:$D$331,$B13) -> 6 | D13: =IFERROR(COUNTIFS('Event stream steps'!$C$2:$C$331,$A13,'Event stream steps'!$D$2:$D$331,$B13,'Event stream steps'!$G$2:$G$331,D$6)/$C13,0) -> 1 | E13: =IFERROR(COUNTIFS('Event stream steps'!$C$2:$C$331,$A13,'Event stream steps'!$D$2:$D$331,$B13,'Event stream steps'!$G$2:$G$331,E$6)/$C13,0) -> 0 | F13: =IFERROR(COUNTIFS('Event stream steps'!$C$2:$C$331,$A13,'Event stream steps'!$D$2:$D$331,$B13,'Event stream steps'!$G$2:$G$331,F$6)/$C13,0) -> 0 | G13: =IFERROR(COUNTIFS('Event stream steps'!$C$2:$C$331,$A13,'Event stream steps'!$D$2:$D$331,$B13,'Event stream steps'!$G$2:$G$331,G$6)/$C13,0) -> 0 | H13: =IFERROR(COUNTIFS('Event stream steps'!$C$2:$C$331,$A13,'Event stream steps'!$D$2:$D$331,$B13,'Event stream steps'!$G$2:$G$331,H$6)/$C13,0) -> 0 | I13: =IFERROR(COUNTIFS('Event stream steps'!$C$2:$C$331,$A13,'Event stream steps'!$D$2:$D$331,$B13,'Event stream steps'!$G$2:$G$331,I$6)/$C13,0) -> 0 | J13: =IFERROR(COUNTIFS('Event stream steps'!$C$2:$C$331,$A13,'Event stream steps'!$D$2:$D$331,$B13,'Event stream steps'!$G$2:$G$331,J$6)/$C13,0) -> 0 | K13: =IFERROR(COUNTIFS('Event stream steps'!$C$2:$C$331,$A13,'Event stream steps'!$D$2:$D$331,$B13,'Event stream steps'!$G$2:$G$331,K$6)/$C13,0) -> 0 | M13: =IFERROR(COUNTIFS('Event stream steps'!$C$2:$C$331,$A13,'Event stream steps'!$D$2:$D$331,$B13,'Event stream steps'!$I$2:$I$331,M$6)/$C13,0) -> 0 | N13: =IFERROR(COUNTIFS('Event stream steps'!$C$2:$C$331,$A13,'Event stream steps'!$D$2:$D$331,$B13,'Event stream steps'!$I$2:$I$331,N$6)/$C13,0) -> 1 | P13: =IFERROR(COUNTIFS('Event stream steps'!$C$2:$C$331,$A13,'Event stream steps'!$D$2:$D$331,$B13,'Event stream steps'!$K$2:$K$331,P$6)/$C13,0) -> 0 | Q13: =IFERROR(COUNTIFS('Event stream steps'!$C$2:$C$331,$A13,'Event stream steps'!$D$2:$D$331,$B13,'Event stream steps'!$K$2:$K$331,Q$6)/$C13,0) -> 1 | R13: =IFERROR(COUNTIFS('Event stream steps'!$C$2:$C$331,$A13,'Event stream steps'!$D$2:$D$331,$B13,'Event stream steps'!$K$2:$K$331,R$6)/$C13,0) -> 0
A14: Motor | B14: All episodes | C14: =COUNTIFS('Event stream steps'!$C$2:$C$331,$A14) -> 126 | D14: =IFERROR(COUNTIFS('Event stream steps'!$C$2:$C$331,$A14,'Event stream steps'!$G$2:$G$331,D$6)/$C14,0) -> 1 | E14: =IFERROR(COUNTIFS('Event stream steps'!$C$2:$C$331,$A14,'Event stream steps'!$G$2:$G$331,E$6)/$C14,0) -> 0 | F14: =IFERROR(COUNTIFS('Event stream steps'!$C$2:$C$331,$A14,'Event stream steps'!$G$2:$G$331,F$6)/$C14,0) -> 0 | G14: =IFERROR(COUNTIFS('Event stream steps'!$C$2:$C$331,$A14,'Event stream steps'!$G$2:$G$331,G$6)/$C14,0) -> 0 | H14: =IFERROR(COUNTIFS('Event stream steps'!$C$2:$C$331,$A14,'Event stream steps'!$G$2:$G$331,H$6)/$C14,0) -> 0 | I14: =IFERROR(COUNTIFS('Event stream steps'!$C$2:$C$331,$A14,'Event stream steps'!$G$2:$G$331,I$6)/$C14,0) -> 0 | J14: =IFERROR(COUNTIFS('Event stream steps'!$C$2:$C$331,$A14,'Event stream steps'!$G$2:$G$331,J$6)/$C14,0) -> 0 | K14: =IFERROR(COUNTIFS('Event stream steps'!$C$2:$C$331,$A14,'Event stream steps'!$G$2:$G$331,K$6)/$C14,0) -> 0 | M14: =IFERROR(COUNTIFS('Event stream steps'!$C$2:$C$331,$A14,'Event stream steps'!$I$2:$I$331,M$6)/$C14,0) -> 0.023809524 | N14: =IFERROR(COUNTIFS('Event stream steps'!$C$2:$C$331,$A14,'Event stream steps'!$I$2:$I$331,N$6)/$C14,0) -> 0.97619048 | P14: =IFERROR(COUNTIFS('Event stream steps'!$C$2:$C$331,$A14,'Event stream steps'!$K$2:$K$331,P$6)/$C14,0) -> 0.58730159 | Q14: =IFERROR(COUNTIFS('Event stream steps'!$C$2:$C$331,$A14,'Event stream steps'!$K$2:$K$331,Q$6)/$C14,0) -> 0.41269841 | R14: =IFERROR(COUNTIFS('Event stream steps'!$C$2:$C$331,$A14,'Event stream steps'!$K$2:$K$331,R$6)/$C14,0) -> 0
A15: Home | B15: Acquisition | C15: =COUNTIFS('Event stream steps'!$C$2:$C$331,$A15,'Event stream steps'!$D$2:$D$331,$B15) -> 32 | D15: =IFERROR(COUNTIFS('Event stream steps'!$C$2:$C$331,$A15,'Event stream steps'!$D$2:$D$331,$B15,'Event stream steps'!$G$2:$G$331,D$6)/$C15,0) -> 1 | E15: =IFERROR(COUNTIFS('Event stream steps'!$C$2:$C$331,$A15,'Event stream steps'!$D$2:$D$331,$B15,'Event stream steps'!$G$2:$G$331,E$6)/$C15,0) -> 0 | F15: =IFERROR(COUNTIFS('Event stream steps'!$C$2:$C$331,$A15,'Event stream steps'!$D$2:$D$331,$B15,'Event stream steps'!$G$2:$G$331,F$6)/$C15,0) -> 0 | G15: =IFERROR(COUNTIFS('Event stream steps'!$C$2:$C$331,$A15,'Event stream steps'!$D$2:$D$331,$B15,'Event stream steps'!$G$2:$G$331,G$6)/$C15,0) -> 0 | H15: =IFERROR(COUNTIFS('Event stream steps'!$C$2:$C$331,$A15,'Event stream steps'!$D$2:$D$331,$B15,'Event stream steps'!$G$2:$G$331,H$6)/$C15,0) -> 0 | I15: =IFERROR(COUNTIFS('Event stream steps'!$C$2:$C$331,$A15,'Event stream steps'!$D$2:$D$331,$B15,'Event stream steps'!$G$2:$G$331,I$6)/$C15,0) -> 0 | J15: =IFERROR(COUNTIFS('Event stream steps'!$C$2:$C$331,$A15,'Event stream steps'!$D$2:$D$331,$B15,'Event stream steps'!$G$2:$G$331,J$6)/$C15,0) -> 0 | K15: =IFERROR(COUNTIFS('Event stream steps'!$C$2:$C$331,$A15,'Event stream steps'!$D$2:$D$331,$B15,'Event stream steps'!$G$2:$G$331,K$6)/$C15,0) -> 0 | M15: =IFERROR(COUNTIFS('Event stream steps'!$C$2:$C$331,$A15,'Event stream steps'!$D$2:$D$331,$B15,'Event stream steps'!$I$2:$I$331,M$6)/$C15,0) -> 0 | N15: =IFERROR(COUNTIFS('Event stream steps'!$C$2:$C$331,$A15,'Event stream steps'!$D$2:$D$331,$B15,'Event stream steps'!$I$2:$I$331,N$6)/$C15,0) -> 1 | P15: =IFERROR(COUNTIFS('Event stream steps'!$C$2:$C$331,$A15,'Event stream steps'!$D$2:$D$331,$B15,'Event stream steps'!$K$2:$K$331,P$6)/$C15,0) -> 0.78125 | Q15: =IFERROR(COUNTIFS('Event stream steps'!$C$2:$C$331,$A15,'Event stream steps'!$D$2:$D$331,$B15,'Event stream steps'!$K$2:$K$331,Q$6)/$C15,0) -> 0.21875 | R15: =IFERROR(COUNTIFS('Event stream steps'!$C$2:$C$331,$A15,'Event stream steps'!$D$2:$D$331,$B15,'Event stream steps'!$K$2:$K$331,R$6)/$C15,0) -> 0
A16: Home | B16: Renewal | C16: =COUNTIFS('Event stream steps'!$C$2:$C$331,$A16,'Event stream steps'!$D$2:$D$331,$B16) -> 45 | D16: =IFERROR(COUNTIFS('Event stream steps'!$C$2:$C$331,$A16,'Event stream steps'!$D$2:$D$331,$B16,'Event stream steps'!$G$2:$G$331,D$6)/$C16,0) -> 1 | E16: =IFERROR(COUNTIFS('Event stream steps'!$C$2:$C$331,$A16,'Event stream steps'!$D$2:$D$331,$B16,'Event stream steps'!$G$2:$G$331,E$6)/$C16,0) -> 0 | F16: =IFERROR(COUNTIFS('Event stream steps'!$C$2:$C$331,$A16,'Event stream steps'!$D$2:$D$331,$B16,'Event stream steps'!$G$2:$G$331,F$6)/$C16,0) -> 0 | G16: =IFERROR(COUNTIFS('Event stream steps'!$C$2:$C$331,$A16,'Event stream steps'!$D$2:$D$331,$B16,'Event stream steps'!$G$2:$G$331,G$6)/$C16,0) -> 0 | H16: =IFERROR(COUNTIFS('Event stream steps'!$C$2:$C$331,$A16,'Event stream steps'!$D$2:$D$331,$B16,'Event stream steps'!$G$2:$G$331,H$6)/$C16,0) -> 0 | I16: =IFERROR(COUNTIFS('Event stream steps'!$C$2:$C$331,$A16,'Event stream steps'!$D$2:$D$331,$B16,'Event stream steps'!$G$2:$G$331,I$6)/$C16,0) -> 0 | J16: =IFERROR(COUNTIFS('Event stream steps'!$C$2:$C$331,$A16,'Event stream steps'!$D$2:$D$331,$B16,'Event stream steps'!$G$2:$G$331,J$6)/$C16,0) -> 0 | K16: =IFERROR(COUNTIFS('Event stream steps'!$C$2:$C$331,$A16,'Event stream steps'!$D$2:$D$331,$B16,'Event stream steps'!$G$2:$G$331,K$6)/$C16,0) -> 0 | M16: =IFERROR(COUNTIFS('Event stream steps'!$C$2:$C$331,$A16,'Event stream steps'!$D$2:$D$331,$B16,'Event stream steps'!$I$2:$I$331,M$6)/$C16,0) -> 0 | N16: =IFERROR(COUNTIFS('Event stream steps'!$C$2:$C$331,$A16,'Event stream steps'!$D$2:$D$331,$B16,'Event stream steps'!$I$2:$I$331,N$6)/$C16,0) -> 1 | P16: =IFERROR(COUNTIFS('Event stream steps'!$C$2:$C$331,$A16,'Event stream steps'!$D$2:$D$331,$B16,'Event stream steps'!$K$2:$K$331,P$6)/$C16,0) -> 0.57777778 | Q16: =IFERROR(COUNTIFS('Event stream steps'!$C$2:$C$331,$A16,'Event stream steps'!$D$2:$D$331,$B16,'Event stream steps'!$K$2:$K$331,Q$6)/$C16,0) -> 0.42222222 | R16: =IFERROR(COUNTIFS('Event stream steps'!$C$2:$C$331,$A16,'Event stream steps'!$D$2:$D$331,$B16,'Event stream steps'!$K$2:$K$331,R$6)/$C16,0) -> 0
A17: Home | B17: MTA | C17: =COUNTIFS('Event stream steps'!$C$2:$C$331,$A17,'Event stream steps'!$D$2:$D$331,$B17) -> 18 | D17: =IFERROR(COUNTIFS('Event stream steps'!$C$2:$C$331,$A17,'Event stream steps'!$D$2:$D$331,$B17,'Event stream steps'!$G$2:$G$331,D$6)/$C17,0) -> 1 | E17: =IFERROR(COUNTIFS('Event stream steps'!$C$2:$C$331,$A17,'Event stream steps'!$D$2:$D$331,$B17,'Event stream steps'!$G$2:$G$331,E$6)/$C17,0) -> 0 | F17: =IFERROR(COUNTIFS('Event stream steps'!$C$2:$C$331,$A17,'Event stream steps'!$D$2:$D$331,$B17,'Event stream steps'!$G$2:$G$331,F$6)/$C17,0) -> 0 | G17: =IFERROR(COUNTIFS('Event stream steps'!$C$2:$C$331,$A17,'Event stream steps'!$D$2:$D$331,$B17,'Event stream steps'!$G$2:$G$331,G$6)/$C17,0) -> 0 | H17: =IFERROR(COUNTIFS('Event stream steps'!$C$2:$C$331,$A17,'Event stream steps'!$D$2:$D$331,$B17,'Event stream steps'!$G$2:$G$331,H$6)/$C17,0) -> 0 | I17: =IFERROR(COUNTIFS('Event stream steps'!$C$2:$C$331,$A17,'Event stream steps'!$D$2:$D$331,$B17,'Event stream steps'!$G$2:$G$331,I$6)/$C17,0) -> 0 | J17: =IFERROR(COUNTIFS('Event stream steps'!$C$2:$C$331,$A17,'Event stream steps'!$D$2:$D$331,$B17,'Event stream steps'!$G$2:$G$331,J$6)/$C17,0) -> 0 | K17: =IFERROR(COUNTIFS('Event stream steps'!$C$2:$C$331,$A17,'Event stream steps'!$D$2:$D$331,$B17,'Event stream steps'!$G$2:$G$331,K$6)/$C17,0) -> 0 | M17: =IFERROR(COUNTIFS('Event stream steps'!$C$2:$C$331,$A17,'Event stream steps'!$D$2:$D$331,$B17,'Event stream steps'!$I$2:$I$331,M$6)/$C17,0) -> 0 | N17: =IFERROR(COUNTIFS('Event stream steps'!$C$2:$C$331,$A17,'Event stream steps'!$D$2:$D$331,$B17,'Event stream steps'!$I$2:$I$331,N$6)/$C17,0) -> 1 | P17: =IFERROR(COUNTIFS('Event stream steps'!$C$2:$C$331,$A17,'Event stream steps'!$D$2:$D$331,$B17,'Event stream steps'!$K$2:$K$331,P$6)/$C17,0) -> 0.61111111 | Q17: =IFERROR(COUNTIFS('Event stream steps'!$C$2:$C$331,$A17,'Event stream steps'!$D$2:$D$331,$B17,'Event stream steps'!$K$2:$K$331,Q$6)/$C17,0) -> 0.38888889 | R17: =IFERROR(COUNTIFS('Event stream steps'!$C$2:$C$331,$A17,'Event stream steps'!$D$2:$D$331,$B17,'Event stream steps'!$K$2:$K$331,R$6)/$C17,0) -> 0
A18: Home | B18: Cancellation | C18: =COUNTIFS('Event stream steps'!$C$2:$C$331,$A18,'Event stream steps'!$D$2:$D$331,$B18) -> 7 | D18: =IFERROR(COUNTIFS('Event stream steps'!$C$2:$C$331,$A18,'Event stream steps'!$D$2:$D$331,$B18,'Event stream steps'!$G$2:$G$331,D$6)/$C18,0) -> 1 | E18: =IFERROR(COUNTIFS('Event stream steps'!$C$2:$C$331,$A18,'Event stream steps'!$D$2:$D$331,$B18,'Event stream steps'!$G$2:$G$331,E$6)/$C18,0) -> 0 | F18: =IFERROR(COUNTIFS('Event stream steps'!$C$2:$C$331,$A18,'Event stream steps'!$D$2:$D$331,$B18,'Event stream steps'!$G$2:$G$331,F$6)/$C18,0) -> 0 | G18: =IFERROR(COUNTIFS('Event stream steps'!$C$2:$C$331,$A18,'Event stream steps'!$D$2:$D$331,$B18,'Event stream steps'!$G$2:$G$331,G$6)/$C18,0) -> 0 | H18: =IFERROR(COUNTIFS('Event stream steps'!$C$2:$C$331,$A18,'Event stream steps'!$D$2:$D$331,$B18,'Event stream steps'!$G$2:$G$331,H$6)/$C18,0) -> 0 | I18: =IFERROR(COUNTIFS('Event stream steps'!$C$2:$C$331,$A18,'Event stream steps'!$D$2:$D$331,$B18,'Event stream steps'!$G$2:$G$331,I$6)/$C18,0) -> 0 | J18: =IFERROR(COUNTIFS('Event stream steps'!$C$2:$C$331,$A18,'Event stream steps'!$D$2:$D$331,$B18,'Event stream steps'!$G$2:$G$331,J$6)/$C18,0) -> 0 | K18: =IFERROR(COUNTIFS('Event stream steps'!$C$2:$C$331,$A18,'Event stream steps'!$D$2:$D$331,$B18,'Event stream steps'!$G$2:$G$331,K$6)/$C18,0) -> 0 | M18: =IFERROR(COUNTIFS('Event stream steps'!$C$2:$C$331,$A18,'Event stream steps'!$D$2:$D$331,$B18,'Event stream steps'!$I$2:$I$331,M$6)/$C18,0) -> 0.14285714 | N18: =IFERROR(COUNTIFS('Event stream steps'!$C$2:$C$331,$A18,'Event stream steps'!$D$2:$D$331,$B18,'Event stream steps'!$I$2:$I$331,N$6)/$C18,0) -> 0.85714286 | P18: =IFERROR(COUNTIFS('Event stream steps'!$C$2:$C$331,$A18,'Event stream steps'!$D$2:$D$331,$B18,'Event stream steps'!$K$2:$K$331,P$6)/$C18,0) -> 1 | Q18: =IFERROR(COUNTIFS('Event stream steps'!$C$2:$C$331,$A18,'Event stream steps'!$D$2:$D$331,$B18,'Event stream steps'!$K$2:$K$331,Q$6)/$C18,0) -> 0 | R18: =IFERROR(COUNTIFS('Event stream steps'!$C$2:$C$331,$A18,'Event stream steps'!$D$2:$D$331,$B18,'Event stream steps'!$K$2:$K$331,R$6)/$C18,0) -> 0
A19: Home | B19: Arrears | C19: =COUNTIFS('Event stream steps'!$C$2:$C$331,$A19,'Event stream steps'!$D$2:$D$331,$B19) -> 5 | D19: =IFERROR(COUNTIFS('Event stream steps'!$C$2:$C$331,$A19,'Event stream steps'!$D$2:$D$331,$B19,'Event stream steps'!$G$2:$G$331,D$6)/$C19,0) -> 1 | E19: =IFERROR(COUNTIFS('Event stream steps'!$C$2:$C$331,$A19,'Event stream steps'!$D$2:$D$331,$B19,'Event stream steps'!$G$2:$G$331,E$6)/$C19,0) -> 0 | F19: =IFERROR(COUNTIFS('Event stream steps'!$C$2:$C$331,$A19,'Event stream steps'!$D$2:$D$331,$B19,'Event stream steps'!$G$2:$G$331,F$6)/$C19,0) -> 0 | G19: =IFERROR(COUNTIFS('Event stream steps'!$C$2:$C$331,$A19,'Event stream steps'!$D$2:$D$331,$B19,'Event stream steps'!$G$2:$G$331,G$6)/$C19,0) -> 0 | H19: =IFERROR(COUNTIFS('Event stream steps'!$C$2:$C$331,$A19,'Event stream steps'!$D$2:$D$331,$B19,'Event stream steps'!$G$2:$G$331,H$6)/$C19,0) -> 0 | I19: =IFERROR(COUNTIFS('Event stream steps'!$C$2:$C$331,$A19,'Event stream steps'!$D$2:$D$331,$B19,'Event stream steps'!$G$2:$G$331,I$6)/$C19,0) -> 0 | J19: =IFERROR(COUNTIFS('Event stream steps'!$C$2:$C$331,$A19,'Event stream steps'!$D$2:$D$331,$B19,'Event stream steps'!$G$2:$G$331,J$6)/$C19,0) -> 0 | K19: =IFERROR(COUNTIFS('Event stream steps'!$C$2:$C$331,$A19,'Event stream steps'!$D$2:$D$331,$B19,'Event stream steps'!$G$2:$G$331,K$6)/$C19,0) -> 0 | M19: =IFERROR(COUNTIFS('Event stream steps'!$C$2:$C$331,$A19,'Event stream steps'!$D$2:$D$331,$B19,'Event stream steps'!$I$2:$I$331,M$6)/$C19,0) -> 0 | N19: =IFERROR(COUNTIFS('Event stream steps'!$C$2:$C$331,$A19,'Event stream steps'!$D$2:$D$331,$B19,'Event stream steps'!$I$2:$I$331,N$6)/$C19,0) -> 1 | P19: =IFERROR(COUNTIFS('Event stream steps'!$C$2:$C$331,$A19,'Event stream steps'!$D$2:$D$331,$B19,'Event stream steps'!$K$2:$K$331,P$6)/$C19,0) -> 1 | Q19: =IFERROR(COUNTIFS('Event stream steps'!$C$2:$C$331,$A19,'Event stream steps'!$D$2:$D$331,$B19,'Event stream steps'!$K$2:$K$331,Q$6)/$C19,0) -> 0 | R19: =IFERROR(COUNTIFS('Event stream steps'!$C$2:$C$331,$A19,'Event stream steps'!$D$2:$D$331,$B19,'Event stream steps'!$K$2:$K$331,R$6)/$C19,0) -> 0
A20: Home | B20: Claims | C20: =COUNTIFS('Event stream steps'!$C$2:$C$331,$A20,'Event stream steps'!$D$2:$D$331,$B20) -> 4 | D20: =IFERROR(COUNTIFS('Event stream steps'!$C$2:$C$331,$A20,'Event stream steps'!$D$2:$D$331,$B20,'Event stream steps'!$G$2:$G$331,D$6)/$C20,0) -> 1 | E20: =IFERROR(COUNTIFS('Event stream steps'!$C$2:$C$331,$A20,'Event stream steps'!$D$2:$D$331,$B20,'Event stream steps'!$G$2:$G$331,E$6)/$C20,0) -> 0 | F20: =IFERROR(COUNTIFS('Event stream steps'!$C$2:$C$331,$A20,'Event stream steps'!$D$2:$D$331,$B20,'Event stream steps'!$G$2:$G$331,F$6)/$C20,0) -> 0 | G20: =IFERROR(COUNTIFS('Event stream steps'!$C$2:$C$331,$A20,'Event stream steps'!$D$2:$D$331,$B20,'Event stream steps'!$G$2:$G$331,G$6)/$C20,0) -> 0 | H20: =IFERROR(COUNTIFS('Event stream steps'!$C$2:$C$331,$A20,'Event stream steps'!$D$2:$D$331,$B20,'Event stream steps'!$G$2:$G$331,H$6)/$C20,0) -> 0 | I20: =IFERROR(COUNTIFS('Event stream steps'!$C$2:$C$331,$A20,'Event stream steps'!$D$2:$D$331,$B20,'Event stream steps'!$G$2:$G$331,I$6)/$C20,0) -> 0 | J20: =IFERROR(COUNTIFS('Event stream steps'!$C$2:$C$331,$A20,'Event stream steps'!$D$2:$D$331,$B20,'Event stream steps'!$G$2:$G$331,J$6)/$C20,0) -> 0 | K20: =IFERROR(COUNTIFS('Event stream steps'!$C$2:$C$331,$A20,'Event stream steps'!$D$2:$D$331,$B20,'Event stream steps'!$G$2:$G$331,K$6)/$C20,0) -> 0 | M20: =IFERROR(COUNTIFS('Event stream steps'!$C$2:$C$331,$A20,'Event stream steps'!$D$2:$D$331,$B20,'Event stream steps'!$I$2:$I$331,M$6)/$C20,0) -> 0 | N20: =IFERROR(COUNTIFS('Event stream steps'!$C$2:$C$331,$A20,'Event stream steps'!$D$2:$D$331,$B20,'Event stream steps'!$I$2:$I$331,N$6)/$C20,0) -> 1 | P20: =IFERROR(COUNTIFS('Event stream steps'!$C$2:$C$331,$A20,'Event stream steps'!$D$2:$D$331,$B20,'Event stream steps'!$K$2:$K$331,P$6)/$C20,0) -> 0.75 | Q20: =IFERROR(COUNTIFS('Event stream steps'!$C$2:$C$331,$A20,'Event stream steps'!$D$2:$D$331,$B20,'Event stream steps'!$K$2:$K$331,Q$6)/$C20,0) -> 0.25 | R20: =IFERROR(COUNTIFS('Event stream steps'!$C$2:$C$331,$A20,'Event stream steps'!$D$2:$D$331,$B20,'Event stream steps'!$K$2:$K$331,R$6)/$C20,0) -> 0
A21: Home | B21: Doc Request | C21: =COUNTIFS('Event stream steps'!$C$2:$C$331,$A21,'Event stream steps'!$D$2:$D$331,$B21) -> 5 | D21: =IFERROR(COUNTIFS('Event stream steps'!$C$2:$C$331,$A21,'Event stream steps'!$D$2:$D$331,$B21,'Event stream steps'!$G$2:$G$331,D$6)/$C21,0) -> 1 | E21: =IFERROR(COUNTIFS('Event stream steps'!$C$2:$C$331,$A21,'Event stream steps'!$D$2:$D$331,$B21,'Event stream steps'!$G$2:$G$331,E$6)/$C21,0) -> 0 | F21: =IFERROR(COUNTIFS('Event stream steps'!$C$2:$C$331,$A21,'Event stream steps'!$D$2:$D$331,$B21,'Event stream steps'!$G$2:$G$331,F$6)/$C21,0) -> 0 | G21: =IFERROR(COUNTIFS('Event stream steps'!$C$2:$C$331,$A21,'Event stream steps'!$D$2:$D$331,$B21,'Event stream steps'!$G$2:$G$331,G$6)/$C21,0) -> 0 | H21: =IFERROR(COUNTIFS('Event stream steps'!$C$2:$C$331,$A21,'Event stream steps'!$D$2:$D$331,$B21,'Event stream steps'!$G$2:$G$331,H$6)/$C21,0) -> 0 | I21: =IFERROR(COUNTIFS('Event stream steps'!$C$2:$C$331,$A21,'Event stream steps'!$D$2:$D$331,$B21,'Event stream steps'!$G$2:$G$331,I$6)/$C21,0) -> 0 | J21: =IFERROR(COUNTIFS('Event stream steps'!$C$2:$C$331,$A21,'Event stream steps'!$D$2:$D$331,$B21,'Event stream steps'!$G$2:$G$331,J$6)/$C21,0) -> 0 | K21: =IFERROR(COUNTIFS('Event stream steps'!$C$2:$C$331,$A21,'Event stream steps'!$D$2:$D$331,$B21,'Event stream steps'!$G$2:$G$331,K$6)/$C21,0) -> 0 | M21: =IFERROR(COUNTIFS('Event stream steps'!$C$2:$C$331,$A21,'Event stream steps'!$D$2:$D$331,$B21,'Event stream steps'!$I$2:$I$331,M$6)/$C21,0) -> 0 | N21: =IFERROR(COUNTIFS('Event stream steps'!$C$2:$C$331,$A21,'Event stream steps'!$D$2:$D$331,$B21,'Event stream steps'!$I$2:$I$331,N$6)/$C21,0) -> 1 | P21: =IFERROR(COUNTIFS('Event stream steps'!$C$2:$C$331,$A21,'Event stream steps'!$D$2:$D$331,$B21,'Event stream steps'!$K$2:$K$331,P$6)/$C21,0) -> 0 | Q21: =IFERROR(COUNTIFS('Event stream steps'!$C$2:$C$331,$A21,'Event stream steps'!$D$2:$D$331,$B21,'Event stream steps'!$K$2:$K$331,Q$6)/$C21,0) -> 1 | R21: =IFERROR(COUNTIFS('Event stream steps'!$C$2:$C$331,$A21,'Event stream steps'!$D$2:$D$331,$B21,'Event stream steps'!$K$2:$K$331,R$6)/$C21,0) -> 0
A22: Home | B22: All episodes | C22: =COUNTIFS('Event stream steps'!$C$2:$C$331,$A22) -> 116 | D22: =IFERROR(COUNTIFS('Event stream steps'!$C$2:$C$331,$A22,'Event stream steps'!$G$2:$G$331,D$6)/$C22,0) -> 1 | E22: =IFERROR(COUNTIFS('Event stream steps'!$C$2:$C$331,$A22,'Event stream steps'!$G$2:$G$331,E$6)/$C22,0) -> 0 | F22: =IFERROR(COUNTIFS('Event stream steps'!$C$2:$C$331,$A22,'Event stream steps'!$G$2:$G$331,F$6)/$C22,0) -> 0 | G22: =IFERROR(COUNTIFS('Event stream steps'!$C$2:$C$331,$A22,'Event stream steps'!$G$2:$G$331,G$6)/$C22,0) -> 0 | H22: =IFERROR(COUNTIFS('Event stream steps'!$C$2:$C$331,$A22,'Event stream steps'!$G$2:$G$331,H$6)/$C22,0) -> 0 | I22: =IFERROR(COUNTIFS('Event stream steps'!$C$2:$C$331,$A22,'Event stream steps'!$G$2:$G$331,I$6)/$C22,0) -> 0 | J22: =IFERROR(COUNTIFS('Event stream steps'!$C$2:$C$331,$A22,'Event stream steps'!$G$2:$G$331,J$6)/$C22,0) -> 0 | K22: =IFERROR(COUNTIFS('Event stream steps'!$C$2:$C$331,$A22,'Event stream steps'!$G$2:$G$331,K$6)/$C22,0) -> 0 | M22: =IFERROR(COUNTIFS('Event stream steps'!$C$2:$C$331,$A22,'Event stream steps'!$I$2:$I$331,M$6)/$C22,0) -> 0.0086206897 | N22: =IFERROR(COUNTIFS('Event stream steps'!$C$2:$C$331,$A22,'Event stream steps'!$I$2:$I$331,N$6)/$C22,0) -> 0.99137931 | P22: =IFERROR(COUNTIFS('Event stream steps'!$C$2:$C$331,$A22,'Event stream steps'!$K$2:$K$331,P$6)/$C22,0) -> 0.6637931 | Q22: =IFERROR(COUNTIFS('Event stream steps'!$C$2:$C$331,$A22,'Event stream steps'!$K$2:$K$331,Q$6)/$C22,0) -> 0.3362069 | R22: =IFERROR(COUNTIFS('Event stream steps'!$C$2:$C$331,$A22,'Event stream steps'!$K$2:$K$331,R$6)/$C22,0) -> 0
A23: Van | B23: Acquisition | C23: =COUNTIFS('Event stream steps'!$C$2:$C$331,$A23,'Event stream steps'!$D$2:$D$331,$B23) -> 19 | D23: =IFERROR(COUNTIFS('Event stream steps'!$C$2:$C$331,$A23,'Event stream steps'!$D$2:$D$331,$B23,'Event stream steps'!$G$2:$G$331,D$6)/$C23,0) -> 1 | E23: =IFERROR(COUNTIFS('Event stream steps'!$C$2:$C$331,$A23,'Event stream steps'!$D$2:$D$331,$B23,'Event stream steps'!$G$2:$G$331,E$6)/$C23,0) -> 0 | F23: =IFERROR(COUNTIFS('Event stream steps'!$C$2:$C$331,$A23,'Event stream steps'!$D$2:$D$331,$B23,'Event stream steps'!$G$2:$G$331,F$6)/$C23,0) -> 0 | G23: =IFERROR(COUNTIFS('Event stream steps'!$C$2:$C$331,$A23,'Event stream steps'!$D$2:$D$331,$B23,'Event stream steps'!$G$2:$G$331,G$6)/$C23,0) -> 0 | H23: =IFERROR(COUNTIFS('Event stream steps'!$C$2:$C$331,$A23,'Event stream steps'!$D$2:$D$331,$B23,'Event stream steps'!$G$2:$G$331,H$6)/$C23,0) -> 0 | I23: =IFERROR(COUNTIFS('Event stream steps'!$C$2:$C$331,$A23,'Event stream steps'!$D$2:$D$331,$B23,'Event stream steps'!$G$2:$G$331,I$6)/$C23,0) -> 0 | J23: =IFERROR(COUNTIFS('Event stream steps'!$C$2:$C$331,$A23,'Event stream steps'!$D$2:$D$331,$B23,'Event stream steps'!$G$2:$G$331,J$6)/$C23,0) -> 0 | K23: =IFERROR(COUNTIFS('Event stream steps'!$C$2:$C$331,$A23,'Event stream steps'!$D$2:$D$331,$B23,'Event stream steps'!$G$2:$G$331,K$6)/$C23,0) -> 0 | M23: =IFERROR(COUNTIFS('Event stream steps'!$C$2:$C$331,$A23,'Event stream steps'!$D$2:$D$331,$B23,'Event stream steps'!$I$2:$I$331,M$6)/$C23,0) -> 0 | N23: =IFERROR(COUNTIFS('Event stream steps'!$C$2:$C$331,$A23,'Event stream steps'!$D$2:$D$331,$B23,'Event stream steps'!$I$2:$I$331,N$6)/$C23,0) -> 1 | P23: =IFERROR(COUNTIFS('Event stream steps'!$C$2:$C$331,$A23,'Event stream steps'!$D$2:$D$331,$B23,'Event stream steps'!$K$2:$K$331,P$6)/$C23,0) -> 0.78947368 | Q23: =IFERROR(COUNTIFS('Event stream steps'!$C$2:$C$331,$A23,'Event stream steps'!$D$2:$D$331,$B23,'Event stream steps'!$K$2:$K$331,Q$6)/$C23,0) -> 0.21052632 | R23: =IFERROR(COUNTIFS('Event stream steps'!$C$2:$C$331,$A23,'Event stream steps'!$D$2:$D$331,$B23,'Event stream steps'!$K$2:$K$331,R$6)/$C23,0) -> 0
A24: Van | B24: Renewal | C24: =COUNTIFS('Event stream steps'!$C$2:$C$331,$A24,'Event stream steps'!$D$2:$D$331,$B24) -> 27 | D24: =IFERROR(COUNTIFS('Event stream steps'!$C$2:$C$331,$A24,'Event stream steps'!$D$2:$D$331,$B24,'Event stream steps'!$G$2:$G$331,D$6)/$C24,0) -> 1 | E24: =IFERROR(COUNTIFS('Event stream steps'!$C$2:$C$331,$A24,'Event stream steps'!$D$2:$D$331,$B24,'Event stream steps'!$G$2:$G$331,E$6)/$C24,0) -> 0 | F24: =IFERROR(COUNTIFS('Event stream steps'!$C$2:$C$331,$A24,'Event stream steps'!$D$2:$D$331,$B24,'Event stream steps'!$G$2:$G$331,F$6)/$C24,0) -> 0 | G24: =IFERROR(COUNTIFS('Event stream steps'!$C$2:$C$331,$A24,'Event stream steps'!$D$2:$D$331,$B24,'Event stream steps'!$G$2:$G$331,G$6)/$C24,0) -> 0 | H24: =IFERROR(COUNTIFS('Event stream steps'!$C$2:$C$331,$A24,'Event stream steps'!$D$2:$D$331,$B24,'Event stream steps'!$G$2:$G$331,H$6)/$C24,0) -> 0 | I24: =IFERROR(COUNTIFS('Event stream steps'!$C$2:$C$331,$A24,'Event stream steps'!$D$2:$D$331,$B24,'Event stream steps'!$G$2:$G$331,I$6)/$C24,0) -> 0 | J24: =IFERROR(COUNTIFS('Event stream steps'!$C$2:$C$331,$A24,'Event stream steps'!$D$2:$D$331,$B24,'Event stream steps'!$G$2:$G$331,J$6)/$C24,0) -> 0 | K24: =IFERROR(COUNTIFS('Event stream steps'!$C$2:$C$331,$A24,'Event stream steps'!$D$2:$D$331,$B24,'Event stream steps'!$G$2:$G$331,K$6)/$C24,0) -> 0 | M24: =IFERROR(COUNTIFS('Event stream steps'!$C$2:$C$331,$A24,'Event stream steps'!$D$2:$D$331,$B24,'Event stream steps'!$I$2:$I$331,M$6)/$C24,0) -> 0 | N24: =IFERROR(COUNTIFS('Event stream steps'!$C$2:$C$331,$A24,'Event stream steps'!$D$2:$D$331,$B24,'Event stream steps'!$I$2:$I$331,N$6)/$C24,0) -> 1 | P24: =IFERROR(COUNTIFS('Event stream steps'!$C$2:$C$331,$A24,'Event stream steps'!$D$2:$D$331,$B24,'Event stream steps'!$K$2:$K$331,P$6)/$C24,0) -> 0.62962963 | Q24: =IFERROR(COUNTIFS('Event stream steps'!$C$2:$C$331,$A24,'Event stream steps'!$D$2:$D$331,$B24,'Event stream steps'!$K$2:$K$331,Q$6)/$C24,0) -> 0.37037037 | R24: =IFERROR(COUNTIFS('Event stream steps'!$C$2:$C$331,$A24,'Event stream steps'!$D$2:$D$331,$B24,'Event stream steps'!$K$2:$K$331,R$6)/$C24,0) -> 0
A25: Van | B25: MTA | C25: =COUNTIFS('Event stream steps'!$C$2:$C$331,$A25,'Event stream steps'!$D$2:$D$331,$B25) -> 16 | D25: =IFERROR(COUNTIFS('Event stream steps'!$C$2:$C$331,$A25,'Event stream steps'!$D$2:$D$331,$B25,'Event stream steps'!$G$2:$G$331,D$6)/$C25,0) -> 1 | E25: =IFERROR(COUNTIFS('Event stream steps'!$C$2:$C$331,$A25,'Event stream steps'!$D$2:$D$331,$B25,'Event stream steps'!$G$2:$G$331,E$6)/$C25,0) -> 0 | F25: =IFERROR(COUNTIFS('Event stream steps'!$C$2:$C$331,$A25,'Event stream steps'!$D$2:$D$331,$B25,'Event stream steps'!$G$2:$G$331,F$6)/$C25,0) -> 0 | G25: =IFERROR(COUNTIFS('Event stream steps'!$C$2:$C$331,$A25,'Event stream steps'!$D$2:$D$331,$B25,'Event stream steps'!$G$2:$G$331,G$6)/$C25,0) -> 0 | H25: =IFERROR(COUNTIFS('Event stream steps'!$C$2:$C$331,$A25,'Event stream steps'!$D$2:$D$331,$B25,'Event stream steps'!$G$2:$G$331,H$6)/$C25,0) -> 0 | I25: =IFERROR(COUNTIFS('Event stream steps'!$C$2:$C$331,$A25,'Event stream steps'!$D$2:$D$331,$B25,'Event stream steps'!$G$2:$G$331,I$6)/$C25,0) -> 0 | J25: =IFERROR(COUNTIFS('Event stream steps'!$C$2:$C$331,$A25,'Event stream steps'!$D$2:$D$331,$B25,'Event stream steps'!$G$2:$G$331,J$6)/$C25,0) -> 0 | K25: =IFERROR(COUNTIFS('Event stream steps'!$C$2:$C$331,$A25,'Event stream steps'!$D$2:$D$331,$B25,'Event stream steps'!$G$2:$G$331,K$6)/$C25,0) -> 0 | M25: =IFERROR(COUNTIFS('Event stream steps'!$C$2:$C$331,$A25,'Event stream steps'!$D$2:$D$331,$B25,'Event stream steps'!$I$2:$I$331,M$6)/$C25,0) -> 0 | N25: =IFERROR(COUNTIFS('Event stream steps'!$C$2:$C$331,$A25,'Event stream steps'!$D$2:$D$331,$B25,'Event stream steps'!$I$2:$I$331,N$6)/$C25,0) -> 1 | P25: =IFERROR(COUNTIFS('Event stream steps'!$C$2:$C$331,$A25,'Event stream steps'!$D$2:$D$331,$B25,'Event stream steps'!$K$2:$K$331,P$6)/$C25,0) -> 0.6875 | Q25: =IFERROR(COUNTIFS('Event stream steps'!$C$2:$C$331,$A25,'Event stream steps'!$D$2:$D$331,$B25,'Event stream steps'!$K$2:$K$331,Q$6)/$C25,0) -> 0.3125 | R25: =IFERROR(COUNTIFS('Event stream steps'!$C$2:$C$331,$A25,'Event stream steps'!$D$2:$D$331,$B25,'Event stream steps'!$K$2:$K$331,R$6)/$C25,0) -> 0
A26: Van | B26: Cancellation | C26: =COUNTIFS('Event stream steps'!$C$2:$C$331,$A26,'Event stream steps'!$D$2:$D$331,$B26) -> 6 | D26: =IFERROR(COUNTIFS('Event stream steps'!$C$2:$C$331,$A26,'Event stream steps'!$D$2:$D$331,$B26,'Event stream steps'!$G$2:$G$331,D$6)/$C26,0) -> 1 | E26: =IFERROR(COUNTIFS('Event stream steps'!$C$2:$C$331,$A26,'Event stream steps'!$D$2:$D$331,$B26,'Event stream steps'!$G$2:$G$331,E$6)/$C26,0) -> 0 | F26: =IFERROR(COUNTIFS('Event stream steps'!$C$2:$C$331,$A26,'Event stream steps'!$D$2:$D$331,$B26,'Event stream steps'!$G$2:$G$331,F$6)/$C26,0) -> 0 | G26: =IFERROR(COUNTIFS('Event stream steps'!$C$2:$C$331,$A26,'Event stream steps'!$D$2:$D$331,$B26,'Event stream steps'!$G$2:$G$331,G$6)/$C26,0) -> 0 | H26: =IFERROR(COUNTIFS('Event stream steps'!$C$2:$C$331,$A26,'Event stream steps'!$D$2:$D$331,$B26,'Event stream steps'!$G$2:$G$331,H$6)/$C26,0) -> 0 | I26: =IFERROR(COUNTIFS('Event stream steps'!$C$2:$C$331,$A26,'Event stream steps'!$D$2:$D$331,$B26,'Event stream steps'!$G$2:$G$331,I$6)/$C26,0) -> 0 | J26: =IFERROR(COUNTIFS('Event stream steps'!$C$2:$C$331,$A26,'Event stream steps'!$D$2:$D$331,$B26,'Event stream steps'!$G$2:$G$331,J$6)/$C26,0) -> 0 | K26: =IFERROR(COUNTIFS('Event stream steps'!$C$2:$C$331,$A26,'Event stream steps'!$D$2:$D$331,$B26,'Event stream steps'!$G$2:$G$331,K$6)/$C26,0) -> 0 | M26: =IFERROR(COUNTIFS('Event stream steps'!$C$2:$C$331,$A26,'Event stream steps'!$D$2:$D$331,$B26,'Event stream steps'!$I$2:$I$331,M$6)/$C26,0) -> 0.16666667 | N26: =IFERROR(COUNTIFS('Event stream steps'!$C$2:$C$331,$A26,'Event stream steps'!$D$2:$D$331,$B26,'Event stream steps'!$I$2:$I$331,N$6)/$C26,0) -> 0.83333333 | P26: =IFERROR(COUNTIFS('Event stream steps'!$C$2:$C$331,$A26,'Event stream steps'!$D$2:$D$331,$B26,'Event stream steps'!$K$2:$K$331,P$6)/$C26,0) -> 1 | Q26: =IFERROR(COUNTIFS('Event stream steps'!$C$2:$C$331,$A26,'Event stream steps'!$D$2:$D$331,$B26,'Event stream steps'!$K$2:$K$331,Q$6)/$C26,0) -> 0 | R26: =IFERROR(COUNTIFS('Event stream steps'!$C$2:$C$331,$A26,'Event stream steps'!$D$2:$D$331,$B26,'Event stream steps'!$K$2:$K$331,R$6)/$C26,0) -> 0
A27: Van | B27: Arrears | C27: =COUNTIFS('Event stream steps'!$C$2:$C$331,$A27,'Event stream steps'!$D$2:$D$331,$B27) -> 6 | D27: =IFERROR(COUNTIFS('Event stream steps'!$C$2:$C$331,$A27,'Event stream steps'!$D$2:$D$331,$B27,'Event stream steps'!$G$2:$G$331,D$6)/$C27,0) -> 1 | E27: =IFERROR(COUNTIFS('Event stream steps'!$C$2:$C$331,$A27,'Event stream steps'!$D$2:$D$331,$B27,'Event stream steps'!$G$2:$G$331,E$6)/$C27,0) -> 0 | F27: =IFERROR(COUNTIFS('Event stream steps'!$C$2:$C$331,$A27,'Event stream steps'!$D$2:$D$331,$B27,'Event stream steps'!$G$2:$G$331,F$6)/$C27,0) -> 0 | G27: =IFERROR(COUNTIFS('Event stream steps'!$C$2:$C$331,$A27,'Event stream steps'!$D$2:$D$331,$B27,'Event stream steps'!$G$2:$G$331,G$6)/$C27,0) -> 0 | H27: =IFERROR(COUNTIFS('Event stream steps'!$C$2:$C$331,$A27,'Event stream steps'!$D$2:$D$331,$B27,'Event stream steps'!$G$2:$G$331,H$6)/$C27,0) -> 0 | I27: =IFERROR(COUNTIFS('Event stream steps'!$C$2:$C$331,$A27,'Event stream steps'!$D$2:$D$331,$B27,'Event stream steps'!$G$2:$G$331,I$6)/$C27,0) -> 0 | J27: =IFERROR(COUNTIFS('Event stream steps'!$C$2:$C$331,$A27,'Event stream steps'!$D$2:$D$331,$B27,'Event stream steps'!$G$2:$G$331,J$6)/$C27,0) -> 0 | K27: =IFERROR(COUNTIFS('Event stream steps'!$C$2:$C$331,$A27,'Event stream steps'!$D$2:$D$331,$B27,'Event stream steps'!$G$2:$G$331,K$6)/$C27,0) -> 0 | M27: =IFERROR(COUNTIFS('Event stream steps'!$C$2:$C$331,$A27,'Event stream steps'!$D$2:$D$331,$B27,'Event stream steps'!$I$2:$I$331,M$6)/$C27,0) -> 0 | N27: =IFERROR(COUNTIFS('Event stream steps'!$C$2:$C$331,$A27,'Event stream steps'!$D$2:$D$331,$B27,'Event stream steps'!$I$2:$I$331,N$6)/$C27,0) -> 1 | P27: =IFERROR(COUNTIFS('Event stream steps'!$C$2:$C$331,$A27,'Event stream steps'!$D$2:$D$331,$B27,'Event stream steps'!$K$2:$K$331,P$6)/$C27,0) -> 1 | Q27: =IFERROR(COUNTIFS('Event stream steps'!$C$2:$C$331,$A27,'Event stream steps'!$D$2:$D$331,$B27,'Event stream steps'!$K$2:$K$331,Q$6)/$C27,0) -> 0 | R27: =IFERROR(COUNTIFS('Event stream steps'!$C$2:$C$331,$A27,'Event stream steps'!$D$2:$D$331,$B27,'Event stream steps'!$K$2:$K$331,R$6)/$C27,0) -> 0
A28: Van | B28: Claims | C28: =COUNTIFS('Event stream steps'!$C$2:$C$331,$A28,'Event stream steps'!$D$2:$D$331,$B28) -> 1 | D28: =IFERROR(COUNTIFS('Event stream steps'!$C$2:$C$331,$A28,'Event stream steps'!$D$2:$D$331,$B28,'Event stream steps'!$G$2:$G$331,D$6)/$C28,0) -> 1 | E28: =IFERROR(COUNTIFS('Event stream steps'!$C$2:$C$331,$A28,'Event stream steps'!$D$2:$D$331,$B28,'Event stream steps'!$G$2:$G$331,E$6)/$C28,0) -> 0 | F28: =IFERROR(COUNTIFS('Event stream steps'!$C$2:$C$331,$A28,'Event stream steps'!$D$2:$D$331,$B28,'Event stream steps'!$G$2:$G$331,F$6)/$C28,0) -> 0 | G28: =IFERROR(COUNTIFS('Event stream steps'!$C$2:$C$331,$A28,'Event stream steps'!$D$2:$D$331,$B28,'Event stream steps'!$G$2:$G$331,G$6)/$C28,0) -> 0 | H28: =IFERROR(COUNTIFS('Event stream steps'!$C$2:$C$331,$A28,'Event stream steps'!$D$2:$D$331,$B28,'Event stream steps'!$G$2:$G$331,H$6)/$C28,0) -> 0 | I28: =IFERROR(COUNTIFS('Event stream steps'!$C$2:$C$331,$A28,'Event stream steps'!$D$2:$D$331,$B28,'Event stream steps'!$G$2:$G$331,I$6)/$C28,0) -> 0 | J28: =IFERROR(COUNTIFS('Event stream steps'!$C$2:$C$331,$A28,'Event stream steps'!$D$2:$D$331,$B28,'Event stream steps'!$G$2:$G$331,J$6)/$C28,0) -> 0 | K28: =IFERROR(COUNTIFS('Event stream steps'!$C$2:$C$331,$A28,'Event stream steps'!$D$2:$D$331,$B28,'Event stream steps'!$G$2:$G$331,K$6)/$C28,0) -> 0 | M28: =IFERROR(COUNTIFS('Event stream steps'!$C$2:$C$331,$A28,'Event stream steps'!$D$2:$D$331,$B28,'Event stream steps'!$I$2:$I$331,M$6)/$C28,0) -> 0 | N28: =IFERROR(COUNTIFS('Event stream steps'!$C$2:$C$331,$A28,'Event stream steps'!$D$2:$D$331,$B28,'Event stream steps'!$I$2:$I$331,N$6)/$C28,0) -> 1 | P28: =IFERROR(COUNTIFS('Event stream steps'!$C$2:$C$331,$A28,'Event stream steps'!$D$2:$D$331,$B28,'Event stream steps'!$K$2:$K$331,P$6)/$C28,0) -> 0 | Q28: =IFERROR(COUNTIFS('Event stream steps'!$C$2:$C$331,$A28,'Event stream steps'!$D$2:$D$331,$B28,'Event stream steps'!$K$2:$K$331,Q$6)/$C28,0) -> 1 | R28: =IFERROR(COUNTIFS('Event stream steps'!$C$2:$C$331,$A28,'Event stream steps'!$D$2:$D$331,$B28,'Event stream steps'!$K$2:$K$331,R$6)/$C28,0) -> 0
A29: Van | B29: Doc Request | C29: =COUNTIFS('Event stream steps'!$C$2:$C$331,$A29,'Event stream steps'!$D$2:$D$331,$B29) -> 6 | D29: =IFERROR(COUNTIFS('Event stream steps'!$C$2:$C$331,$A29,'Event stream steps'!$D$2:$D$331,$B29,'Event stream steps'!$G$2:$G$331,D$6)/$C29,0) -> 1 | E29: =IFERROR(COUNTIFS('Event stream steps'!$C$2:$C$331,$A29,'Event stream steps'!$D$2:$D$331,$B29,'Event stream steps'!$G$2:$G$331,E$6)/$C29,0) -> 0 | F29: =IFERROR(COUNTIFS('Event stream steps'!$C$2:$C$331,$A29,'Event stream steps'!$D$2:$D$331,$B29,'Event stream steps'!$G$2:$G$331,F$6)/$C29,0) -> 0 | G29: =IFERROR(COUNTIFS('Event stream steps'!$C$2:$C$331,$A29,'Event stream steps'!$D$2:$D$331,$B29,'Event stream steps'!$G$2:$G$331,G$6)/$C29,0) -> 0 | H29: =IFERROR(COUNTIFS('Event stream steps'!$C$2:$C$331,$A29,'Event stream steps'!$D$2:$D$331,$B29,'Event stream steps'!$G$2:$G$331,H$6)/$C29,0) -> 0 | I29: =IFERROR(COUNTIFS('Event stream steps'!$C$2:$C$331,$A29,'Event stream steps'!$D$2:$D$331,$B29,'Event stream steps'!$G$2:$G$331,I$6)/$C29,0) -> 0 | J29: =IFERROR(COUNTIFS('Event stream steps'!$C$2:$C$331,$A29,'Event stream steps'!$D$2:$D$331,$B29,'Event stream steps'!$G$2:$G$331,J$6)/$C29,0) -> 0 | K29: =IFERROR(COUNTIFS('Event stream steps'!$C$2:$C$331,$A29,'Event stream steps'!$D$2:$D$331,$B29,'Event stream steps'!$G$2:$G$331,K$6)/$C29,0) -> 0 | M29: =IFERROR(COUNTIFS('Event stream steps'!$C$2:$C$331,$A29,'Event stream steps'!$D$2:$D$331,$B29,'Event stream steps'!$I$2:$I$331,M$6)/$C29,0) -> 0 | N29: =IFERROR(COUNTIFS('Event stream steps'!$C$2:$C$331,$A29,'Event stream steps'!$D$2:$D$331,$B29,'Event stream steps'!$I$2:$I$331,N$6)/$C29,0) -> 1 | P29: =IFERROR(COUNTIFS('Event stream steps'!$C$2:$C$331,$A29,'Event stream steps'!$D$2:$D$331,$B29,'Event stream steps'!$K$2:$K$331,P$6)/$C29,0) -> 0 | Q29: =IFERROR(COUNTIFS('Event stream steps'!$C$2:$C$331,$A29,'Event stream steps'!$D$2:$D$331,$B29,'Event stream steps'!$K$2:$K$331,Q$6)/$C29,0) -> 1 | R29: =IFERROR(COUNTIFS('Event stream steps'!$C$2:$C$331,$A29,'Event stream steps'!$D$2:$D$331,$B29,'Event stream steps'!$K$2:$K$331,R$6)/$C29,0) -> 0
A30: Van | B30: All episodes | C30: =COUNTIFS('Event stream steps'!$C$2:$C$331,$A30) -> 81 | D30: =IFERROR(COUNTIFS('Event stream steps'!$C$2:$C$331,$A30,'Event stream steps'!$G$2:$G$331,D$6)/$C30,0) -> 1 | E30: =IFERROR(COUNTIFS('Event stream steps'!$C$2:$C$331,$A30,'Event stream steps'!$G$2:$G$331,E$6)/$C30,0) -> 0 | F30: =IFERROR(COUNTIFS('Event stream steps'!$C$2:$C$331,$A30,'Event stream steps'!$G$2:$G$331,F$6)/$C30,0) -> 0 | G30: =IFERROR(COUNTIFS('Event stream steps'!$C$2:$C$331,$A30,'Event stream steps'!$G$2:$G$331,G$6)/$C30,0) -> 0 | H30: =IFERROR(COUNTIFS('Event stream steps'!$C$2:$C$331,$A30,'Event stream steps'!$G$2:$G$331,H$6)/$C30,0) -> 0 | I30: =IFERROR(COUNTIFS('Event stream steps'!$C$2:$C$331,$A30,'Event stream steps'!$G$2:$G$331,I$6)/$C30,0) -> 0 | J30: =IFERROR(COUNTIFS('Event stream steps'!$C$2:$C$331,$A30,'Event stream steps'!$G$2:$G$331,J$6)/$C30,0) -> 0 | K30: =IFERROR(COUNTIFS('Event stream steps'!$C$2:$C$331,$A30,'Event stream steps'!$G$2:$G$331,K$6)/$C30,0) -> 0 | M30: =IFERROR(COUNTIFS('Event stream steps'!$C$2:$C$331,$A30,'Event stream steps'!$I$2:$I$331,M$6)/$C30,0) -> 0.012345679 | N30: =IFERROR(COUNTIFS('Event stream steps'!$C$2:$C$331,$A30,'Event stream steps'!$I$2:$I$331,N$6)/$C30,0) -> 0.98765432 | P30: =IFERROR(COUNTIFS('Event stream steps'!$C$2:$C$331,$A30,'Event stream steps'!$K$2:$K$331,P$6)/$C30,0) -> 0.67901235 | Q30: =IFERROR(COUNTIFS('Event stream steps'!$C$2:$C$331,$A30,'Event stream steps'!$K$2:$K$331,Q$6)/$C30,0) -> 0.32098765 | R30: =IFERROR(COUNTIFS('Event stream steps'!$C$2:$C$331,$A30,'Event stream steps'!$K$2:$K$331,R$6)/$C30,0) -> 0
A31: Travel | B31: Acquisition | C31: =COUNTIFS('Event stream steps'!$C$2:$C$331,$A31,'Event stream steps'!$D$2:$D$331,$B31) -> 4 | D31: =IFERROR(COUNTIFS('Event stream steps'!$C$2:$C$331,$A31,'Event stream steps'!$D$2:$D$331,$B31,'Event stream steps'!$G$2:$G$331,D$6)/$C31,0) -> 1 | E31: =IFERROR(COUNTIFS('Event stream steps'!$C$2:$C$331,$A31,'Event stream steps'!$D$2:$D$331,$B31,'Event stream steps'!$G$2:$G$331,E$6)/$C31,0) -> 0 | F31: =IFERROR(COUNTIFS('Event stream steps'!$C$2:$C$331,$A31,'Event stream steps'!$D$2:$D$331,$B31,'Event stream steps'!$G$2:$G$331,F$6)/$C31,0) -> 0 | G31: =IFERROR(COUNTIFS('Event stream steps'!$C$2:$C$331,$A31,'Event stream steps'!$D$2:$D$331,$B31,'Event stream steps'!$G$2:$G$331,G$6)/$C31,0) -> 0 | H31: =IFERROR(COUNTIFS('Event stream steps'!$C$2:$C$331,$A31,'Event stream steps'!$D$2:$D$331,$B31,'Event stream steps'!$G$2:$G$331,H$6)/$C31,0) -> 0 | I31: =IFERROR(COUNTIFS('Event stream steps'!$C$2:$C$331,$A31,'Event stream steps'!$D$2:$D$331,$B31,'Event stream steps'!$G$2:$G$331,I$6)/$C31,0) -> 0 | J31: =IFERROR(COUNTIFS('Event stream steps'!$C$2:$C$331,$A31,'Event stream steps'!$D$2:$D$331,$B31,'Event stream steps'!$G$2:$G$331,J$6)/$C31,0) -> 0 | K31: =IFERROR(COUNTIFS('Event stream steps'!$C$2:$C$331,$A31,'Event stream steps'!$D$2:$D$331,$B31,'Event stream steps'!$G$2:$G$331,K$6)/$C31,0) -> 0 | M31: =IFERROR(COUNTIFS('Event stream steps'!$C$2:$C$331,$A31,'Event stream steps'!$D$2:$D$331,$B31,'Event stream steps'!$I$2:$I$331,M$6)/$C31,0) -> 0 | N31: =IFERROR(COUNTIFS('Event stream steps'!$C$2:$C$331,$A31,'Event stream steps'!$D$2:$D$331,$B31,'Event stream steps'!$I$2:$I$331,N$6)/$C31,0) -> 1 | P31: =IFERROR(COUNTIFS('Event stream steps'!$C$2:$C$331,$A31,'Event stream steps'!$D$2:$D$331,$B31,'Event stream steps'!$K$2:$K$331,P$6)/$C31,0) -> 0.75 | Q31: =IFERROR(COUNTIFS('Event stream steps'!$C$2:$C$331,$A31,'Event stream steps'!$D$2:$D$331,$B31,'Event stream steps'!$K$2:$K$331,Q$6)/$C31,0) -> 0.25 | R31: =IFERROR(COUNTIFS('Event stream steps'!$C$2:$C$331,$A31,'Event stream steps'!$D$2:$D$331,$B31,'Event stream steps'!$K$2:$K$331,R$6)/$C31,0) -> 0
A32: Travel | B32: Renewal | C32: =COUNTIFS('Event stream steps'!$C$2:$C$331,$A32,'Event stream steps'!$D$2:$D$331,$B32) -> 3 | D32: =IFERROR(COUNTIFS('Event stream steps'!$C$2:$C$331,$A32,'Event stream steps'!$D$2:$D$331,$B32,'Event stream steps'!$G$2:$G$331,D$6)/$C32,0) -> 1 | E32: =IFERROR(COUNTIFS('Event stream steps'!$C$2:$C$331,$A32,'Event stream steps'!$D$2:$D$331,$B32,'Event stream steps'!$G$2:$G$331,E$6)/$C32,0) -> 0 | F32: =IFERROR(COUNTIFS('Event stream steps'!$C$2:$C$331,$A32,'Event stream steps'!$D$2:$D$331,$B32,'Event stream steps'!$G$2:$G$331,F$6)/$C32,0) -> 0 | G32: =IFERROR(COUNTIFS('Event stream steps'!$C$2:$C$331,$A32,'Event stream steps'!$D$2:$D$331,$B32,'Event stream steps'!$G$2:$G$331,G$6)/$C32,0) -> 0 | H32: =IFERROR(COUNTIFS('Event stream steps'!$C$2:$C$331,$A32,'Event stream steps'!$D$2:$D$331,$B32,'Event stream steps'!$G$2:$G$331,H$6)/$C32,0) -> 0 | I32: =IFERROR(COUNTIFS('Event stream steps'!$C$2:$C$331,$A32,'Event stream steps'!$D$2:$D$331,$B32,'Event stream steps'!$G$2:$G$331,I$6)/$C32,0) -> 0 | J32: =IFERROR(COUNTIFS('Event stream steps'!$C$2:$C$331,$A32,'Event stream steps'!$D$2:$D$331,$B32,'Event stream steps'!$G$2:$G$331,J$6)/$C32,0) -> 0 | K32: =IFERROR(COUNTIFS('Event stream steps'!$C$2:$C$331,$A32,'Event stream steps'!$D$2:$D$331,$B32,'Event stream steps'!$G$2:$G$331,K$6)/$C32,0) -> 0 | M32: =IFERROR(COUNTIFS('Event stream steps'!$C$2:$C$331,$A32,'Event stream steps'!$D$2:$D$331,$B32,'Event stream steps'!$I$2:$I$331,M$6)/$C32,0) -> 0 | N32: =IFERROR(COUNTIFS('Event stream steps'!$C$2:$C$331,$A32,'Event stream steps'!$D$2:$D$331,$B32,'Event stream steps'!$I$2:$I$331,N$6)/$C32,0) -> 1 | P32: =IFERROR(COUNTIFS('Event stream steps'!$C$2:$C$331,$A32,'Event stream steps'!$D$2:$D$331,$B32,'Event stream steps'!$K$2:$K$331,P$6)/$C32,0) -> 1 | Q32: =IFERROR(COUNTIFS('Event stream steps'!$C$2:$C$331,$A32,'Event stream steps'!$D$2:$D$331,$B32,'Event stream steps'!$K$2:$K$331,Q$6)/$C32,0) -> 0 | R32: =IFERROR(COUNTIFS('Event stream steps'!$C$2:$C$331,$A32,'Event stream steps'!$D$2:$D$331,$B32,'Event stream steps'!$K$2:$K$331,R$6)/$C32,0) -> 0
A33: Travel | B33: All episodes | C33: =COUNTIFS('Event stream steps'!$C$2:$C$331,$A33) -> 7 | D33: =IFERROR(COUNTIFS('Event stream steps'!$C$2:$C$331,$A33,'Event stream steps'!$G$2:$G$331,D$6)/$C33,0) -> 1 | E33: =IFERROR(COUNTIFS('Event stream steps'!$C$2:$C$331,$A33,'Event stream steps'!$G$2:$G$331,E$6)/$C33,0) -> 0 | F33: =IFERROR(COUNTIFS('Event stream steps'!$C$2:$C$331,$A33,'Event stream steps'!$G$2:$G$331,F$6)/$C33,0) -> 0 | G33: =IFERROR(COUNTIFS('Event stream steps'!$C$2:$C$331,$A33,'Event stream steps'!$G$2:$G$331,G$6)/$C33,0) -> 0 | H33: =IFERROR(COUNTIFS('Event stream steps'!$C$2:$C$331,$A33,'Event stream steps'!$G$2:$G$331,H$6)/$C33,0) -> 0 | I33: =IFERROR(COUNTIFS('Event stream steps'!$C$2:$C$331,$A33,'Event stream steps'!$G$2:$G$331,I$6)/$C33,0) -> 0 | J33: =IFERROR(COUNTIFS('Event stream steps'!$C$2:$C$331,$A33,'Event stream steps'!$G$2:$G$331,J$6)/$C33,0) -> 0 | K33: =IFERROR(COUNTIFS('Event stream steps'!$C$2:$C$331,$A33,'Event stream steps'!$G$2:$G$331,K$6)/$C33,0) -> 0 | M33: =IFERROR(COUNTIFS('Event stream steps'!$C$2:$C$331,$A33,'Event stream steps'!$I$2:$I$331,M$6)/$C33,0) -> 0 | N33: =IFERROR(COUNTIFS('Event stream steps'!$C$2:$C$331,$A33,'Event stream steps'!$I$2:$I$331,N$6)/$C33,0) -> 1 | P33: =IFERROR(COUNTIFS('Event stream steps'!$C$2:$C$331,$A33,'Event stream steps'!$K$2:$K$331,P$6)/$C33,0) -> 0.85714286 | Q33: =IFERROR(COUNTIFS('Event stream steps'!$C$2:$C$331,$A33,'Event stream steps'!$K$2:$K$331,Q$6)/$C33,0) -> 0.14285714 | R33: =IFERROR(COUNTIFS('Event stream steps'!$C$2:$C$331,$A33,'Event stream steps'!$K$2:$K$331,R$6)/$C33,0) -> 0
A34: All products | B34: All episodes | C34: =COUNTA('Event stream steps'!$A$2:$A$331) -> 330 | D34: =IFERROR(COUNTIFS('Event stream steps'!$G$2:$G$331,D$6)/$C34,0) -> 1 | E34: =IFERROR(COUNTIFS('Event stream steps'!$G$2:$G$331,E$6)/$C34,0) -> 0 | F34: =IFERROR(COUNTIFS('Event stream steps'!$G$2:$G$331,F$6)/$C34,0) -> 0 | G34: =IFERROR(COUNTIFS('Event stream steps'!$G$2:$G$331,G$6)/$C34,0) -> 0 | H34: =IFERROR(COUNTIFS('Event stream steps'!$G$2:$G$331,H$6)/$C34,0) -> 0 | I34: =IFERROR(COUNTIFS('Event stream steps'!$G$2:$G$331,I$6)/$C34,0) -> 0 | J34: =IFERROR(COUNTIFS('Event stream steps'!$G$2:$G$331,J$6)/$C34,0) -> 0 | K34: =IFERROR(COUNTIFS('Event stream steps'!$G$2:$G$331,K$6)/$C34,0) -> 0 | M34: =IFERROR(COUNTIFS('Event stream steps'!$I$2:$I$331,M$6)/$C34,0) -> 0.015151515 | N34: =IFERROR(COUNTIFS('Event stream steps'!$I$2:$I$331,N$6)/$C34,0) -> 0.98484848 | P34: =IFERROR(COUNTIFS('Event stream steps'!$K$2:$K$331,P$6)/$C34,0) -> 0.64242424 | Q34: =IFERROR(COUNTIFS('Event stream steps'!$K$2:$K$331,Q$6)/$C34,0) -> 0.35757576 | R34: =IFERROR(COUNTIFS('Event stream steps'!$K$2:$K$331,R$6)/$C34,0) -> 0
A36: Percentages on each row add to 100%. Steps counts change only if rows are added to or removed from the Event stream steps tab.

Sheet Source migration
A1: Source tables to migrate
A2: Every table script 04 reads that is not already in ods, grouped by schema. Steps affected counts how many of the 330 event steps depend on the table, following the staging tables the script builds itself, so a table read only by a staging build still shows the steps behind it. The tables script 04 builds are listed too: each one is a decision about whether it becomes an ods object or disappears once its own sources move.
A5: Schema | B5: Tables | C5: Needs triage | D5: Triaged | E5: Already available in ods | F5: Blocked | G5: In progress | H5: Migrated | I5: Not required
A6: edw | B6: =COUNTIF($A$14:$A$55,$A6) -> 9 | C6: =COUNTIFS($A$14:$A$55,$A6,$G$14:$G$55,C$5) -> 9 | D6: =COUNTIFS($A$14:$A$55,$A6,$G$14:$G$55,D$5) -> 0 | E6: =COUNTIFS($A$14:$A$55,$A6,$G$14:$G$55,E$5) -> 0 | F6: =COUNTIFS($A$14:$A$55,$A6,$G$14:$G$55,F$5) -> 0 | G6: =COUNTIFS($A$14:$A$55,$A6,$G$14:$G$55,G$5) -> 0 | H6: =COUNTIFS($A$14:$A$55,$A6,$G$14:$G$55,H$5) -> 0 | I6: =COUNTIFS($A$14:$A$55,$A6,$G$14:$G$55,I$5) -> 0
A7: dlk | B7: =COUNTIF($A$14:$A$55,$A7) -> 26 | C7: =COUNTIFS($A$14:$A$55,$A7,$G$14:$G$55,C$5) -> 26 | D7: =COUNTIFS($A$14:$A$55,$A7,$G$14:$G$55,D$5) -> 0 | E7: =COUNTIFS($A$14:$A$55,$A7,$G$14:$G$55,E$5) -> 0 | F7: =COUNTIFS($A$14:$A$55,$A7,$G$14:$G$55,F$5) -> 0 | G7: =COUNTIFS($A$14:$A$55,$A7,$G$14:$G$55,G$5) -> 0 | H7: =COUNTIFS($A$14:$A$55,$A7,$G$14:$G$55,H$5) -> 0 | I7: =COUNTIFS($A$14:$A$55,$A7,$G$14:$G$55,I$5) -> 0
A8: pii | B8: =COUNTIF($A$14:$A$55,$A8) -> 1 | C8: =COUNTIFS($A$14:$A$55,$A8,$G$14:$G$55,C$5) -> 1 | D8: =COUNTIFS($A$14:$A$55,$A8,$G$14:$G$55,D$5) -> 0 | E8: =COUNTIFS($A$14:$A$55,$A8,$G$14:$G$55,E$5) -> 0 | F8: =COUNTIFS($A$14:$A$55,$A8,$G$14:$G$55,F$5) -> 0 | G8: =COUNTIFS($A$14:$A$55,$A8,$G$14:$G$55,G$5) -> 0 | H8: =COUNTIFS($A$14:$A$55,$A8,$G$14:$G$55,H$5) -> 0 | I8: =COUNTIFS($A$14:$A$55,$A8,$G$14:$G$55,I$5) -> 0
A9: tmp | B9: =COUNTIF($A$14:$A$55,$A9) -> 1 | C9: =COUNTIFS($A$14:$A$55,$A9,$G$14:$G$55,C$5) -> 1 | D9: =COUNTIFS($A$14:$A$55,$A9,$G$14:$G$55,D$5) -> 0 | E9: =COUNTIFS($A$14:$A$55,$A9,$G$14:$G$55,E$5) -> 0 | F9: =COUNTIFS($A$14:$A$55,$A9,$G$14:$G$55,F$5) -> 0 | G9: =COUNTIFS($A$14:$A$55,$A9,$G$14:$G$55,G$5) -> 0 | H9: =COUNTIFS($A$14:$A$55,$A9,$G$14:$G$55,H$5) -> 0 | I9: =COUNTIFS($A$14:$A$55,$A9,$G$14:$G$55,I$5) -> 0
A10: stg | B10: =COUNTIF($A$14:$A$55,$A10) -> 5 | C10: =COUNTIFS($A$14:$A$55,$A10,$G$14:$G$55,C$5) -> 5 | D10: =COUNTIFS($A$14:$A$55,$A10,$G$14:$G$55,D$5) -> 0 | E10: =COUNTIFS($A$14:$A$55,$A10,$G$14:$G$55,E$5) -> 0 | F10: =COUNTIFS($A$14:$A$55,$A10,$G$14:$G$55,F$5) -> 0 | G10: =COUNTIFS($A$14:$A$55,$A10,$G$14:$G$55,G$5) -> 0 | H10: =COUNTIFS($A$14:$A$55,$A10,$G$14:$G$55,H$5) -> 0 | I10: =COUNTIFS($A$14:$A$55,$A10,$G$14:$G$55,I$5) -> 0
A11: All schemas | B11: =COUNTA($A$14:$A$55) -> 42 | C11: =COUNTIF($G$14:$G$55,C$5) -> 42 | D11: =COUNTIF($G$14:$G$55,D$5) -> 0 | E11: =COUNTIF($G$14:$G$55,E$5) -> 0 | F11: =COUNTIF($G$14:$G$55,F$5) -> 0 | G11: =COUNTIF($G$14:$G$55,G$5) -> 0 | H11: =COUNTIF($G$14:$G$55,H$5) -> 0 | I11: =COUNTIF($G$14:$G$55,I$5) -> 0
A13: Schema | B13: Table | C13: Kind | D13: Steps affected | E13: Read directly by | F13: Built in cell | G13: Status | H13: Target in ods | I13: Notes
A14: edw | B14: tbl_fact_policy_renewals | C14: External source | D14: 113 | E14: 5 | G14: Needs triage
A15: edw | B15: tbl_fact_Policy_Mvt | C15: External source | D15: 45 | E15: 0 | G15: Needs triage | I15: read only by stg.Home_PhoneNumbers, stg.JulyPolicyState, stg.Motor_PhoneNumbers and 1 more
A16: edw | B16: tbl_fact_policy_sales | C16: External source | D16: 38 | E16: 0 | G16: Needs triage | I16: read only by stg.GlobalPoliciesSold, stg.VanSales
A17: edw | B17: tbl_ref_Mapping_BAR_Premium_Type | C17: External source | D17: 36 | E17: 1 | G17: Needs triage
A18: edw | B18: EXP_MyChill_Chase_Daily_Snapshot_MotorVan | C18: External source | D18: 29 | E18: 28 | G18: Needs triage
A19: edw | B19: exp_mychill_chase_daily_snapshot_home | C19: External source | D19: 16 | E19: 16 | G19: Needs triage
A20: edw | B20: tbl_fact_policy_mtc | C20: External source | D20: 16 | E20: 5 | G20: Needs triage
A21: edw | B21: tbl_fact_mfq | C21: External source | D21: 4 | E21: 0 | G21: Needs triage | I21: read only by stg.R2B1_4_F1_MFQPrices
A22: edw | B22: tbl_fact_TravelAllQuotesSales | C22: External source | D22: 1 | E22: 1 | G22: Needs triage
A23: dlk | B23: genesys_session_summary | C23: External source | D23: 45 | E23: 2 | G23: Needs triage
A24: dlk | B24: RBSDATA2_NewArchive | C24: External source | D24: 36 | E24: 1 | G24: Needs triage
A25: dlk | B25: MyChillWorkflow_DocumentStatus | C25: External source | D25: 17 | E25: 17 | G25: Needs triage
A26: dlk | B26: EXT_XtremePushResults | C26: External source | D26: 14 | E26: 14 | G26: Needs triage
A27: dlk | B27: mfq_quotequery | C27: External source | D27: 14 | E27: 0 | G27: Needs triage | I27: read only by stg.A0_mfq_derived_data, stg.A1_MotorAcquisitionQuoteInitiated, stg.MFQInsurersQuoted
A28: dlk | B28: HFQ_QuoteDetails_Snapshot_v2 | C28: External source | D28: 13 | E28: 0 | G28: Needs triage | I28: read only by stg.HA1_HFQ_Quotes, stg.HFQ_Quotes
A29: dlk | B29: EXT_XtremePushResults_Policy | C29: External source | D29: 12 | E29: 13 | G29: Needs triage
A30: dlk | B30: MyChill_NewUploadDocumentEvents | C30: External source | D30: 11 | E30: 11 | G30: Needs triage
A31: dlk | B31: HFQ_Response_Quotes | C31: External source | D31: 9 | E31: 4 | G31: Needs triage
A32: dlk | B32: AppliedRenewals_PaymentSuccess | C32: External source | D32: 7 | E32: 5 | G32: Needs triage
A33: dlk | B33: MFQ_QuoteResponses | C33: External source | D33: 7 | E33: 0 | G33: Needs triage | I33: read only by stg.MFQInsurersQuoted
A34: dlk | B34: MFQ_QuoteSummary | C34: External source | D34: 7 | E34: 0 | G34: Needs triage | I34: read only by stg.MFQInsurersQuoted
A35: dlk | B35: EXT_Home_QS_ClaimDetails | C35: External source | D35: 6 | E35: 6 | G35: Needs triage
A36: dlk | B36: ext_home_qs_policydetails | C36: External source | D36: 6 | E36: 6 | G36: Needs triage
A37: dlk | B37: EXT_Travel_policy | C37: External source | D37: 4 | E37: 1 | G37: Needs triage
A38: dlk | B38: EXT_Travel_Quotes | C38: External source | D38: 4 | E38: 1 | G38: Needs triage
A39: dlk | B39: HFQ_PaymentRequest_Failed | C39: External source | D39: 4 | E39: 0 | G39: Needs triage | I39: read only by stg.HFQ_Payments
A40: dlk | B40: HFQ_PaymentRequest_Request | C40: External source | D40: 4 | E40: 0 | G40: Needs triage | I40: read only by stg.HFQ_Payments
A41: dlk | B41: HFQ_PaymentRequest_Response | C41: External source | D41: 4 | E41: 0 | G41: Needs triage | I41: read only by stg.HFQ_Payments
A42: dlk | B42: HFQ_PaymentResponse_Response | C42: External source | D42: 4 | E42: 0 | G42: Needs triage | I42: read only by stg.HFQ_Payments
A43: dlk | B43: appliedrenewals_successfulloginevent | C43: External source | D43: 3 | E43: 3 | G43: Needs triage
A44: dlk | B44: rbsdata2_policy_physical | C44: External source | D44: 2 | E44: 0 | G44: Needs triage | I44: read only by stg.HR3B1_LapsedThisYearPolicy, stg.R3B1_LapsedThisYearPolicy
A45: dlk | B45: appliedrenewals_failedloginevent | C45: External source | D45: 1 | E45: 1 | G45: Needs triage
A46: dlk | B46: AppliedRenewals_PaymentFailedEvent | C46: External source | D46: 1 | E46: 1 | G46: Needs triage
A47: dlk | B47: MFQ_MON_Session | C47: External source | D47: 1 | E47: 1 | G47: Needs triage
A48: dlk | B48: vanquotedetails | C48: External source | D48: 1 | E48: 1 | G48: Needs triage
A49: pii | B49: customer_data_assembled | C49: External source | D49: 20 | E49: 0 | G49: Needs triage | I49: read only by stg.DocRequestClientCodes, stg.Home_PhoneNumbers, stg.Motor_PhoneNumbers and 1 more
A50: tmp | B50: CurrentPolicy | C50: External source | D50: 15 | E50: 15 | G50: Needs triage
A51: stg | B51: VM0_van_phone_numbers | C51: Staging table, no build anywhere | D51: 9 | E51: 9 | G51: Needs triage | I51: no build anywhere in the repo or the Fabric extracts
A52: stg | B52: MFQ_Quote_Payments | C52: Staging table, no build anywhere | D52: 5 | E52: 4 | G52: Needs triage | I52: no build anywhere in the repo or the Fabric extracts
A53: stg | B53: A3_SL10_QQGUIDS | C53: Staging table, no build anywhere | D53: 2 | E53: 2 | G53: Needs triage | I53: no build anywhere in the repo or the Fabric extracts
A54: stg | B54: MFQ_quotes | C54: Staging table, no build anywhere | D54: 1 | E54: 1 | G54: Needs triage | I54: no build anywhere in the repo or the Fabric extracts
A55: stg | B55: motorclaims | C55: Staging table, no build anywhere | D55: 1 | E55: 1 | G55: Needs triage | I55: no build anywhere in the repo or the Fabric extracts

Sheet Event stream steps
A1: Step ID | B1: Step name | C1: Product | D1: Episode | E1: Grain | F1: Notebook cell | G1: Status | H1: Notes | I1: Source change | J1: Reads from | K1: Delta change | L1: Known blocker
A2: A1 | B2: Quote Initiated | C2: Motor | D2: Acquisition | E2: Quote | F2: 70 | G2: Unchecked | I2: Needs re-sourcing | J2: dlk | K2: Watermark sits upstream
A3: A1.E1 | B3: Service retrieve | C3: Motor | D3: Acquisition | E3: Quote | F3: 71 | G3: Unchecked | I3: Needs re-sourcing | J3: dlk | K3: Watermark sits upstream
A4: A0 | B4: straight into call centre | C4: Motor | D4: Acquisition | E4: Call | F4: 72 | G4: Unchecked | I4: Needs re-sourcing | J4: dlk | K4: Watermark sits upstream
A5: A0.F1 | B5: Call wait time, or fails to make contact | C5: Motor | D5: Acquisition | E5: Call | F5: 73 | G5: Unchecked | I5: Needs re-sourcing | J5: dlk | K5: Watermark sits upstream
A6: A2 | B6: Customer details complete | C6: Motor | D6: Acquisition | E6: Quote | F6: 74 | G6: Unchecked | I6: Needs re-sourcing | J6: dlk | K6: Windowed in query
A7: A2.F1 | B7: Customer details complete | C7: Motor | D7: Acquisition | E7: Quote | F7: 75 | G7: Unchecked | I7: Needs re-sourcing | J7: dlk | K7: Watermark sits upstream
A8: A2.E1 | B8: This year retrieve (TYR) | C8: Motor | D8: Acquisition | E8: Quote | F8: 76 | G8: Unchecked | I8: Needs re-sourcing | J8: dlk | K8: Windowed in query
A9: A3 | B9: Customer gets a price | C9: Motor | D9: Acquisition | E9: Quote | F9: 77 | G9: Unchecked | I9: Needs re-sourcing | J9: dlk | K9: Windowed in query | L9: no build for stg.a3_sl10_qqguids
A10: A3.F1 | B10: No price returned, told to call us | C10: Motor | D10: Acquisition | E10: Quote | F10: 78 | G10: Unchecked | I10: Needs re-sourcing | J10: dlk | K10: Watermark sits upstream | L10: no build for stg.a3_sl10_qqguids
A11: A3.E1 | B11: Outbound sales callback | C11: Motor | D11: Acquisition | E11: Customer | F11: 79 | G11: Unchecked | I11: Needs re-sourcing | J11: dlk | K11: Watermark sits upstream
A12: A4a | B12: Customer buys ONLINE | C12: Motor | D12: Acquisition | E12: Quote | F12: 80 | G12: Unchecked | I12: Needs re-sourcing | J12: edw | K12: Windowed in query | L12: no build for stg.mfq_quote_payments
A13: A4b | B13: Agent quotes and converts on the CALL | C13: Motor | D13: Acquisition | E13: Policy | F13: 81 | G13: Unchecked | I13: Needs re-sourcing | J13: edw | K13: Watermark sits upstream
A14: A4.F1 | B14: Web assist: starts online, then calls to complete | C14: Motor | D14: Acquisition | E14: Policy | F14: 82 | G14: Unchecked | I14: Needs re-sourcing | J14: edw | K14: Watermark sits upstream
A15: A5a | B15: Payment attempted ONLINE | C15: Motor | D15: Acquisition | E15: Payment Attempt | F15: 83 | G15: Unchecked | I15: Needs re-sourcing | J15: ods only | K15: Windowed in query | L15: no build for stg.mfq_quote_payments
A16: A5.F1 | B16: Payment failed | C16: Motor | D16: Acquisition | E16: Quote | F16: 84 | G16: Unchecked | I16: Needs re-sourcing | J16: ods only | K16: Windowed in query | L16: no build for stg.mfq_quote_payments
A17: A5.1 | B17: Service retrieve | C17: Motor | D17: Acquisition | E17: Policy | F17: 85 | G17: Unchecked | I17: Needs re-sourcing | J17: dlk | K17: Windowed in query
A18: A6 | B18: Documents requested | C18: Motor | D18: Acquisition | E18: Policy | F18: 86 | G18: Unchecked | I18: Needs re-sourcing | J18: edw | K18: Windowed in query
A19: A6.F1 | B19: Chases before the customer submits, and documents never submitted | C19: Motor | D19: Acquisition | E19: Policy | F19: 87 | G19: Unchecked | I19: Needs re-sourcing | J19: edw | K19: Windowed in query
A20: A6.B1.F1 | B20: Documents never submitted, policy at risk. Bites A5a customers hardest | C20: Motor | D20: Acquisition | E20: Policy | F20: 88 | G20: Unchecked | I20: Needs re-sourcing | J20: edw | K20: Windowed in query
A21: A7 | B21: Documents requested | C21: Motor | D21: Acquisition | E21: Policy | F21: 89 | G21: Unchecked | I21: Needs re-sourcing | J21: edw | K21: Windowed in query
A22: A7.F1 | B22: Non-arrival, and time taken to receive | C22: Motor | D22: Acquisition | E22: Policy | F22: 90 | G22: Unchecked | I22: Needs re-sourcing | J22: edw | K22: Windowed in query
A23: A3.B1.1 | B23: Quote retrieved or iterated | C23: Motor | D23: Acquisition | E23: Quote | F23: 91 | G23: Unchecked | I23: Needs re-sourcing | J23: dlk | K23: Watermark sits upstream
A24: A6.B1.1 | B24: Document request issued | C24: Motor | D24: Acquisition | E24: Policy | F24: 92 | G24: Unchecked | I24: Needs re-sourcing | J24: edw | K24: Windowed in query
A25: A6.B1.2 | B25: Customer submits documents | C25: Motor | D25: Acquisition | E25: Policy | F25: 93 | G25: Unchecked | I25: Needs re-sourcing | J25: dlk, edw | K25: Windowed in query
A26: A6.B1.4 | B26: Chase, first reminder | C26: Motor | D26: Acquisition | E26: Policy | F26: 94 | G26: Unchecked | I26: Needs re-sourcing | J26: edw | K26: Windowed in query
A27: A6.B1.5 | B27: Documents requested | C27: Motor | D27: Acquisition | E27: Policy | F27: 95 | G27: Unchecked | I27: Needs re-sourcing | J27: edw | K27: Windowed in query
A28: A6.B1.3 | B28: Documents validated | C28: Motor | D28: Acquisition | E28: Policy | F28: 96 | G28: Unchecked | I28: Needs re-sourcing | J28: dlk, edw | K28: Windowed in query
... A36: A7.B1.5 | B36: Documents requested | C36: Motor | D36: Acquisition | E36: Policy | F36: 104 | G36: Unchecked | I36: Needs re-sourcing | J36: edw | K36: Windowed in query
A37: R0 | B37: Pre-renewal notification, 60 days | C37: Motor | D37: Renewal | E37: Policy | F37: 106 | G37: Unchecked | H37: cell is marked --RO | I37: Needs re-sourcing | J37: edw | K37: Windowed in query
A38: R0.F1 | B38: Not sent - no terms from Insurer | C38: Motor | D38: Renewal | E38: Policy | F38: 107 | G38: Unchecked | I38: Already ods | J38: ods only | K38: Windowed in query
A39: R0.B1 | B39: Renewal held letter | C39: Motor | D39: Renewal | E39: Policy | F39: 108 | G39: Unchecked | I39: Already ods | J39: ods only | K39: Windowed in query
A40: R0.F2 | B40: Declared claims not recorded | C40: Motor | D40: Renewal | E40: Policy | F40: 109 | G40: Unchecked | I40: Needs re-sourcing | J40: edw | K40: Windowed in query | L40: no build for stg.motorclaims
A41: R1a | B41: Renewal invitation sent by EMAIL | C41: Motor | D41: Renewal | E41: Policy | F41: 110 | G41: Unchecked | I41: Needs re-sourcing | J41: edw | K41: Watermark sits upstream
A42: R1b | B42: Renewal invitation sent by POST | C42: Motor | D42: Renewal | E42: Policy | F42: 111 | G42: Unchecked | I42: Needs re-sourcing | J42: edw | K42: Watermark sits upstream
A43: R1.B2 | B43: Alternative offer sent | C43: Motor | D43: Renewal | E43: Policy | F43: 112 | G43: Unchecked | I43: Needs re-sourcing | J43: edw | K43: Windowed in query
A44: R1.E1 | B44: Renewal campaigns: CRM | C44: Motor | D44: Renewal | E44: Policy | F44: 113 | G44: Unchecked | I44: Needs re-sourcing | J44: edw | K44: Windowed in query
A45: R1.E1.F3 | B45: Renewal customer in an acquisition campaign audience | C45: Motor | D45: Renewal | E45: Policy | F45: 114 | G45: Unchecked | I45: Needs re-sourcing | J45: dlk, edw | K45: Windowed in query
A46: R2a | B46: Customer logs in to portal | C46: Motor | D46: Renewal | E46: Policy | F46: 115 | G46: Unchecked | I46: Needs re-sourcing | J46: dlk, edw | K46: Watermark sits upstream
A47: R2b | B47: Customer phones call cente | C47: Motor | D47: Renewal | E47: Call | F47: 116 | G47: Unchecked | I47: Needs re-sourcing | J47: dlk | K47: Watermark sits upstream
A48: R2.F1 | B48: Failed login | C48: Motor | D48: Renewal | E48: Policy | F48: 117 | G48: Unchecked | I48: Needs re-sourcing | J48: dlk, edw | K48: Watermark sits upstream
A49: R2.B1.F1 | B49: New quote does not beat the renewal price, or the quote is abandoned | C49: Motor | D49: Renewal | E49: Policy | F49: 118 | G49: Unchecked | I49: Needs re-sourcing | J49: edw | K49: Windowed in query | L49: no build for stg.mfq_quote_payments
A50: R2.E1 | B50: In-flight price improvement: promo code, or the agent reduces the fee | C50: Motor | D50: Renewal | E50: Policy | F50: 119 | G50: Unchecked | I50: Needs re-sourcing | J50: edw | K50: Windowed in query
A51: R3a | B51: Customer renews ONLINE | C51: Motor | D51: Renewal | E51: Policy | F51: 120 | G51: Unchecked | I51: Needs re-sourcing | J51: dlk, edw | K51: Watermark sits upstream | L51: no build for stg.mfq_quote_payments
A52: R3b | B52: Customer renews on an INBOUND call | C52: Motor | D52: Renewal | E52: Policy | F52: 121 | G52: Unchecked | I52: Needs re-sourcing | J52: dlk, edw | K52: Windowed in query
A53: R3c | B53: Customer renews on an OUTBOUND call | C53: Motor | D53: Renewal | E53: Policy | F53: 122 | G53: Unchecked | I53: Needs re-sourcing | J53: edw | K53: Windowed in query
A54: R3d | B54: Customer renews on CHAT | C54: Motor | D54: Renewal | E54: Policy | F54: 123 | G54: Unchecked | I54: Needs re-sourcing | J54: edw | K54: Windowed in query
A55: R3b.F1 | B55: Call wait time, or fails to make contact | C55: Motor | D55: Renewal | E55: Call | F55: 124 | G55: Unchecked | I55: Needs re-sourcing | J55: dlk | K55: Watermark sits upstream
A56: R3.O1 | B56: Policy lapsed | C56: Motor | D56: Renewal | E56: Policy | F56: 125 | G56: Unchecked | I56: Needs re-sourcing | J56: dlk, edw | K56: Watermark sits upstream
A57: R4 | B57: Payment taken | C57: Motor | D57: Renewal | E57: Policy | F57: 126 | G57: Unchecked | I57: Needs re-sourcing | J57: edw | K57: Watermark sits upstream
A58: R4.F1 | B58: Payment failed | C58: Motor | D58: Renewal | E58: Policy | F58: 127 | G58: Unchecked | I58: Needs re-sourcing | J58: dlk, edw | K58: Watermark sits upstream
A59: R4a | B59: Pay in full | C59: Motor | D59: Renewal | E59: Policy | F59: 128 | G59: Unchecked | I59: Needs re-sourcing | J59: dlk, edw | K59: Watermark sits upstream
A60: R4c | B60: New monthly agreement | C60: Motor | D60: Renewal | E60: Policy | F60: 129 | G60: Unchecked | I60: Needs re-sourcing | J60: dlk, edw | K60: Watermark sits upstream
A61: R5 | B61: Renewal processed, policy continued | C61: Motor | D61: Renewal | E61: Policy | F61: 130 | G61: Unchecked | I61: Needs re-sourcing | J61: edw | K61: Windowed in query
A62: R6 | B62: Cert and disc sent | C62: Motor | D62: Renewal | E62: Policy | F62: 131 | G62: Unchecked | I62: Needs re-sourcing | J62: edw | K62: Windowed in query
A63: R2.B1.1 | B63: MFQ quote started from the renewal price | C63: Motor | D63: Renewal | E63: Policy | F63: 132 | G63: Unchecked | I63: Needs re-sourcing | J63: edw | K63: Watermark sits upstream
A64: R2.B1.2 | B64: Details amended | C64: Motor | D64: Renewal | E64: Policy | F64: 133 | G64: Unchecked | I64: Needs re-sourcing | J64: edw | K64: Watermark sits upstream | L64: no build for stg.mfq_quotes
A65: R2.B1.3 | B65: New price returned | C65: Motor | D65: Renewal | E65: Policy | F65: 134 | G65: Unchecked | I65: Needs re-sourcing | J65: dlk, edw | K65: Watermark sits upstream
A66: R2.B1.3.F1 | B66: No price returned, or the quote is abandoned | C66: Motor | D66: Renewal | E66: Policy | F66: 135 | G66: Unchecked | I66: Needs re-sourcing | J66: dlk, edw | K66: Watermark sits upstream
A67: R2.B1.4.F1 | B67: New price is worse than the renewal offer | C67: Motor | D67: Renewal | E67: Policy | F67: 136 | G67: Unchecked | I67: Needs re-sourcing | J67: dlk, edw | K67: Watermark sits upstream
A68: R2.B1.O1 | B68: Renews on the renewal offer | C68: Motor | D68: Renewal | E68: Policy | F68: 137 | G68: Unchecked | I68: Needs re-sourcing | J68: dlk, edw | K68: Watermark sits upstream
A69: R2.B1.O2 | B69: Renews on a new MFQ price | C69: Motor | D69: Renewal | E69: Policy | F69: 138 | G69: Unchecked | I69: Needs re-sourcing | J69: dlk, edw | K69: Watermark sits upstream
A70: R2.B1.O3 | B70: Buys elsewhere, no renewal | C70: Motor | D70: Renewal | E70: Policy | F70: 139 | G70: Unchecked | I70: Needs re-sourcing | J70: dlk, edw | K70: Watermark sits upstream
A71: R3.B1 | B71: This year lapsed | C71: Motor | D71: Renewal | E71: Policy | F71: 140 | G71: Unchecked | I71: Needs re-sourcing | J71: edw | K71: Watermark sits upstream
A72: R3.B1.1 | B72: Renewal date passes with no renewal | C72: Motor | D72: Renewal | E72: Policy | F72: 141 | G72: Unchecked | I72: Needs re-sourcing | J72: edw | K72: Watermark sits upstream
A73: R3.B1.1.F1 | B73: CRM bounces | C73: Motor | D73: Renewal | E73: Policy | F73: 142 | G73: Unchecked | I73: Needs re-sourcing | J73: dlk, edw | K73: Windowed in query
A74: R3.B1.2 | B74: Lapse CRM sequence runs | C74: Motor | D74: Renewal | E74: Policy | F74: 143 | G74: Unchecked | I74: Needs re-sourcing | J74: dlk, edw | K74: Windowed in query
A75: R3.B1.2.F1 | B75: Unreachable on the lapse sequence | C75: Motor | D75: Renewal | E75: Policy | F75: 144 | G75: Unchecked | I75: Needs re-sourcing | J75: edw | K75: Windowed in query
A76: R3.B1.3 | B76: Online renewal window closes at day 7 | C76: Motor | D76: Renewal | E76: Policy | F76: 145 | G76: Unchecked | I76: Needs re-sourcing | J76: edw | K76: Watermark sits upstream
... A92: R6.B1.5 | B92: Replacement requested | C92: Motor | D92: Renewal | E92: Policy | F92: 161 | G92: Unchecked | I92: Needs re-sourcing | J92: edw | K92: Windowed in query
A93: M1 | B93: Customer calls Chill with a change request | C93: Motor | D93: MTA | E93: Call | F93: 281 | G93: Unchecked | I93: Needs re-sourcing | J93: dlk | K93: Watermark sits upstream | L93: no build for stg.vm0_van_phone_numbers
A94: M1.F1 | B94: Customer calls Chill with a change request | C94: Motor | D94: MTA | E94: Call | F94: 282 | G94: Unchecked | I94: Needs re-sourcing | J94: dlk | K94: Watermark sits upstream | L94: no build for stg.vm0_van_phone_numbers
A95: M3 | B95: Customer accepts | C95: Motor | D95: MTA | E95: Policy | F95: 283 | G95: Unchecked | I95: Needs re-sourcing | J95: dlk, edw | K95: Watermark sits upstream
A96: M4 | B96: Money due on the change | C96: Motor | D96: MTA | E96: Policy | F96: 284 | G96: Unchecked | I96: Needs re-sourcing | J96: dlk, edw | K96: Watermark sits upstream
A97: M4a | B97: Paid now | C97: Motor | D97: MTA | E97: Policy | F97: 285 | G97: Unchecked | I97: Needs re-sourcing | J97: dlk, edw | K97: Watermark sits upstream
A98: M6 | B98: Cert and disc sent | C98: Motor | D98: MTA | E98: Policy | F98: 286 | G98: Unchecked | I98: Needs re-sourcing | J98: dlk, edw | K98: Windowed in query
A99: M.V1 | B99: Vehicle change | C99: Motor | D99: MTA | E99: Call | F99: 287 | G99: Unchecked | I99: Needs re-sourcing | J99: dlk | K99: Watermark sits upstream | L99: no build for stg.vm0_van_phone_numbers
A100: M.V2 | B100: Named driver add or remove | C100: Motor | D100: MTA | E100: Call | F100: 288 | G100: Unchecked | I100: Needs re-sourcing | J100: dlk | K100: Watermark sits upstream | L100: no build for stg.vm0_van_phone_numbers
A101: M.V3 | B101: Licence update | C101: Motor | D101: MTA | E101: Call | F101: 289 | G101: Unchecked | I101: Needs re-sourcing | J101: dlk | K101: Watermark sits upstream | L101: no build for stg.vm0_van_phone_numbers
A102: M.V4 | B102: Address change | C102: Motor | D102: MTA | E102: Call | F102: 290 | G102: Unchecked | I102: Needs re-sourcing | J102: dlk | K102: Watermark sits upstream | L102: no build for stg.vm0_van_phone_numbers
A103: M3.B1.1 | B103: Document request issued | C103: Motor | D103: MTA | E103: Policy | F103: 291 | G103: Unchecked | I103: Needs re-sourcing | J103: edw | K103: Windowed in query
A104: M3.B1.2 | B104: Customer submits documents | C104: Motor | D104: MTA | E104: Policy | F104: 292 | G104: Unchecked | I104: Needs re-sourcing | J104: dlk, edw | K104: Windowed in query
A105: M3.B1.4 | B105: Chase, first reminder | C105: Motor | D105: MTA | E105: Policy | F105: 293 | G105: Unchecked | I105: Needs re-sourcing | J105: edw | K105: Windowed in query
A106: M3.B1.5 | B106: Chase, escalation | C106: Motor | D106: MTA | E106: Policy | F106: 294 | G106: Unchecked | I106: Needs re-sourcing | J106: edw | K106: Windowed in query
A107: M3.B1.3 | B107: Documents validated | C107: Motor | D107: MTA | E107: Policy | F107: 295 | G107: Unchecked | I107: Needs re-sourcing | J107: dlk, edw | K107: Windowed in query
A108: M3.B1.6 | B108: Documents received and validated | C108: Motor | D108: MTA | E108: Policy | F108: 296 | G108: Unchecked | I108: Needs re-sourcing | J108: dlk, edw | K108: Windowed in query
A109: C1a | B109: Customer asks to cancel | C109: Motor | D109: Cancellation | E109: Policy | F109: 297 | G109: Unchecked | I109: Needs re-sourcing | J109: edw | K109: Windowed in query
A110: C1a.F1 | B110: Call wait time, or fails to make contact | C110: Motor | D110: Cancellation | E110: Policy | F110: 298 | G110: Unchecked | I110: Needs re-sourcing | J110: edw | K110: Windowed in query
A111: C2 | B111: Document chase, reminder | C111: Motor | D111: Cancellation | E111: Policy | F111: 299 | G111: Unchecked | I111: Needs re-sourcing | J111: edw | K111: Windowed in query
A112: C3 | B112: Document chase, escalation | C112: Motor | D112: Cancellation | E112: Policy | F112: 300 | G112: Unchecked | I112: Needs re-sourcing | J112: edw | K112: Windowed in query
A113: C4 | B113: Final notice | C113: Motor | D113: Cancellation | E113: Policy | F113: 301 | G113: Unchecked | I113: Needs re-sourcing | J113: edw | K113: Windowed in query
A114: C5 | B114: Cancellation processed | C114: Motor | D114: Cancellation | E114: Policy | F114: 302 | G114: Unchecked | I114: Needs re-sourcing | J114: edw | K114: Windowed in query
... A169: HR2.B1.F1 | B169: The customer shops the renewal | C169: Home | D169: Renewal | E169: Policy | F169: 205 | G169: Unchecked | I169: Needs re-sourcing | J169: dlk, edw | K169: Windowed in query
A170: HR1.E1.F1 | B170: Programme fails and the renewal date is missed | C170: Home | D170: Renewal | E170: Policy | F170: 206 | G170: Unchecked | H170: written by 2 insert statements, in cells 206, 207; cell is marked --HR1.E1 | I170: Needs re-sourcing | J170: dlk, edw | K170: Windowed in query
A171: HR3a | B171: Customer renews ONLINE | C171: Home | D171: Renewal | E171: Policy | F171: 208 | G171: Unchecked | I171: Needs re-sourcing | J171: dlk, edw | K171: Watermark sits upstream
A172: HR3b | B172: Customer renews on an INBOUND call | C172: Home | D172: Renewal | E172: Policy | F172: 209 | G172: Unchecked | I172: Needs re-sourcing | J172: edw | K172: Watermark sits upstream
A173: HR3b.F1 | B173: Call wait time, or fails to make contact | C173: Home | D173: Renewal | E173: Call | F173: 210 | G173: Unchecked | I173: Needs re-sourcing | J173: dlk | K173: Windowed in query
A174: HR3.O1 | B174: Policy lapsed | C174: Home | D174: Renewal | E174: Policy | F174: 211 | G174: Unchecked | I174: Needs re-sourcing | J174: dlk, edw | K174: Watermark sits upstream
A175: HR4 | B175: Payment taken | C175: Home | D175: Renewal | E175: Policy | F175: 212 | G175: Unchecked | I175: Needs re-sourcing | J175: edw | K175: Watermark sits upstream
A176: HR4.B2.F1 | B176: Chases before the customer submits, and documents never submitted | C176: Home | D176: Renewal | E176: Policy | F176: 213 | G176: Unchecked | I176: Needs re-sourcing | J176: edw | K176: Windowed in query
...

Sheet Step to source
A1: Step to source dependencies
A2: One row per route from a step to a source table, ods included. A step that reaches the same source by two routes has two rows. Intermediary lists the tables script 04 builds along the way, source first, so the last name is what the step reads. Blank means the step reads the source itself. 812 routes, covering 330 steps and 46 sources, of which 174 routes are already on ods.
A6: Step | B6: Source table | C6: Intermediary
A7: A1 | B7: dlk.mfq_quotequery | C7: stg.A1_MotorAcquisitionQuoteInitiated
A8: A1.E1 | B8: dlk.mfq_quotequery | C8: stg.A1_MotorAcquisitionQuoteInitiated
A9: A0 | B9: dlk.genesys_session_summary | C9: stg.A0_genesys_derived_data > stg.A0_genesys_derived_data_filtered > stg.A0_MFQ_genesys_link
A10: A0 | B10: dlk.mfq_quotequery | C10: stg.A0_mfq_derived_data > stg.A0_MFQ_genesys_link
A11: A0.F1 | B11: dlk.genesys_session_summary | C11: stg.A0_genesys_derived_data > stg.A0F1_genesys_inbound_call_duration_summary
A12: A2 | B12: dlk.mfq_quotequery | C12: stg.A1_MotorAcquisitionQuoteInitiated
A13: A2.F1 | B13: dlk.mfq_quotequery | C13: stg.A1_MotorAcquisitionQuoteInitiated
A14: A2.E1 | B14: dlk.EXT_XtremePushResults
A15: A3 | B15: dlk.MFQ_MON_Session
A16: A3 | B16: dlk.mfq_quotequery | C16: stg.A1_MotorAcquisitionQuoteInitiated
A17: A3 | B17: dlk.mfq_quotequery | C17: stg.A1_MotorAcquisitionQuoteInitiated > stg.MFQInsurersQuoted
A18: A3 | B18: dlk.mfq_quotequery | C18: stg.MFQInsurersQuoted
A19: A3 | B19: dlk.MFQ_QuoteResponses | C19: stg.MFQInsurersQuoted
A20: A3 | B20: dlk.MFQ_QuoteSummary | C20: stg.MFQInsurersQuoted
A21: A3 | B21: stg.A3_SL10_QQGUIDS
A22: A3.F1 | B22: dlk.mfq_quotequery | C22: stg.A1_MotorAcquisitionQuoteInitiated
A23: A3.F1 | B23: stg.A3_SL10_QQGUIDS
A24: A3.E1 | B24: dlk.genesys_session_summary | C24: stg.A0_genesys_derived_data
A25: A4a | B25: edw.tbl_fact_policy_sales | C25: stg.GlobalPoliciesSold
A26: A4a | B26: stg.MFQ_Quote_Payments
A27: A4b | B27: edw.tbl_fact_policy_sales | C27: stg.GlobalPoliciesSold
A28: A4.F1 | B28: edw.tbl_fact_policy_sales | C28: stg.GlobalPoliciesSold
A29: A5a | B29: stg.MFQ_Quote_Payments
A30: A5.F1 | B30: stg.MFQ_Quote_Payments
A31: A5.1 | B31: dlk.EXT_XtremePushResults
A32: A6 | B32: edw.EXP_MyChill_Chase_Daily_Snapshot_MotorVan
A33: A6.F1 | B33: edw.EXP_MyChill_Chase_Daily_Snapshot_MotorVan
A34: A6.B1.F1 | B34: edw.EXP_MyChill_Chase_Daily_Snapshot_MotorVan
A35: A7 | B35: edw.tbl_fact_policy_sales | C35: stg.GlobalPoliciesSold
A36: A7 | B36: ods.EventStream
A37: A7.F1 | B37: edw.EXP_MyChill_Chase_Daily_Snapshot_MotorVan
A38: A3.B1.1 | B38: dlk.mfq_quotequery | C38: stg.A1_MotorAcquisitionQuoteInitiated
A39: A6.B1.1 | B39: edw.EXP_MyChill_Chase_Daily_Snapshot_MotorVan
A40: A6.B1.2 | B40: dlk.MyChill_NewUploadDocumentEvents
A41: A6.B1.2 | B41: edw.tbl_fact_policy_sales | C41: stg.GlobalPoliciesSold
A42: A6.B1.4 | B42: edw.EXP_MyChill_Chase_Daily_Snapshot_MotorVan
A43: A6.B1.5 | B43: edw.tbl_fact_policy_sales | C43: stg.GlobalPoliciesSold
A44: A6.B1.5 | B44: ods.EventStream
A45: A6.B1.3 | B45: dlk.MyChillWorkflow_DocumentStatus
A46: A6.B1.3 | B46: edw.tbl_fact_policy_sales | C46: stg.GlobalPoliciesSold
A47: A6.B1.O1 | B47: edw.tbl_fact_policy_sales | C47: stg.GlobalPoliciesSold
A48: A6.B1.O1 | B48: ods.EventStream
A49: A6.B1.6 | B49: dlk.MyChillWorkflow_DocumentStatus
A50: A6.B1.6 | B50: edw.tbl_fact_policy_sales | C50: stg.GlobalPoliciesSold
A51: A7.B1 | B51: edw.tbl_fact_policy_sales | C51: stg.GlobalPoliciesSold
A52: A7.B1 | B52: ods.EventStream
A53: A7.B1.1 | B53: edw.tbl_fact_policy_sales | C53: stg.GlobalPoliciesSold
A54: A7.B1.1 | B54: ods.EventStream
A55: A7.B1.2 | B55: edw.tbl_fact_policy_sales | C55: stg.GlobalPoliciesSold
A56: A7.B1.2 | B56: ods.EventStream
A57: A7.B1.3 | B57: edw.tbl_fact_policy_sales | C57: stg.GlobalPoliciesSold
A58: A7.B1.3 | B58: ods.EventStream
A59: A7.B1.4 | B59: edw.EXP_MyChill_Chase_Daily_Snapshot_MotorVan
A60: A7.B1.5 | B60: edw.tbl_fact_policy_sales | C60: stg.GlobalPoliciesSold
A61: A7.B1.5 | B61: ods.EventStream
A62: R0 | B62: edw.tbl_fact_policy_renewals
A63: R0.F1 | B63: ods.EventStream
A64: R0.B1 | B64: ods.EventStream
A65: R0.F2 | B65: edw.tbl_fact_policy_renewals | C65: stg.R0_MotorPoliciesEligibleForRenewals
A66: R0.F2 | B66: stg.motorclaims
A67: R1a | B67: edw.tbl_fact_policy_renewals | C67: stg.R0_MotorPoliciesEligibleForRenewals > stg.R1_Motor_Renewals_EmailOffered
A68: R1a | B68: ods.EventStream | C68: stg.R1_Motor_Renewals_EmailOffered
A69: R1b | B69: edw.tbl_fact_policy_renewals | C69: stg.R0_MotorPoliciesEligibleForRenewals > stg.R1_Motor_Renewals_PostOffered
A70: R1b | B70: ods.EventStream | C70: stg.R1_Motor_Renewals_PostOffered
A71: R1.B2 | B71: edw.tbl_fact_policy_renewals
A72: R1.E1 | B72: edw.tbl_fact_policy_renewals | C72: stg.R0_MotorPoliciesEligibleForRenewals
A73: R1.E1 | B73: ods.scvcampaignhistory
A74: R1.E1.F3 | B74: dlk.EXT_XtremePushResults
A75: R1.E1.F3 | B75: dlk.EXT_XtremePushResults_Policy
A76: R1.E1.F3 | B76: edw.tbl_fact_policy_renewals | C76: stg.R0_MotorPoliciesEligibleForRenewals
A77: R2a | B77: dlk.appliedrenewals_successfulloginevent
A78: R2a | B78: edw.tbl_fact_policy_renewals | C78: stg.R0_MotorPoliciesEligibleForRenewals
A79: R2b | B79: dlk.genesys_session_summary | C79: stg.R0_genesys_derived_data
A80: R2.F1 | B80: dlk.appliedrenewals_failedloginevent
A81: R2.F1 | B81: edw.tbl_fact_policy_renewals | C81: stg.R0_MotorPoliciesEligibleForRenewals
A82: R2.B1.F1 | B82: edw.tbl_fact_policy_renewals | C82: stg.R0_MotorPoliciesEligibleForRenewals > stg.RenewalScvCustomerKeys > stg.RenewalsDoingMFQ
A83: R2.B1.F1 | B83: ods.MFQSCVLink | C83: stg.RenewalsDoingMFQ
A84: R2.B1.F1 | B84: ods.scv_customer_key | C84: stg.RenewalScvCustomerKeys > stg.RenewalsDoingMFQ
A85: R2.B1.F1 | B85: ods.scv_customer_key | C85: stg.RenewalsDoingMFQ
A86: R2.B1.F1 | B86: stg.MFQ_Quote_Payments
A87: R2.E1 | B87: edw.tbl_fact_policy_renewals
A88: R2.E1 | B88: edw.tbl_fact_policy_renewals | C88: stg.R0_MotorPoliciesEligibleForRenewals
A89: R3a | B89: dlk.AppliedRenewals_PaymentSuccess | C89: stg.MotorRenewalsOnline
A90: R3a | B90: edw.tbl_fact_policy_renewals | C90: stg.R0_MotorPoliciesEligibleForRenewals > stg.MotorRenewalsOnline
A91: R3a | B91: edw.tbl_fact_policy_renewals | C91: stg.R0_MotorPoliciesEligibleForRenewals > stg.RenewalScvCustomerKeys > stg.RenewalsDoingMFQ > stg.MotorRenewalsOnline
A92: R3a | B92: ods.MFQSCVLink | C92: stg.RenewalsDoingMFQ > stg.MotorRenewalsOnline
A93: R3a | B93: ods.scv_customer_key | C93: stg.RenewalScvCustomerKeys > stg.RenewalsDoingMFQ > stg.MotorRenewalsOnline
A94: R3a | B94: ods.scv_customer_key | C94: stg.RenewalsDoingMFQ > stg.MotorRenewalsOnline
A95: R3a | B95: stg.MFQ_Quote_Payments | C95: stg.MotorRenewalsOnline
A96: R3b | B96: dlk.RBSDATA2_NewArchive
A97: R3b | B97: edw.tbl_ref_Mapping_BAR_Premium_Type
A98: R3c | B98: edw.tbl_fact_policy_renewals
A99: R3d | B99: edw.tbl_fact_policy_renewals
A100: R3b.F1 | B100: dlk.genesys_session_summary | C100: stg.R0_genesys_derived_data
A101: R3b.F1 | B101: dlk.genesys_session_summary | C101: stg.R0_genesys_derived_data > stg.R3bF1_genesys_inbound_call_duration_summary
A102: R3.O1 | B102: dlk.rbsdata2_policy_physical | C102: stg.R3B1_LapsedThisYearPolicy
A103: R3.O1 | B103: edw.tbl_fact_policy_renewals | C103: stg.R0_MotorPoliciesEligibleForRenewals > stg.R3B1_LapsedThisYearPolicy
...

Sheet Status key
A1: How to use this workbook
A2: Column G is the single status for each query and moves left to right through the list below. Columns I, K and L were filled in from the code in main\04 - Populate Episode Event Stream.ipynb and are a starting point for triage, not a decision. Column H is free text.
A5: Status (column G) | B5: When it applies
A6: Unchecked | B6: Not yet looked at. The starting value for all 330.
A7: Triaged | B7: Read through, work understood, source confirmed to exist. Ready to pick up.
A8: Blocked | B8: Cannot start. The ods object does not exist yet, or a source is missing. Say what in column L.
A9: In progress | B9: Being rewritten.
A10: In review | B10: Rewritten, waiting on a second pair of eyes.
A11: Reconciled | B11: Rebuilt query runs and matches the July baseline volume.
A12: Done | B12: Merged into the production notebook.
A13: Not required | B13: Step being dropped, or a duplicate of another step.
A16: Source change (column I) | B16: Meaning
A17: Already ods | B17: Every table it reads is already in ods. Five queries.
A18: Needs re-sourcing | B18: Reaches edw, dlk, pii or tmp somewhere in the chain, counting the staging tables the notebook builds itself. Column J names which.
... A24: Needs a watermark | B24: No date filter anywhere in the chain.
A27: Picklists
A28: Status | B28: Source change | C28: Delta change | D28: Source migration
A29: Unchecked | B29: Already ods | C29: Windowed in query | D29: Needs triage
A30: Triaged | B30: Needs re-sourcing | C30: Watermark sits upstream | D30: Triaged
A31: Blocked | C31: Needs a watermark | D31: Already available in ods
A32: In progress | D32: Blocked
A33: In review | D33: In progress
A34: Reconciled | D34: Migrated
A35: Done | D35: Not required
A36: Not required
