Workbook

Sheet Missing Inserts
A1: Product | B1: Journey | C1: step_id | D1: Step | E1: Priority | F1: Source for recon | G1: Reporting - Volumes | H1: Fabric Volumes | I1: Status | J1: Stub cell in notebook? | K1: Notebook cell # | L1: Recon doc row | M1: Owner / where found | N1: Query located? | O1: Code status | P1: Line in code
A2: Motor | B2: Renewal | C2: --- | D2: Web assist: starts online, then calls to complete | G2: 24 | H2: 22 | I2: Under Investigation | J2: No cell at all | L2: 96 | O2: no step id assigned
A3: Travel | B3: Renewal | C3: --- | D3: Renewal Quotes | E3: 1 | G3: 5333 | H3: 5273 | I3: Reconciled within acceptable variance | J3: No cell at all | L3: 718 | O3: no step id assigned
A4: Home | B4: Renewal | C4: ?? | D4: Customer login in to portal Failure | H4: 848 | I4: No report data supplied | J4: No cell at all | L4: 165 | O4: no step id assigned
A5: Motor | B5: Acquisition | C5: A2.E1 | D5: This year retrieve (TYR) | H5: 46375 | I5: No report data supplied | J5: Yes - stub only | K5: 29 | L5: 11 | O5: empty | P5: 692
A6: Motor | B6: Acquisition | C6: A3.B1.1 | D6: Quote retrieved or iterated | E6: 1 | G6: 15231 | H6: 14919 | I6: Reconciled with Reasons supplied | J6: Yes - stub only | K6: 62 | L6: 44 | O6: empty | P6: 1292
A7: Motor | B7: Acquisition | C7: A3.B1.2 | D7: Purchase | E7: 1 | G7: 1485 | H7: 1507 | I7: Reconciled within acceptable variance | J7: Yes - stub only | K7: 63 | L7: 45 | O7: empty | P7: 1298
A8: Motor | B8: Acquisition | C8: A3.B1.O1 | D8: Abandoned or expired | H8: 13412 | I8: No report data supplied | J8: Yes - stub only | K8: 64 | L8: 46 | O8: empty | P8: 1304
A9: Motor | B9: Acquisition | C9: A3.E1 | D9: Outbound sales callback | H9: 24 | I9: No report data supplied | J9: Yes - stub only | K9: 36 | L9: 18 | O9: insert query | P9: 813
A10: Motor | B10: Acquisition | C10: A4b.O1 | D10: Not proceeded with | H10: 4780 | I10: No report data supplied | J10: Yes - stub only | K10: 42 | L10: 24 | O10: empty | P10: 960
A11: Motor | B11: Acquisition | C11: A6.B1 | D11: Document intake | H11: 1646 | I11: No report data supplied | J11: Yes - stub only | K11: 57 | L11: 39 | O11: empty | P11: 1226
A12: Motor | B12: Acquisition | C12: A6.B1.1 | D12: Document request issued | H12: 2580 | I12: No report data supplied | J12: Yes - stub only | K12: 78 | L12: 60 | O12: empty | P12: 1310
A13: Motor | B13: Acquisition | C13: A6.B1.4 | D13: Chase, first reminder | H13: 9662 | I13: No report data supplied | J13: Yes - stub only | K13: 80 | L13: 62 | O13: empty | P13: 1350
A14: Motor | B14: Acquisition | C14: A6.B1.6 | D14: Documents received and validated | H14: 1088 | I14: No report data supplied | J14: Yes - stub only | K14: 84 | L14: 66 | O14: empty | P14: 1484
A15: Motor | B15: Acquisition | C15: A6.B1.F1 | D15: Documents never submitted, policy at risk. Bites A5a customers hardest | H15: 1178 | I15: No report data supplied | J15: Yes - stub only | K15: 58 | L15: 40 | O15: empty | P15: 1232
A16: Motor | B16: Acquisition | C16: A6.F1 | D16: Chases before the customer submits, and documents never submitted | E16: 1 | G16: 1178 | H16: 1178 | I16: Reconciled | J16: No cell at all | L16: 37 | O16: insert query | P16: 1160
A17: Motor | B17: Acquisition | C17: A7.B1 | D17: Cert and disc dispatch | H17: 3918 | I17: No report data supplied | J17: Yes - stub only | K17: 61 | L17: 43 | O17: empty | P17: 1286
A18: Motor | B18: Acquisition | C18: A7.B1.4 | D18: Non-arrival chase, inbound | H18: 253 | I18: No report data supplied | J18: Yes - stub only | K18: 88 | L18: 70 | O18: empty | P18: 1611
A19: Motor | B19: Acquisition | C19: A7.F1 | D19: Non-arrival, and time taken to receive | H19: 28 | I19: No report data supplied | J19: Yes - stub only | K19: 60 | L19: 42 | O19: empty | P19: 1280
A20: Motor | B20: Arrears | C20: ARR.1 | D20: Missed payment detected | H20: 1650 | I20: No report data supplied | J20: No cell at all | L20: 447 | O20: empty | P20: 6855
A21: Motor | B21: Arrears | C21: ARR.2 | D21: Arrears chase, automated | E21: 1 | H21: 1650 | I21: No report data supplied | J21: No cell at all | L21: 448 | O21: empty | P21: 6856
A22: Motor | B22: Arrears | C22: ARR.3 | D22: Loan defaults, arrears not cleared | H22: 274 | I22: No report data supplied | J22: No cell at all | L22: 452 | O22: empty | P22: 6858
A23: Motor | B23: Arrears | C23: ARR.O1 | D23: Arrears cleared | H23: 1376 | I23: No report data supplied | J23: No cell at all | L23: 449 | O23: empty | P23: 6857
A24: Motor | B24: Arrears | C24: ARR.O2 | D24: Escalation to forced cancellation | E24: 1 | H24: 5 | I24: No report data supplied | J24: No cell at all | L24: 457 | O24: empty | P24: 6859
A25: Motor | B25: Cancellation | C25: C1a | D25: Customer asks to cancel | E25: 1 | H25: 1676 | I25: No report data supplied | J25: No cell at all | L25: 431 | O25: empty | P25: 6771
A26: Motor | B26: Cancellation | C26: C1a.F1 | D26: Call wait time, or fails to make contact | H26: 353 | I26: No report data supplied | J26: No cell at all | L26: 432 | O26: empty | P26: 6772
A27: Motor | B27: Cancellation | C27: C2 | D27: Document chase, reminder | H27: 2580 | I27: No report data supplied | J27: No cell at all | L27: 435 | O27: empty | P27: 6773
A28: Motor | B28: Cancellation | C28: C3 | D28: Document chase, escalation | E28: 1 | H28: 1178 | I28: No report data supplied | J28: No cell at all | L28: 436 | O28: empty | P28: 6774
A29: Motor | B29: Cancellation | C29: C5 | D29: Cancellation processed | E29: 1 | H29: 1382 | I29: No report data supplied | J29: No cell at all | L29: 440 | O29: empty | P29: 6853
A30: Motor | B30: Cancellation | C30: C6 | D30: Cancellation confirmation sent | E30: 1 | H30: 1382 | I30: No report data supplied | J30: No cell at all | L30: 443 | O30: empty | P30: 6854
A31: Motor | B31: Claims | C31: CL1a | D31: Motor claim reported | E31: 1 | H31: 808 | I31: No report data supplied | J31: No cell at all | L31: 468 | O31: empty | P31: 6860
A32: Motor | B32: Doc Request | C32: D.V1 | D32: Replacement cert and disc | H32: 151 | I32: No report data supplied | J32: No cell at all | L32: 486 | O32: empty | P32: 6916
A33: Motor | B33: Doc Request | C33: D1 | D33: Customer rings and asks for a document | E33: 1 | H33: 1445 | I33: No report data supplied | J33: No cell at all | L33: 479 | O33: empty | P33: 6861
A34: Motor | B34: Doc Request | C34: D1.F1 | D34: Call wait time, or fails to make contact | H34: 245 | I34: No report data supplied | J34: No cell at all | L34: 480 | M34: XX - Episode Reconciliation - Gaps.html, cell 74 | N34: Yes - covered by another step cell, see pointer comment | O34: empty | P34: 6862
A35: Motor | B35: Doc Request | C35: D2 | D35: Agent locates and sends the document | E35: 1 | H35: 483 | I35: No report data supplied | J35: No cell at all | L35: 481 | M35: XX - Episode Reconciliation - Gaps.html, cell 76 | N35: Yes - count query added under the step marker | O35: insert query | P35: 6868
A36: Motor | B36: Doc Request | C36: D3.F1 | D36: Non-arrival, and the customer rings again | H36: 134 | I36: No report data supplied | J36: No cell at all | L36: 484 | M36: XX - Episode Reconciliation - Gaps.html, cell 78 | N36: Yes - covered by another step cell, see pointer comment | O36: empty | P36: 6910
A37: Motor | B37: Doc Request | C37: D3.F2 | D37: The same document downloaded again and again | H37: 984 | I37: No report data supplied | J37: No cell at all | L37: 485 | M37: XX - Episode Reconciliation - Gaps.html, cell 79 | N37: Yes - covered by another step cell, see pointer comment | O37: empty | P37: 6913
A38: Home | B38: Acquisition | C38: HA0 | D38: Straight into the CALL CENTRE | E38: 1 | G38: 921 | H38: 924 | I38: Reconciled within acceptable variance | J38: Yes - stub only | K38: 141 | L38: 228 | O38: count query | P38: 3368
A39: Home | B39: Acquisition | C39: HA0.F1 | D39: Call wait time, or fails to make contact | E39: 1 | H39: 123 | I39: No report data supplied | J39: Yes - stub only | K39: 142 | L39: 229 | O39: count query | P39: 3374
A40: Home | B40: Acquisition | C40: HA1 | D40: Quote initiated ONLINE | E40: 1 | G40: 15019 | H40: 15398 | I40: Reconciled | J40: Yes - stub only | K40: 138 | L40: 224 | O40: insert query | P40: 3229
A41: Home | B41: Acquisition | C41: HA1.E2 | D41: Outbound sales callback | E41: 1 | H41: 5 | I41: No report data supplied | J41: Yes - stub only | K41: 140 | L41: 226 | O41: insert query | P41: 3319
A42: Home | B42: Acquisition | C42: HA2 | D42: Quote progressed | E42: 1 | H42: 8798 | I42: No report data supplied | J42: Yes - stub only | K42: 143 | L42: 230 | O42: insert query | P42: 3379
A43: Home | B43: Acquisition | C43: HA2.E1 | D43: TYR Campaign | H43: 2814 | I43: No report data supplied | J43: Yes - stub only | K43: 145 | L43: 232 | O43: empty | P43: 3446
A44: Home | B44: Acquisition | C44: HA2.F1 | D44: Drop off before completing the details | H44: 4100 | I44: No report data supplied | J44: Yes - stub only | K44: 144 | L44: 231 | O44: insert query | P44: 3412
A45: Home | B45: Acquisition | C45: HA3 | D45: Customer gets a price | H45: 8452 | I45: No report data supplied | J45: Yes - stub only | K45: 146 | L45: 233 | O45: insert query | P45: 3450
A46: Home | B46: Acquisition | C46: HA3.F1 | D46: No price returned, told to call us | H46: 3531 | I46: No report data supplied | J46: Yes - stub only | K46: 146 | L46: 236 | M46: XX - Episode Reconciliation - Gaps.html, cell 27 | N46: Yes - count query added under the step marker | O46: insert query | P46: 3485
A47: Home | B47: Acquisition | C47: HA4.F1 | D47: Web assist: starts online, then calls to complete | E47: 1 | F47: 1 | G47: 23 | H47: 23 | I47: Reconciled | J47: Yes - stub only | K47: 149 | L47: 239 | O47: empty | P47: 3597
A48: Home | B48: Acquisition | C48: HA4a | D48: Customer buys ONLINE | E48: 1 | G48: 632 | H48: 637 | I48: Reconciled within acceptable variance | J48: Yes - stub only | K48: 147 | L48: 237 | O48: insert query | P48: 3527
A49: Home | B49: Acquisition | C49: HA4b | D49: Agent quotes and converts on the CALL | E49: 1 | G49: 466 | H49: 466 | I49: Reconciled | J49: Yes - stub only | K49: 148 | L49: 238 | O49: insert query | P49: 3561
A50: Home | B50: Acquisition | C50: HA4b.O1 | D50: Not proceeded with | E50: 1 | H50: 435 | I50: No report data supplied | J50: Yes - stub only | K50: 149 | L50: 240 | O50: empty | P50: 3598
A51: Home | B51: Acquisition | C51: HA5 | D51: Payment successful | F51: 1 | H51: 644 | I51: No report data supplied | J51: Yes - stub only | K51: 150 | L51: 241 | O51: insert query | P51: 3602
A52: Home | B52: Acquisition | C52: HA5.1 | D52: Terms of business sent | H52: 1053 | I52: No report data supplied | J52: Yes - stub only | K52: 154 | L52: 247 | O52: insert query | P52: 3708
A53: Home | B53: Acquisition | C53: HA5.B1 | D53: Payment and loan setup | H53: 197 | I53: No report data supplied | J53: Yes - stub only | K53: 152 | L53: 243 | O53: insert query | P53: 3672
A54: Home | B54: Acquisition | C54: HA5.F1 | D54: Payment attempted with friction | H54: 68 | I54: No report data supplied | J54: Yes - stub only | K54: 151 | L54: 242 | O54: insert query | P54: 3638
A55: Home | B55: Acquisition | C55: HA6 | D55: Documents requested | E55: 1 | H55: 322 | I55: No report data supplied | J55: Yes - stub only | K55: 155 | L55: 248 | M55: XX - Episode Reconciliation - Gaps.html, cell 28 | N55: Yes - count query added as an alternative cell, marker already had SQL | O55: insert query | P55: 3752
A56: Home | B56: Acquisition | C56: HA6.B1 | D56: Document intake | E56: 1 | H56: 91 | I56: No report data supplied | J56: Yes - stub only | K56: 156 | L56: 250 | O56: empty | P56: 3862
A57: Home | B57: Acquisition | C57: HA6.B1.1 | D57: Document request issued | H57: 322 | I57: No report data supplied | J57: Yes - stub only | K57: 160 | L57: 267 | O57: empty | P57: 4004
A58: Home | B58: Acquisition | C58: HA6.B1.2 | D58: Customer submits documents | H58: 91 | I58: No report data supplied | J58: Yes - stub only | K58: 160 | L58: 268 | M58: XX - Episode Reconciliation - Gaps.html, cell 30 | N58: Yes - count query added under the step marker | O58: insert query | P58: 4005
A59: Home | B59: Acquisition | C59: HA6.B1.3 | D59: Documents validated | H59: 64 | I59: No report data supplied | J59: Yes - stub only | K59: 160 | L59: 271 | M59: XX - Episode Reconciliation - Gaps.html, cell 34 | N59: Yes - count query added under the step marker | O59: insert query | P59: 4155
A60: Home | B60: Acquisition | C60: HA6.B1.4 | D60: Chase, first reminder | H60: 282 | I60: No report data supplied | J60: Yes - stub only | K60: 160 | L60: 269 | M60: XX - Episode Reconciliation - Gaps.html, cell 31 | N60: Yes - count query added under the step marker | O60: insert query | P60: 4042
A61: Home | B61: Acquisition | C61: HA6.B1.6 | D61: Documents received and validated | H61: 64 | I61: No report data supplied | J61: Yes - stub only | K61: 160 | L61: 273 | O61: empty | P61: 4247
A62: Home | B62: Acquisition | C62: HA6.B1.F1 | D62: Documents never submitted, policy at risk of cancellation | H62: 131 | I62: No report data supplied | J62: Yes - stub only | K62: 156 | L62: 251 | O62: empty | P62: 3863
A63: Home | B63: Acquisition | C63: HA6.B1.O1 | D63: Cancellation, non-receipt | H63: 6 | I63: No report data supplied | J63: Yes - stub only | K63: 160 | L63: 272 | M63: XX - Episode Reconciliation - Gaps.html, cell 35 | N63: Yes - count query added under the step marker | O63: insert query | P63: 4193
A64: Home | B64: Acquisition | C64: HA6.F1 | D64: Number of chases before the customer submits | E64: 1 | H64: 243 | I64: No report data supplied | J64: Yes - stub only | K64: 156 | L64: 249 | M64: XX - Episode Reconciliation - Gaps.html, cell 29 | N64: Yes - count query added under the step marker | O64: insert query | P64: 3813
A65: Home | B65: Acquisition | C65: HA7 | D65: Policy documents dispatched | H65: 1108 | I65: No report data supplied | J65: Yes - stub only | K65: 157 | L65: 252 | O65: insert query | P65: 3867
A66: Home | B66: Acquisition | C66: HA7.B1 | D66: Policy fulfilment | H66: 1108 | I66: No report data supplied | J66: Yes - stub only | K66: 158 | L66: 253 | O66: empty | P66: 3911
A67: Home | B67: Acquisition | C67: HA7.B1.1 | D67: Policy documents dispatched | H67: 1108 | I67: No report data supplied | J67: Yes - stub only | K67: 158 | L67: 255 | O67: empty | P67: 3912
A68: Home | B68: Acquisition | C68: HA7.B1.1 | D68: Policy documents dispatched | H68: 1108 | I68: No report data supplied | J68: Yes - stub only | K68: 158 | L68: 274 | O68: empty | P68: 3912
A69: Home | B69: Acquisition | C69: HA7.B1.2 | D69: Document pack dispatched | H69: 1108 | I69: No report data supplied | J69: Yes - stub only | K69: 159 | L69: 256 | O69: insert query | P69: 3916
A70: Home | B70: Acquisition | C70: HA7.B1.2 | D70: Document pack dispatched | H70: 1108 | I70: No report data supplied | J70: Yes - stub only | K70: 159 | L70: 275 | O70: insert query | P70: 3916
A71: Home | B71: Acquisition | C71: HA7.B1.3 | D71: Customer receipt, implicit | H71: 1108 | I71: No report data supplied | J71: Yes - stub only | K71: 160 | L71: 276 | O71: empty | P71: 4250
A72: Home | B72: Acquisition | C72: HA7.B1.4 | D72: Non-arrival chase, inbound | H72: 0 | I72: No report data supplied | J72: Yes - stub only | K72: 160 | L72: 277 | O72: empty | P72: 4251
A73: Home | B73: Acquisition | C73: HA7.B1.5 | D73: Replacement requested | H73: 0 | I73: No report data supplied | J73: Yes - stub only | K73: 160 | L73: 278 | O73: empty | P73: 4252
A74: Home | B74: Arrears | C74: HARR.1 | D74: Missed payment detected | H74: 124 | I74: No report data supplied | J74: No cell at all | L74: 347 | O74: empty | P74: 6388
A75: Home | B75: Arrears | C75: HARR.2 | D75: Arrears chase | E75: 1 | H75: 124 | I75: No report data supplied | J75: No cell at all | L75: 348 | O75: empty | P75: 6389
A76: Home | B76: Arrears | C76: HARR.3 | D76: Loan defaults, arrears not cleared | H76: 19 | I76: No report data supplied | J76: No cell at all | L76: 352 | O76: empty | P76: 6391
A77: Home | B77: Arrears | C77: HARR.O1 | D77: Arrears cleared | H77: 105 | I77: No report data supplied | J77: No cell at all | L77: 349 | O77: empty | P77: 6390
A78: Home | B78: Arrears | C78: HARR.O2 | D78: Escalation to forced cancellation | E78: 1 | H78: 0 | I78: No report data supplied | J78: No cell at all | L78: 357 | O78: empty | P78: 6392
A79: Home | B79: Cancellation | C79: HC1a | D79: Customer asks to cancel | H79: 21 | I79: No report data supplied | J79: No cell at all | L79: 324 | M79: XX - Episode Reconciliation - Gaps.html, cell 62 | N79: Yes - count query added as an alternative cell, marker already had SQL | O79: other SQL, no insert | P79: 6187
A80: Home | B80: Cancellation | C80: HC1a.F1 | D80: No retention or save attempt anywhere | H80: 0 | I80: No report data supplied | J80: No cell at all | L80: 325 | O80: other SQL, no insert | P80: 6207
A81: Home | B81: Cancellation | C81: HC1b.F1 | D81: The framework says NCT failure | H81: 0 | I81: No report data supplied | J81: No cell at all | L81: 327 | M81: XX - Episode Reconciliation - Gaps.html, cell 63 | N81: Yes - count query added under the step marker | O81: other SQL, no insert | P81: 6218
A82: Home | B82: Cancellation | C82: HC2 | D82: Document chase, reminder | H82: 31 | I82: No report data supplied | J82: No cell at all | L82: 328 | M82: XX - Episode Reconciliation - Gaps.html, cell 64 | N82: Yes - count query added as an alternative cell, marker already had SQL | O82: insert query | P82: 6229
A83: Home | B83: Cancellation | C83: HC3 | D83: Document chase, escalation | H83: 22 | I83: No report data supplied | J83: No cell at all | L83: 329 | M83: XX - Episode Reconciliation - Gaps.html, cell 65 | N83: Yes - count query added as an alternative cell, marker already had SQL | O83: insert query | P83: 6269
A84: Home | B84: Cancellation | C84: HC4 | D84: Final notice | E84: 1 | H84: 17 | I84: No report data supplied | J84: No cell at all | L84: 331 | M84: XX - Episode Reconciliation - Gaps.html, cell 66 | N84: Yes - count query added as an alternative cell, marker already had SQL | O84: insert query | P84: 6310
A85: Home | B85: Cancellation | C85: HC5 | D85: Cancellation processed | H85: 26 | I85: No report data supplied | J85: No cell at all | L85: 334 | M85: XX - Episode Reconciliation - Gaps.html, cell 67 | N85: Yes - count query added as an alternative cell, marker already had SQL | O85: insert query | P85: 6349
A86: Home | B86: Cancellation | C86: HC6 | D86: Cancellation confirmation sent | E86: 1 | H86: 26 | I86: No report data supplied | J86: No cell at all | L86: 335 | O86: empty | P86: 6387
A87: Home | B87: Claims | C87: HCL.O2 | D87: Policy ended | E87: 1 | H87: 5 | I87: No report data supplied | J87: No cell at all | L87: 371 | O87: empty | P87: 6397
A88: Home | B88: Claims | C88: HCL1a | D88: Home claim reported | E88: 1 | H88: 220 | I88: No report data supplied | J88: No cell at all | L88: 362 | O88: empty | P88: 6393
A89: Home | B89: Claims | C89: HCL1b | D89: Escape of water or emergency assistance | H89: 235 | I89: No report data supplied | J89: No cell at all | L89: 363 | O89: empty | P89: 6394
A90: Home | B90: Claims | C90: HCL1c | D90: Storm, flood or weather claim | H90: 350 | I90: No report data supplied | J90: No cell at all | L90: 364 | O90: empty | P90: 6395
A91: Home | B91: Claims | C91: HCL4 | D91: Policy continues with a claim on it | E91: 1 | H91: 215 | I91: No report data supplied | J91: No cell at all | L91: 368 | O91: empty | P91: 6396
A92: Home | B92: Doc Request | C92: HD1 | D92: Customer rings and asks for a document | E92: 1 | H92: 314 | I92: No report data supplied | J92: No cell at all | L92: 373 | M92: XX - Episode Reconciliation - Gaps.html, cell 72 | N92: Yes - count query added under the step marker | O92: other SQL, no insert | P92: 6401
A93: Home | B93: Doc Request | C93: HD1.F1 | D93: Call wait time, or fails to make contact | H93: 78 | I93: No report data supplied | J93: No cell at all | L93: 374 | M93: XX - Episode Reconciliation - Gaps.html, cell 74 | N93: Yes - count query added under the step marker | O93: insert query | P93: 6421
A94: Home | B94: Doc Request | C94: HD2 | D94: Agent locates and sends the document | E94: 1 | H94: 81 | I94: No report data supplied | J94: No cell at all | L94: 375 | M94: XX - Episode Reconciliation - Gaps.html, cell 75 | N94: Yes - count query added under the step marker | O94: insert query | P94: 6463
A95: Home | B95: Doc Request | C95: HD3.F1 | D95: Non-arrival, and the customer rings again | H95: 30 | I95: No report data supplied | J95: No cell at all | L95: 378 | M95: XX - Episode Reconciliation - Gaps.html, cell 78 | N95: Yes - count query added under the step marker | O95: insert query | P95: 6505
A96: Home | B96: Doc Request | C96: HD3.F2 | D96: The same document downloaded again and again | H96: 99 | I96: No report data supplied | J96: No cell at all | L96: 379 | M96: XX - Episode Reconciliation - Gaps.html, cell 79 | N96: Yes - count query added under the step marker | O96: insert query | P96: 6549
A97: Home | B97: Mta | C97: HM1 | D97: Customer contacts Chill with a change request | E97: 1 | H97: 757 | I97: No report data supplied | J97: No cell at all | L97: 282 | O97: empty | P97: 5567
A98: Home | B98: Mta | C98: HM1.F1 | D98: Call wait time, or fails to make contact | H98: 319 | I98: No report data supplied | J98: No cell at all | L98: 283 | O98: empty | P98: 5568
A99: Home | B99: Mta | C99: HM2 | D99: Agent quotes the new premium and fee | H99: 438 | I99: No report data supplied | J99: No cell at all | L99: 284 | O99: empty | P99: 5569
A100: Home | B100: Mta | C100: HM2.O1 | D100: Cancellation, declined or not proceeded with | H100: 109 | I100: No report data supplied | J100: No cell at all | L100: 286 | M100: XX - Episode Reconciliation - Gaps.html, cell 40 | N100: Yes - count query added as an alternative cell, marker already had SQL | O100: insert query | P100: 5570
...

Sheet Summary by Journey
A1: Product | B1: Journey | C1: Missing inserts | D1: of which Priority 1 | E1: Stub cell exists | F1: No cell at all
A2: Home | B2: Acquisition | C2: =COUNTIFS('Missing Inserts'!$A$2:$A$285,$A2,'Missing Inserts'!$B$2:$B$285,$B2) | D2: =COUNTIFS('Missing Inserts'!$A$2:$A$285,$A2,'Missing Inserts'!$B$2:$B$285,$B2,'Missing Inserts'!$E$2:$E$285,1) | E2: =COUNTIFS('Missing Inserts'!$A$2:$A$285,$A2,'Missing Inserts'!$B$2:$B$285,$B2,'Missing Inserts'!$J$2:$J$285,"Yes - stub only") | F2: =COUNTIFS('Missing Inserts'!$A$2:$A$285,$A2,'Missing Inserts'!$B$2:$B$285,$B2,'Missing Inserts'!$J$2:$J$285,"No cell at all")
A3: Home | B3: Arrears | C3: =COUNTIFS('Missing Inserts'!$A$2:$A$285,$A3,'Missing Inserts'!$B$2:$B$285,$B3) | D3: =COUNTIFS('Missing Inserts'!$A$2:$A$285,$A3,'Missing Inserts'!$B$2:$B$285,$B3,'Missing Inserts'!$E$2:$E$285,1) | E3: =COUNTIFS('Missing Inserts'!$A$2:$A$285,$A3,'Missing Inserts'!$B$2:$B$285,$B3,'Missing Inserts'!$J$2:$J$285,"Yes - stub only") | F3: =COUNTIFS('Missing Inserts'!$A$2:$A$285,$A3,'Missing Inserts'!$B$2:$B$285,$B3,'Missing Inserts'!$J$2:$J$285,"No cell at all")
A4: Home | B4: Cancellation | C4: =COUNTIFS('Missing Inserts'!$A$2:$A$285,$A4,'Missing Inserts'!$B$2:$B$285,$B4) | D4: =COUNTIFS('Missing Inserts'!$A$2:$A$285,$A4,'Missing Inserts'!$B$2:$B$285,$B4,'Missing Inserts'!$E$2:$E$285,1) | E4: =COUNTIFS('Missing Inserts'!$A$2:$A$285,$A4,'Missing Inserts'!$B$2:$B$285,$B4,'Missing Inserts'!$J$2:$J$285,"Yes - stub only") | F4: =COUNTIFS('Missing Inserts'!$A$2:$A$285,$A4,'Missing Inserts'!$B$2:$B$285,$B4,'Missing Inserts'!$J$2:$J$285,"No cell at all")
A5: Home | B5: Claims | C5: =COUNTIFS('Missing Inserts'!$A$2:$A$285,$A5,'Missing Inserts'!$B$2:$B$285,$B5) | D5: =COUNTIFS('Missing Inserts'!$A$2:$A$285,$A5,'Missing Inserts'!$B$2:$B$285,$B5,'Missing Inserts'!$E$2:$E$285,1) | E5: =COUNTIFS('Missing Inserts'!$A$2:$A$285,$A5,'Missing Inserts'!$B$2:$B$285,$B5,'Missing Inserts'!$J$2:$J$285,"Yes - stub only") | F5: =COUNTIFS('Missing Inserts'!$A$2:$A$285,$A5,'Missing Inserts'!$B$2:$B$285,$B5,'Missing Inserts'!$J$2:$J$285,"No cell at all")
A6: Home | B6: Doc Request | C6: =COUNTIFS('Missing Inserts'!$A$2:$A$285,$A6,'Missing Inserts'!$B$2:$B$285,$B6) | D6: =COUNTIFS('Missing Inserts'!$A$2:$A$285,$A6,'Missing Inserts'!$B$2:$B$285,$B6,'Missing Inserts'!$E$2:$E$285,1) | E6: =COUNTIFS('Missing Inserts'!$A$2:$A$285,$A6,'Missing Inserts'!$B$2:$B$285,$B6,'Missing Inserts'!$J$2:$J$285,"Yes - stub only") | F6: =COUNTIFS('Missing Inserts'!$A$2:$A$285,$A6,'Missing Inserts'!$B$2:$B$285,$B6,'Missing Inserts'!$J$2:$J$285,"No cell at all")
A7: Home | B7: Mta | C7: =COUNTIFS('Missing Inserts'!$A$2:$A$285,$A7,'Missing Inserts'!$B$2:$B$285,$B7) | D7: =COUNTIFS('Missing Inserts'!$A$2:$A$285,$A7,'Missing Inserts'!$B$2:$B$285,$B7,'Missing Inserts'!$E$2:$E$285,1) | E7: =COUNTIFS('Missing Inserts'!$A$2:$A$285,$A7,'Missing Inserts'!$B$2:$B$285,$B7,'Missing Inserts'!$J$2:$J$285,"Yes - stub only") | F7: =COUNTIFS('Missing Inserts'!$A$2:$A$285,$A7,'Missing Inserts'!$B$2:$B$285,$B7,'Missing Inserts'!$J$2:$J$285,"No cell at all")
A8: Home | B8: Renewal | C8: =COUNTIFS('Missing Inserts'!$A$2:$A$285,$A8,'Missing Inserts'!$B$2:$B$285,$B8) | D8: =COUNTIFS('Missing Inserts'!$A$2:$A$285,$A8,'Missing Inserts'!$B$2:$B$285,$B8,'Missing Inserts'!$E$2:$E$285,1) | E8: =COUNTIFS('Missing Inserts'!$A$2:$A$285,$A8,'Missing Inserts'!$B$2:$B$285,$B8,'Missing Inserts'!$J$2:$J$285,"Yes - stub only") | F8: =COUNTIFS('Missing Inserts'!$A$2:$A$285,$A8,'Missing Inserts'!$B$2:$B$285,$B8,'Missing Inserts'!$J$2:$J$285,"No cell at all")
A9: Motor | B9: Acquisition | C9: =COUNTIFS('Missing Inserts'!$A$2:$A$285,$A9,'Missing Inserts'!$B$2:$B$285,$B9) | D9: =COUNTIFS('Missing Inserts'!$A$2:$A$285,$A9,'Missing Inserts'!$B$2:$B$285,$B9,'Missing Inserts'!$E$2:$E$285,1) | E9: =COUNTIFS('Missing Inserts'!$A$2:$A$285,$A9,'Missing Inserts'!$B$2:$B$285,$B9,'Missing Inserts'!$J$2:$J$285,"Yes - stub only") | F9: =COUNTIFS('Missing Inserts'!$A$2:$A$285,$A9,'Missing Inserts'!$B$2:$B$285,$B9,'Missing Inserts'!$J$2:$J$285,"No cell at all")
A10: Motor | B10: Arrears | C10: =COUNTIFS('Missing Inserts'!$A$2:$A$285,$A10,'Missing Inserts'!$B$2:$B$285,$B10) | D10: =COUNTIFS('Missing Inserts'!$A$2:$A$285,$A10,'Missing Inserts'!$B$2:$B$285,$B10,'Missing Inserts'!$E$2:$E$285,1) | E10: =COUNTIFS('Missing Inserts'!$A$2:$A$285,$A10,'Missing Inserts'!$B$2:$B$285,$B10,'Missing Inserts'!$J$2:$J$285,"Yes - stub only") | F10: =COUNTIFS('Missing Inserts'!$A$2:$A$285,$A10,'Missing Inserts'!$B$2:$B$285,$B10,'Missing Inserts'!$J$2:$J$285,"No cell at all")
A11: Motor | B11: Cancellation | C11: =COUNTIFS('Missing Inserts'!$A$2:$A$285,$A11,'Missing Inserts'!$B$2:$B$285,$B11) | D11: =COUNTIFS('Missing Inserts'!$A$2:$A$285,$A11,'Missing Inserts'!$B$2:$B$285,$B11,'Missing Inserts'!$E$2:$E$285,1) | E11: =COUNTIFS('Missing Inserts'!$A$2:$A$285,$A11,'Missing Inserts'!$B$2:$B$285,$B11,'Missing Inserts'!$J$2:$J$285,"Yes - stub only") | F11: =COUNTIFS('Missing Inserts'!$A$2:$A$285,$A11,'Missing Inserts'!$B$2:$B$285,$B11,'Missing Inserts'!$J$2:$J$285,"No cell at all")
A12: Motor | B12: Claims | C12: =COUNTIFS('Missing Inserts'!$A$2:$A$285,$A12,'Missing Inserts'!$B$2:$B$285,$B12) | D12: =COUNTIFS('Missing Inserts'!$A$2:$A$285,$A12,'Missing Inserts'!$B$2:$B$285,$B12,'Missing Inserts'!$E$2:$E$285,1) | E12: =COUNTIFS('Missing Inserts'!$A$2:$A$285,$A12,'Missing Inserts'!$B$2:$B$285,$B12,'Missing Inserts'!$J$2:$J$285,"Yes - stub only") | F12: =COUNTIFS('Missing Inserts'!$A$2:$A$285,$A12,'Missing Inserts'!$B$2:$B$285,$B12,'Missing Inserts'!$J$2:$J$285,"No cell at all")
A13: Motor | B13: Doc Request | C13: =COUNTIFS('Missing Inserts'!$A$2:$A$285,$A13,'Missing Inserts'!$B$2:$B$285,$B13) | D13: =COUNTIFS('Missing Inserts'!$A$2:$A$285,$A13,'Missing Inserts'!$B$2:$B$285,$B13,'Missing Inserts'!$E$2:$E$285,1) | E13: =COUNTIFS('Missing Inserts'!$A$2:$A$285,$A13,'Missing Inserts'!$B$2:$B$285,$B13,'Missing Inserts'!$J$2:$J$285,"Yes - stub only") | F13: =COUNTIFS('Missing Inserts'!$A$2:$A$285,$A13,'Missing Inserts'!$B$2:$B$285,$B13,'Missing Inserts'!$J$2:$J$285,"No cell at all")
... A24: Van | B24: Renewal | C24: =COUNTIFS('Missing Inserts'!$A$2:$A$285,$A24,'Missing Inserts'!$B$2:$B$285,$B24) | D24: =COUNTIFS('Missing Inserts'!$A$2:$A$285,$A24,'Missing Inserts'!$B$2:$B$285,$B24,'Missing Inserts'!$E$2:$E$285,1) | E24: =COUNTIFS('Missing Inserts'!$A$2:$A$285,$A24,'Missing Inserts'!$B$2:$B$285,$B24,'Missing Inserts'!$J$2:$J$285,"Yes - stub only") | F24: =COUNTIFS('Missing Inserts'!$A$2:$A$285,$A24,'Missing Inserts'!$B$2:$B$285,$B24,'Missing Inserts'!$J$2:$J$285,"No cell at all")
B25: TOTAL | C25: =SUM(C2:C24) | D25: =SUM(D2:D24) | E25: =SUM(E2:E24) | F25: =SUM(F2:F24)
A27: Scope: the 359 rows on "Reconciliation Request" that carry a numeric Fabric Volume. 289 have no matching INSERT in 03 - Populate Episode Event Stream.py; 70 do. Coverage was matched on the EventTypeId literal inside each INSERT (e.g. 'A1'), cross-checked against the --step_id cell markers. step_ids are product-prefixed so there are no cross-product collisions. Rows whose Fabric Volume is text ("-", "placeholder", "12 / 751") are excluded - 36 of them.

Sheet Code status summary
A1: Product | B1: Journey | C1: Total steps | D1: insert query | E1: count query | F1: other SQL, no insert | G1: empty
A2: Motor | B2: Acquisition | C2: 41 | D2: 28 | E2: 0 | F2: 0 | G2: 13
A3: Motor | B3: Arrears | C3: 5 | D3: 0 | E3: 0 | F3: 0 | G3: 5
A4: Motor | B4: Cancellation | C4: 7 | D4: 1 | E4: 0 | F4: 0 | G4: 6
A5: Motor | B5: Claims | C5: 1 | D5: 0 | E5: 0 | F5: 0 | G5: 1
A6: Motor | B6: Doc Request | C6: 6 | D6: 1 | E6: 0 | F6: 0 | G6: 5
A7: Motor | B7: Mta | C7: 17 | D7: 5 | E7: 0 | F7: 0 | G7: 12
A8: Motor | B8: Renewal | C8: 55 | D8: 38 | E8: 1 | F8: 1 | G8: 15
A9: Home | B9: Acquisition | C9: 37 | D9: 22 | E9: 3 | F9: 0 | G9: 12
A10: Home | B10: Arrears | C10: 5 | D10: 0 | E10: 0 | F10: 0 | G10: 5
A11: Home | B11: Cancellation | C11: 8 | D11: 4 | E11: 0 | F11: 3 | G11: 1
A12: Home | B12: Claims | C12: 5 | D12: 0 | E12: 0 | F12: 0 | G12: 5
A13: Home | B13: Doc Request | C13: 5 | D13: 4 | E13: 0 | F13: 1 | G13: 0
... A24: Travel | B24: Renewal | C24: 3 | D24: 0 | E24: 0 | F24: 0 | G24: 3
A25: TOTAL | C25: 363 | D25: 179 | E25: 7 | F25: 8 | G25: 169

Sheet Skipped conversions
A1: step_id | B1: Line in code | C1: Why it was left as it is
A2: HA0 | B2: 3094 | C2: It reads stg.A0_MFQ_genesys_link, which is built filtered to queueName = 'INBOUND_SALES_MOTOR', so there is no Home population and no Home equivalent staging table in the notebook.
A3: HA0.F1 | B3: 3100 | C3: It reads stg.HA0F1_genesys_inbound_call_duration_summary, which is never created anywhere in the notebook, so its columns cannot be relied on.
A4: HA1.F1 | B4: 3082 | C4: The step text is about outbound campaigns sent to quotes that never got a price but the query is an anti join that returns HFQ quotes with no campaign row at all and never tests for a price, so the step and the query disagree about what is being measured.
A5: HC1a | B5: 4420 | C5: The only date column the notebook ever names on edw.tbl_fact_policy_mtc is EffectiveDate, which is pinned to the single snapshot date 2026-07-31, so there is no event timestamp to use.
A6: HC1a.F1 | B6: 4440 | C6: The cell is an exploratory select star with no grain, no timestamp and a volume of zero rows.
A7: HC1b.F1 | B7: 4451 | C7: The same exploratory select star as HC1a.F1, with no grain, no timestamp and a volume of zero rows.
A8: HD1 | B8: 4546 | C8: The step is the inbound call asking for a document but the query counts documents emailed or transmitted, which is exactly what HD2 already measures, so the step id and the query disagree.
A9: HM4.B1.1 | B9: 4220 | C9: The cell holds two competing queries with the author's own results of 0 and 28 pencilled against them, so it is an investigation note and there is no single query that defines the step.
A10: HR2.B1.2 | B10: 3931 | C10: This is an exploratory select * with a limit 100 and the cell itself says the record to pick for the event stream has not been decided, so there is no clear grain to insert.
A11: R3b.F1 | B11: 2024 | C11: The cell holds only the table name stg.R0_genesys_derived_data with no select, filters or grain, so there is nothing to convert.
A12: RO.F2 | B12: 1638 | C12: The product is not given so PolicyTypeGroup cannot be set, and stg.motorclaims is not built anywhere in the notebook, its only date column ClaimDate being an integer in yyyymmdd form rather than a timestamp.
A13: TA3a | B13: 6106 | C13: The cell contains only a note about the number covering both acquisition and renewal plus a stray group by line, so there is no query to convert.
... A16: VR3b | B16: 5086 | C16: The query counts policies with a receipt document emailed or transmitted, which is not a measure of renewing on an inbound call, and the notebook itself flags the cell as not enough volume.

Sheet Possible double counts
A1: Cluster | B1: Product | C1: Journey | D1: step_id | E1: Role | F1: Step description | G1: Fabric volume | H1: Code status | I1: Why it is flagged
A2: 1 | B2: Home | C2: Acquisition | D2: HA6 | E2: container | F2: Documents requested | G2: 322 | H2: insert query | I2: ancestor and same volume
A3: 1 | B3: Home | C3: Acquisition | D3: HA6.B1.1 | E3: sub-step | F3: Document request issued | G3: 322 | H3: empty | I3: ancestor and same volume
A4: 2 | B4: Home | C4: Acquisition | D4: HA7 | E4: container | F4: Policy documents dispatched | G4: 1108 | H4: insert query | I4: ancestor and same volume; ancestor, same wording and same volume
A5: 2 | B5: Home | C5: Acquisition | D5: HA7.B1 | E5: container | F5: Policy fulfilment | G5: 1108 | H5: empty | I5: ancestor and same volume; ancestor, same wording and same volume
A6: 2 | B6: Home | C6: Acquisition | D6: HA7.B1.1 | E6: sub-step | F6: Policy documents dispatched | G6: 1108 | H6: empty | I6: ancestor and same volume; ancestor, same wording and same volume
A7: 2 | B7: Home | C7: Acquisition | D7: HA7.B1.2 | E7: sub-step | F7: Document pack dispatched | G7: 1108 | H7: insert query | I7: ancestor and same volume; ancestor, same wording and same volume
A8: 2 | B8: Home | C8: Acquisition | D8: HA7.B1.3 | E8: sub-step | F8: Customer receipt, implicit | G8: 1108 | H8: empty | I8: ancestor and same volume; ancestor, same wording and same volume
A9: 3 | B9: Home | C9: Acquisition | D9: HA6.B1 | E9: container | F9: Document intake | G9: 91 | H9: empty | I9: ancestor and same volume
A10: 3 | B10: Home | C10: Acquisition | D10: HA6.B1.2 | E10: sub-step | F10: Customer submits documents | G10: 91 | H10: insert query | I10: ancestor and same volume
A11: 4 | B11: Home | C11: Cancellation | D11: HC.IN1 | E11: sub-step | F11: Upstream feed: Acquisition | H11: not in code | I11: same wording
A12: 4 | B12: Home | C12: Cancellation | D12: HC.IN2 | E12: sub-step | F12: Upstream feed: Acquisition | H12: not in code | I12: same wording
A13: 5 | B13: Home | C13: Cancellation | D13: HC.IN3 | E13: sub-step | F13: Upstream feed: Renewal | H13: not in code | I13: same wording
A14: 5 | B14: Home | C14: Cancellation | D14: HC.IN4 | E14: sub-step | F14: Upstream feed: Renewal | H14: not in code | I14: same wording
A15: 6 | B15: Home | C15: Mta | D15: HM.V6 | E15: sub-step | F15: Payment schedule change | H15: not in code | I15: same wording
A16: 6 | B16: Home | C16: Mta | D16: HM4b.B1 | E16: sub-step | F16: Payment schedule change | H16: not in code | I16: same wording
A17: 7 | B17: Home | C17: Renewal | D17: HR6 | E17: container | F17: Renewal documents dispatched | G17: 4980 | H17: empty | I17: ancestor and same volume
A18: 7 | B18: Home | C18: Renewal | D18: HR6.B1 | E18: container | F18: Policy fulfilment | G18: 4980 | H18: insert query | I18: ancestor and same volume
A19: 7 | B19: Home | C19: Renewal | D19: HR6.B1.1 | E19: sub-step | F19: Policy documents dispatched | G19: 4980 | H19: empty | I19: ancestor and same volume
A20: 8 | B20: Home | C20: Renewal | D20: HR2.B1 | E20: container | F20: Online re-quote for another price | G20: 252 | H20: insert query | I20: ancestor and same volume
A21: 8 | B21: Home | C21: Renewal | D21: HR2.B1.1 | E21: sub-step | F21: Re-quote started from the renewal price | G21: 252 | H21: insert query | I21: ancestor and same volume
A22: 9 | B22: Home | C22: Renewal | D22: HR3.B1 | E22: container | F22: This year lapsed | G22: 1243 | H22: insert query | I22: ancestor and same volume
A23: 9 | B23: Home | C23: Renewal | D23: HR3.B1.2 | E23: sub-step | F23: Lapse CRM sequence runs | G23: 1243 | H23: empty | I23: ancestor and same volume
A24: 10 | B24: Home | C24: Renewal | D24: HR4.B2 | E24: container | F24: Documents requested | G24: 481 | H24: insert query | I24: ancestor and same volume
A25: 10 | B25: Home | C25: Renewal | D25: HR4.B2.4 | E25: sub-step | F25: Chase, first reminder | G25: 481 | H25: empty | I25: ancestor and same volume
A26: 10 | B26: Home | C26: Renewal | D26: HR4.B2.F1 | E26: sub-step | F26: Chases before the customer submits, and documents never submitted | G26: 481 | H26: empty | I26: ancestor and same volume
A27: 11 | B27: Motor | C27: Acquisition | D27: A6 | E27: container | F27: Documents requested | G27: 2580 | H27: insert query | I27: ancestor and same volume
A28: 11 | B28: Motor | C28: Acquisition | D28: A6.B1.1 | E28: sub-step | F28: Document request issued | G28: 2580 | H28: empty | I28: ancestor and same volume
... A35: 14 | B35: Motor | C35: Acquisition | D35: A7.B1.1 | E35: sub-step | F35: Cert and disc dispatched | G35: 3918 | H35: insert query | I35: ancestor and same volume
A36: 15 | B36: Motor | C36: Acquisition | D36: A5.B1.5 | E36: sub-step | F36: Payment confirmed on the loan path | H36: not in code | I36: same wording
A37: 15 | B37: Motor | C37: Acquisition | D37: A5.B1.PC5 | E37: sub-step | F37: Payment confirmed on the loan path | H37: not in code | I37: same wording
A38: 16 | B38: Motor | C38: Mta | D38: M.V6 | E38: sub-step | F38: Payment schedule change | H38: not in code | I38: same wording
A39: 16 | B39: Motor | C39: Mta | D39: M4b.B1 | E39: sub-step | F39: Payment schedule change | H39: not in code | I39: same wording
A40: 17 | B40: Motor | C40: Renewal | D40: R6 | E40: container | F40: Cert and disc sent | G40: 11559 | H40: insert query | I40: ancestor and same volume
A41: 17 | B41: Motor | C41: Renewal | D41: R6.B1 | E41: container | F41: Cert and disc dispatch | G41: 11559 | H41: empty | I41: ancestor and same volume
A42: 17 | B42: Motor | C42: Renewal | D42: R6.B1.1 | E42: sub-step | F42: Cert and disc dispatched | G42: 11559 | H42: empty | I42: ancestor and same volume
A43: 18 | B43: Motor | C43: Renewal | D43: R3.B1 | E43: container | F43: This year lapsed | G43: 1729 | H43: insert query | I43: ancestor and same volume
A44: 18 | B44: Motor | C44: Renewal | D44: R3.B1.2 | E44: sub-step | F44: Lapse CRM sequence runs | G44: 1729 | H44: insert query | I44: ancestor and same volume
A45: 19 | B45: Van | C45: Acquisition | D45: VA6.B1 | E45: container | F45: Document intake | G45: 266 | H45: empty | I45: ancestor and same volume
A46: 19 | B46: Van | C46: Acquisition | D46: VA6.B1.2 | E46: sub-step | F46: Customer submits documents | G46: 266 | H46: empty | I46: ancestor and same volume
A47: 20 | B47: Van | C47: Acquisition | D47: VA7.B1 | E47: container | F47: Cert and disc dispatch | G47: 17 | H47: empty | I47: ancestor and same volume
A48: 20 | B48: Van | C48: Acquisition | D48: VA7.B1.5 | E48: sub-step | F48: Replacement requested | G48: 17 | H48: insert query | I48: ancestor and same volume
A49: 21 | B49: Van | C49: Cancellation | D49: VC.IN1 | E49: sub-step | F49: Upstream feed: Acquisition | H49: not in code | I49: same wording
A50: 21 | B50: Van | C50: Cancellation | D50: VC.IN2 | E50: sub-step | F50: Upstream feed: Acquisition | H50: not in code | I50: same wording
A51: 22 | B51: Van | C51: Cancellation | D51: VC.IN3 | E51: sub-step | F51: Upstream feed: Renewal | H51: not in code | I51: same wording
A52: 22 | B52: Van | C52: Cancellation | D52: VC.IN4 | E52: sub-step | F52: Upstream feed: Renewal | H52: not in code | I52: same wording
A53: 23 | B53: Van | C53: Mta | D53: VM.V6 | E53: sub-step | F53: Payment schedule change | H53: not in code | I53: same wording
A54: 23 | B54: Van | C54: Mta | D54: VM4b.B1 | E54: sub-step | F54: Payment schedule change | H54: not in code | I54: same wording
A55: 24 | B55: Van | C55: Mta | D55: VM3.B1 | E55: container | F55: Document intake | G55: 14 | H55: empty | I55: ancestor and same volume
A56: 24 | B56: Van | C56: Mta | D56: VM3.B1.2 | E56: sub-step | F56: Customer submits documents | G56: 14 | H56: empty | I56: ancestor and same volume
